Workbook
Name csDesignMode: 1
Name TaxTV: 10%
Name TaxXL: 5%
Name upsell: _xlfn.LAMBDA(_xlpm.HIGHER,_xlpm.LOWER,_xlpm.MARKUP, CEILING(CEILING(_xlpm.HIGHER-_xlpm.LOWER, 10000) + (CEILING(_xlpm.HIGHER-_xlpm.LOWER, 10000) * _xlpm.MARKUP), 10000))
Name upsell: _xlfn.LAMBDA(_xlpm.HIGHER,_xlpm.LOWER,_xlpm.MARKUP, CEILING(CEILING(_xlpm.HIGHER-_xlpm.LOWER, 10000) + (CEILING(_xlpm.HIGHER-_xlpm.LOWER, 10000) * _xlpm.MARKUP), 10000))
Name zone_saisie: #REF!,#REF!,#REF!,#REF!,#REF!
Name zone_saisie: #REF!,#REF!,#REF!,#REF!,#REF!
Name zone_saisie: #REF!,#REF!,#REF!,#REF!,#REF!

Sheet 6. Rate Simulation
A2: The Anvaya Beach Resort Bali | H2: Isi besaran discount hanya pada bagian yang berwarna abu-abu Promo tidak harus diisi seluruhnya, sesuaikan dengan kebutuhan hotel (weekend offer & min stay bersifat optional)
A3: RATE STRUCTURE I RATE SIMULASI I format hitung budget Room OCC & Revenue - Santika Indonesia Hotels & Resorts
H6: Additional Disc : | I6: 0.03 | M6: Additional Disc : | N6: 0.08
C7: Online Travel Agent | H7: Brand.com
A8: Rate Structure | B8: Lowest Room Type Category | C8: Generic Promotion | H8: Publish Rate - Non member | M8: MyValue Rate
C9: Staycation Offer | D9: Flexible Staycation Offer | E9: EBO 60 | H9: =C9 -> Staycation Offer | I9: =D9 -> Flexible Staycation Offer | J9: =E9 -> EBO 60 | K9: =F9 -> 0 | L9: =G9 -> 0 | M9: =H9 -> Staycation Offer | N9: =I9 -> Flexible Staycation Offer | O9: =J9 -> EBO 60 | ... Q9: =L9 -> 0
C10: 0.32 | D10: 0.27 | E10: 0.35 | H10: =C10+$I$6 -> 0.35 | I10: =D10+$I$6 -> 0.3 | J10: =E10+$I$6 -> 0.38 | K10: =F10+$I$6 -> 0.03 | L10: =G10+$I$6 -> 0.03 | M10: =C10+$N$6 -> 0.4 | N10: =D10+$N$6 -> 0.35 | O10: =E10+$N$6 -> 0.43 | P10: =F10+$N$6 -> 0.08 | Q10: =G10+$N$6 -> 0.08
A11: Internet Rate / WIG Rate / BAR 1 | B11: ='7. Rate Strategy'!F16 -> 5850000 | C11: =$B11-($B11*C$10) -> 3978000 | D11: =$B11-($B11*D$10) -> 4270500 | E11: =$B11-($B11*E$10) -> 3802500 | F11: =$B11-($B11*F$10) -> 5850000 | G11: =$B11-($B11*G$10) -> 5850000 | H11: =$B11-($B11*H$10) -> 3802500 | I11: =$B11-($B11*I$10) -> 4095000 | J11: =$B11-($B11*J$10) -> 3627000 | ... Q11: =$B11-($B11*Q$10) -> 5382000
A12: Internet Rate / WIG Rate / BAR 2 | B12: ='7. Rate Strategy'!F17 -> 5525000 | C12: =$B12-($B12*C$10) -> 3757000 | D12: =$B12-($B12*D$10) -> 4033250 | E12: =$B12-($B12*E$10) -> 3591250 | F12: =$B12-($B12*F$10) -> 5525000 | G12: =$B12-($B12*G$10) -> 5525000 | H12: =$B12-($B12*H$10) -> 3591250 | I12: =$B12-($B12*I$10) -> 3867500 | J12: =$B12-($B12*J$10) -> 3425500 | ... Q12: =$B12-($B12*Q$10) -> 5083000
A13: Internet Rate / WIG Rate / BAR 3 | B13: ='7. Rate Strategy'!F18 -> 5200000 | C13: =$B13-($B13*C$10) -> 3536000 | D13: =$B13-($B13*D$10) -> 3796000 | E13: =$B13-($B13*E$10) -> 3380000 | F13: =$B13-($B13*F$10) -> 5200000 | G13: =$B13-($B13*G$10) -> 5200000 | H13: =$B13-($B13*H$10) -> 3380000 | I13: =$B13-($B13*I$10) -> 3640000 | J13: =$B13-($B13*J$10) -> 3224000 | ... Q13: =$B13-($B13*Q$10) -> 4784000
A14: Internet Rate / WIG Rate / BAR 4 | B14: ='7. Rate Strategy'!F19 -> 4875000 | C14: =$B14-($B14*C$10) -> 3315000 | D14: =$B14-($B14*D$10) -> 3558750 | E14: =$B14-($B14*E$10) -> 3168750 | F14: =$B14-($B14*F$10) -> 4875000 | G14: =$B14-($B14*G$10) -> 4875000 | H14: =$B14-($B14*H$10) -> 3168750 | I14: =$B14-($B14*I$10) -> 3412500 | J14: =$B14-($B14*J$10) -> 3022500 | ... Q14: =$B14-($B14*Q$10) -> 4485000
A15: Internet Rate / WIG Rate / BAR 5 | B15: ='7. Rate Strategy'!F20 -> 4550000 | C15: =$B15-($B15*C$10) -> 3094000 | D15: =$B15-($B15*D$10) -> 3321500 | E15: =$B15-($B15*E$10) -> 2957500 | F15: =$B15-($B15*F$10) -> 4550000 | G15: =$B15-($B15*G$10) -> 4550000 | H15: =$B15-($B15*H$10) -> 2957500 | I15: =$B15-($B15*I$10) -> 3185000 | J15: =$B15-($B15*J$10) -> 2821000 | ... Q15: =$B15-($B15*Q$10) -> 4186000
A16: Internet Rate / WIG Rate / BAR 6 | B16: ='7. Rate Strategy'!F21 -> 3900000 | C16: =$B16-($B16*C$10) -> 2652000 | D16: =$B16-($B16*D$10) -> 2847000 | E16: =$B16-($B16*E$10) -> 2535000 | F16: =$B16-($B16*F$10) -> 3900000 | G16: =$B16-($B16*G$10) -> 3900000 | H16: =$B16-($B16*H$10) -> 2535000 | I16: =$B16-($B16*I$10) -> 2730000 | J16: =$B16-($B16*J$10) -> 2418000 | ... Q16: =$B16-($B16*Q$10) -> 3588000
A17: Internet Rate / WIG Rate / BAR 7 | B17: ='7. Rate Strategy'!F22 -> 3737500 | C17: =$B17-($B17*C$10) -> 2541500 | D17: =$B17-($B17*D$10) -> 2728375 | E17: =$B17-($B17*E$10) -> 2429375 | F17: =$B17-($B17*F$10) -> 3737500 | G17: =$B17-($B17*G$10) -> 3737500 | H17: =$B17-($B17*H$10) -> 2429375 | I17: =$B17-($B17*I$10) -> 2616250 | J17: =$B17-($B17*J$10) -> 2317250 | ... Q17: =$B17-($B17*Q$10) -> 3438500
A18: Internet Rate / WIG Rate / BAR 8 | C18: =$B18-($B18*C$10) -> 0 | D18: =$B18-($B18*D$10) -> 0 | E18: =$B18-($B18*E$10) -> 0 | F18: =$B18-($B18*F$10) -> 0 | G18: =$B18-($B18*G$10) -> 0 | H18: =$B18-($B18*H$10) -> 0 | I18: =$B18-($B18*I$10) -> 0 | J18: =$B18-($B18*J$10) -> 0 | ... Q18: =$B18-($B18*Q$10) -> 0
A19: Internet Rate / WIG Rate / BAR 9 | C19: =$B19-($B19*C$10) -> 0 | D19: =$B19-($B19*D$10) -> 0 | E19: =$B19-($B19*E$10) -> 0 | F19: =$B19-($B19*F$10) -> 0 | G19: =$B19-($B19*G$10) -> 0 | H19: =$B19-($B19*H$10) -> 0 | I19: =$B19-($B19*I$10) -> 0 | J19: =$B19-($B19*J$10) -> 0 | ... Q19: =$B19-($B19*Q$10) -> 0
A20: Internet Rate / WIG Rate / BAR 10 | C20: =$B20-($B20*C$10) -> 0 | D20: =$B20-($B20*D$10) -> 0 | E20: =$B20-($B20*E$10) -> 0 | F20: =$B20-($B20*F$10) -> 0 | G20: =$B20-($B20*G$10) -> 0 | H20: =$B20-($B20*H$10) -> 0 | I20: =$B20-($B20*I$10) -> 0 | J20: =$B20-($B20*J$10) -> 0 | ... Q20: =$B20-($B20*Q$10) -> 0
A21: Internet Rate / WIG Rate / BAR 11 | C21: =$B21-($B21*C$10) -> 0 | D21: =$B21-($B21*D$10) -> 0 | E21: =$B21-($B21*E$10) -> 0 | F21: =$B21-($B21*F$10) -> 0 | G21: =$B21-($B21*G$10) -> 0 | H21: =$B21-($B21*H$10) -> 0 | I21: =$B21-($B21*I$10) -> 0 | J21: =$B21-($B21*J$10) -> 0 | ... Q21: =$B21-($B21*Q$10) -> 0
A22: Bottom Online BAR Rate | B22: =B17 -> 3737500 | C22: =C17 -> 2541500 | D22: =D17 -> 2728375 | E22: =E17 -> 2429375 | F22: =F17 -> 3737500 | G22: =G17 -> 3737500 | H22: =H17 -> 2429375 | I22: =I17 -> 2616250 | ... P22: =P17 -> 3438500 | Q22: =$B20-($B20*Q$10) -> 0
C24: Corporate Promotion
B25: Harga ini adalah harga kontrak 1 thn | C25: Shourlder | D25: High | E25: Peak | F25: Normal
C26: -500000 | D26: -500000 | E26: -700000
A27: Corporate New/NCR | B27: ='7. Rate Strategy'!F32 -> 2150000 | C27: =$B27-C$26 -> 2650000 | D27: =$B27-D$26 -> 2650000 | E27: =$B27-E$26 -> 2850000 | F27: =$B27-($B27*F$26) -> 2150000 | H27: BAR akan menyesuaikan dengan Season. BAR 1-4 akan di apply pada periode High dan Peak Season
A28: Corporate Productive | B28: ='7. Rate Strategy'!F33 -> 2100000 | C28: =$B$28-C$26 -> 2600000 | D28: =$B$28-D$26 -> 2600000 | E28: =$B$28-E$26 -> 2800000 | F28: =$B28-($B28*F$26) -> 2100000
A29: Corporate Super Productive/NKA | B29: ='7. Rate Strategy'!F34 -> 2050000 | C29: =$B$29-C$26 -> 2550000 | D29: =$B$29-D$26 -> 2550000 | E29: =$B$29-E$26 -> 2750000 | F29: =$B29-($B29*F$26) -> 2050000
A30: KKG - DLK | C30: =$B30-($B30*C$26) -> 0 | D30: =$B30-($B30*D$26) -> 0 | E30: =$B30-($B30*E$26) -> 0 | F30: =$B30-($B30*F$26) -> 0
A31: Corporate Preffered | C31: =$B31-($B31*C$26) -> 0 | D31: =$B31-($B31*D$26) -> 0 | E31: =$B31-($B31*E$26) -> 0 | F31: =$B31-($B31*F$26) -> 0
A32: Corporate With Inclusion 1 | C32: Harga Corporate include (laundry, transport, etc ) namun bukan package untuk umum
A33: Corporate With Inclusion 2
A34: Corporate With Inclusion 3
A35: Corporate With Inclusion 4
A36: Corporate With Inclusion 5
A38: Government New | B38: =B27 -> 2150000
A39: Government Productive | B39: =B28 -> 2100000
A40: Government Super Productive | B40: 0
A41: Government Preferred 1
A42: Government Preferred 2
A43: Government Preferred 3
A44: Government with Inclusion 1 | C44: Harga Govt include (laundry, transport, etc ) namun bukan package untuk umum
A45: Government with Inclusion 2
A46: Government with Inclusion 3
A47: Government with Inclusion 4
C48: Travel Agent Promotion
B49: Harga ini adalah harga kontrak 1 thn | C49: Shoulder | D49: High | E49: Peak
C50: -300000 | D50: -600000 | E50: -800000 | F50: 0.1
A51: Travel Agent New | B51: ='7. Rate Strategy'!F49 -> 2400000 | C51: =$B$51-C50 -> 2700000 | D51: =$B$51-D50 -> 3000000 | E51: =$B$51-E50 -> 3200000 | F51: =$B51-($B51*F$50) -> 2160000
A52: Travel Agent Productive | B52: ='7. Rate Strategy'!F57 -> 2300000 | C52: =$B$52-C50 -> 2600000 | D52: =$B$52-D50 -> 2900000 | E52: =$B$52-E50 -> 3100000 | F52: =$B52-($B52*F$50) -> 2070000
A53: Travel Agent Wholesale | B53: ='7. Rate Strategy'!F57 -> 2300000 | C53: =$B$53-C50 -> 2600000 | D53: =$B$53-D50 -> 2900000 | E53: =$B$53-E50 -> 3100000 | F53: =$B53-($B53*F$50) -> 2070000
A54: Travel Agent Preffered 1 | B54: 0 | C54: =$B54-($B54*C$50) -> 0 | D54: =$B54-($B54*D$50) -> 0 | E54: =$B54-($B54*E$50) -> 0 | F54: =$B54-($B54*F$50) -> 0
A55: Travel Agent Preffered 2 | B55: 0 | C55: =$B55-($B55*C$50) -> 0 | D55: =$B55-($B55*D$50) -> 0 | E55: =$B55-($B55*E$50) -> 0 | F55: =$B55-($B55*F$50) -> 0
B56: Harga ini adalah harga kontrak 1 thn | C56: Tactical | D56: Tactical
C57: 0.15 | D57: 0.1 | E57: 0.05 | H57: Tactical Rate akan dikeluarkan untuk specific market dan menyesuaikan dengan kebutuhan hotel unutk periode tertentu dan market tertentu.
A58: Travel Agent - Inbound World Wide | B58: ='7. Rate Strategy'!F61 -> 2600000 | C58: =B58-(B58*C57) -> 2210000 | D58: =B58-(B58*D57) -> 2340000 | E58: =B58-(B58*E57) -> 2470000
A59: Travel Agent - Inbound EU,UK | B59: ='7. Rate Strategy'!F65 -> 2550000 | C59: =B59-(B59*C57) -> 2167500 | D59: =B59-(B59*D57) -> 2295000 | E59: =B59-(B59*E57) -> 2422500
A60: KKG - Personal Visit | B60: ='7. Rate Strategy'!F73 -> 1900000 | C60: harga KKG personal visit maupun relasi harus dibawah harga online, bisa dengan harga travel agent new
A61: KKG - Relasi | B61: ='7. Rate Strategy'!F74 -> 2050000
A62: Owner Rate | B62: =B60 -> 1900000 | C62: harga owner, setidaknya sama dengan harga wholesale
A63: GOHR DLK - Single Occupancy | B63: =B62 -> 1900000 | C63: menyesuaikan pagu DLK SIHR, jika 1 kamar di isi sendiri
A64: GOHR DLK - Double Occupancy | B64: =B63 -> 1900000 | C64: bisa dikalikan dengan 2x pagu DLK SIHR, setidaknya sama dengan harga Corporate, jangan lebih mahal apalagi dengan harga online
A65: Conference Rate - SMALL - A | B65: ='7. Rate Strategy'!F81 -> 2100000
A66: Conference Rate - LARGE - B | B66: ='7. Rate Strategy'!F80 -> 2150000
A67: Group Adhoc - RBF only
A68: Corp/TA - GROUP 1
A69: Corp/TA - GROUP 2
A70: Corp/TA - GROUP 3
A71: Corp/TA - GROUP 4
A72: Corp/TA - GROUP 5
A73: Corp/TA - GROUP 6 | B73: 0
A74: Travel Agent - Inbound ADHOC 1
A75: Travel Agent - Inbound ADHOC 2
A76: Travel Agent - Inbound ADHOC 3
A77: Package
A78: Extra Bed | B78: 1000000

Sheet 7. Rate Strategy
B1: The Anvaya Beach Resort Bali
B2: RATE STRUCTURE I RATE STRATEGY I budget format Santika Indonesia Hotels & Resorts
Y3: Rate
B4: Hotel Unit | C4: : | X4: B'fast Rate | Y4: 0 | Z4: 280000
B5: Updated | C5: : | X5: Double Occ | Y5: 0 | Z5: 1.8
X6: spc. Arrangement | Y6: benefit 1 | Z6: benefit 2 | AA6: benefit 3 | AB6: benefit 4 | AC6: benefit 5 | AD6: benefit 6 | AE6: benefit 7
Y7: 0 | Z7: 0 | AA7: 0 | AB7: 0 | AC7: 0 | AD7: 0 | AG7: bisa di input sama
B9: 2024 | E9: RATE STRUCTURE TO BUDGET ACHIEVEMENT | X9: BUSINESS MIX TO BUDGET ACHIEVEMENT | AR9: REVENUE ACHIEVEMENT ( nett )
E10: R. Type | F10: Deluxe Room | G10: Deluxe Pool Access | H10: Premiere Room | I10: Premiere Lagoon Access | J10: Family Premiere | K10: Deluxe Suite | L10: Premiere Suite | M10: The Anvaya Suite No Pool | N10: The Anvaya Suite Whirl Pool | O10: Beach Front Private Suite | P10: Anvaya Residence | Q10: The Anvaya Suite with Pool | R10: The Anvaya Villa | X10: Rate Segment Mix | Z10: Budget Market Segment Mix | AA10: Last Year Market Segment Mix | AB10: R. Type | AC10: =F10 -> Deluxe Room | AD10: =G10 -> Deluxe Pool Access | AE10: =H10 -> Premiere Room | AF10: =I10 -> Premiere Lagoon Access | AG10: =J10 -> Family Premiere | AH10: =K10 -> Deluxe Suite | AI10: =L10 -> Premiere Suite | AJ10: =M10 -> The Anvaya Suite No Pool | AK10: =O10 -> Beach Front Private Suite | AL10: =N10 -> The Anvaya Suite Whirl Pool | AM10: =P10 -> Anvaya Residence | AN10: =Q10 -> The Anvaya Suite with Pool | AO10: =R10 -> The Anvaya Villa | AR10: =AC10 -> Deluxe Room | AS10: =AD10 -> Deluxe Pool Access | AT10: =AE10 -> Premiere Room | AU10: =AF10 -> Premiere Lagoon Access | AV10: =AG10 -> Family Premiere | AW10: =AH10 -> Deluxe Suite | AX10: =AI10 -> Premiere Suite | AY10: =AJ10 -> The Anvaya Suite No Pool | ... BD10: =AO10 -> The Anvaya Villa | BE10: Total Revenue
E11: Publish | F11: =CEILING(F13+(F13*F12),100000) -> 6500000 | G11: =CEILING(G13+(G13*G12),100000) -> 7000000 | H11: =CEILING(H13+(H13*H12),100000) -> 7400000 | I11: =CEILING(I13+(I13*I12),100000) -> 9200000 | J11: =CEILING(J13+(J13*J12),100000) -> 11100000 | K11: =CEILING(K13+(K13*K12),100000) -> 13800000 | L11: =CEILING(L13+(L13*L12),100000) -> 14700000 | M11: =CEILING(M13+(M13*M12),100000) -> 18400000 | ... R11: =CEILING(R13+(R13*R12),100000) -> 56100000 | AB11: R. Avail | AC11: =139*365 -> 50735 | AD11: =21*365 -> 7665 | AE11: =264*365 -> 96360 | AF11: =30*365 -> 10950 | AG11: =5*365 -> 1825 | AH11: =5*365 -> 1825 | AI11: =9*365 -> 3285 | AJ11: =4*365 -> 1460 | AK11: =8*365 -> 2920 | AL11: =4*365 -> 1460 | AM11: =1*365 -> 365 | AN11: =2*365 -> 730 | AO11: =1*365 -> 365 | AP11: =SUM(AC11:AO11) -> 179945 | AT11: incl. benefit 1 | AU11: incl. benefit 2 | AV11: incl. benefit 3 | AW11: incl. benefit 4 | AX11: incl. benefit 5 | AY11: incl. benefit 5 | AZ11: incl. benefit 5 | BA11: incl. benefit 5 | BB11: incl. benefit 5 | BC11: incl. benefit 5 | BD11: incl. benefit 5
F12: 0.12 | G12: 0.12 | H12: 0.12 | I12: 0.12 | J12: 0.12 | K12: 0.1 | L12: 0.1 | M12: 0.1 | N12: 0.1 | O12: 0.1 | P12: 0.06 | Q12: 0.1 | R12: 0.06
E13: 2025 | F13: 5800000 | G13: 6250000 | H13: 6550000 | I13: 8200000 | J13: 9900000 | K13: 12500000 | L13: 13300000 | M13: 16650000 | N13: 18100000 | O13: 18800000 | P13: 19050000 | Q13: 24100000 | R13: 52900000
AB14: Share | AC14: 0.36 | AD14: 0.05 | AE14: 0.463 | AF14: 0.08 | AG14: 0.01 | AH14: 0.01 | AI14: 0.005 | AJ14: 0.005 | AK14: 0.004 | AL14: 0.01 | AM14: 0.001 | AN14: 0.001 | AO14: 0.001 | AP14: =SUM(AC14:AO14) -> 1
AB15: R. Sold | AC15: =AC14*$V$17 -> 51864.154 | AD15: =AD14*$V$17 -> 7203.3547 | AE15: =AE14*$V$17 -> 66703.065 | AF15: =AF14*$V$17 -> 11525.368 | AG15: =AG14*$V$17 -> 1440.6709 | AH15: =AH14*$V$17 -> 1440.6709 | AI15: =AI14*$V$17 -> 720.33547 | AJ15: =AJ14*$V$17 -> 720.33547 | ... AO15: =AO14*$V$17 -> 144.06709 | AP15: =SUM(AC15:AO15) -> 144067.09 | BF15: Total per segment | BH15: budget per segment
B16: Internet Rate / WIG Rate / BAR 1 | E16: 0.1 | F16: =IF(COUNTA($E16),F$11-(F$11*$E16),0) -> 5850000 | G16: =IF(COUNTA($E16),G$11-(G$11*$E16),0) -> 6300000 | H16: =IF(COUNTA($E16),H$11-(H$11*$E16),0) -> 6660000 | I16: =IF(COUNTA($E16),I$11-(I$11*$E16),0) -> 8280000 | J16: =IF(COUNTA($E16),J$11-(J$11*$E16),0) -> 9990000 | K16: =IF(COUNTA($E16),K$11-(K$11*$E16),0) -> 12420000 | L16: =IF(COUNTA($E16),L$11-(L$11*$E16),0) -> 13230000 | M16: =IF(COUNTA($E16),M$11-(M$11*$E16),0) -> 16560000 | ... R16: =IF(COUNTA($E16),R$11-(R$11*$E16),0) -> 50490000 | T16: BUDGET | U16: : | V16: =B9 -> 2024 | X16: =SUM(Y16:Y30) -> 0.37 | Y16: 0 | Z16: 0.46162285 | AA16: 0.34063599 | AC16: =$AC$15*Y16 -> 0 | AD16: =$AD$15*Y16 -> 0 | AE16: =$AE$15*Y16 -> 0 | AF16: =$AF$15*Y16 -> 0 | AG16: =$AG$15*Y16 -> 0 | AH16: =$AH$15*Y16 -> 0 | AI16: =$AI$15*Y16 -> 0 | AJ16: =$AJ$15*Y16 -> 0 | AK16: =$AK$15*Y16 -> 0 | AL16: =$AL$15*Y16 -> 0 | AM16: =$AM$15*Y16 -> 0 | AN16: =$AN$15*Y16 -> 0 | AO16: =$AO$15*Y16 -> 0 | AP16: =SUM(AC16:AO16) -> 0 | AR16: =IF(AC16=0,0,((F16*AC16)-($Y$4*$Y$5*AC16)-Y$7*AC16)/1.21) -> 0 | AT16: =IF(AE16=0,0,((H16*AE16)-($Y$4*$Y$5*AE16)-AA$7*AE16)/1.21) -> 0 | AU16: =IF(AF16=0,0,((I16*AF16)-($Y$4*$Y$5*AF16)-AB$7*AF16)/1.21) -> 0 | AV16: =IF(AG16=0,0,((J16*AG16)-($Y$4*$Y$5*AG16)-AC$7*AG16)/1.21) -> 0 | AW16: =IF(AH16=0,0,((K16*AH16)-($Y$4*$Y$5*AH16)-AD$7*AH16)/1.21) -> 0 | AX16: =IF(AI16=0,0,((L16*AI16)-($Y$4*$Y$5*AI16)-AE$7*AI16)/1.21) -> 0 | AY16: =IF(AJ16=0,0,((M16*AJ16)-($Y$4*$Y$5*AJ16)-AF$7*AJ16)/1.21) -> 0 | AZ16: =IF(AK16=0,0,((O16*AK16)-($Z$4*$Z$5*AK16)-AD7*AK16)/1.21) -> 0 | BA16: =IF(AL16=0,0,((N16*AL16)-($Y$4*$Y$5*AL16)-AH$7*AL16)/1.21) -> 0 | BB16: =IF(AM16=0,0,((P16*AM16)-($Y$4*$Y$5*AM16)-AI$7*AM16)/1.21) -> 0 | BC16: =IF(AN16=0,0,((Q16*AN16)-($Y$4*$Y$5*AN16)-AJ$7*AN16)/1.21) -> 0 | BD16: =IF(AO16=0,0,((R16*AO16)-($Y$4*$Y$5*AO16)-AK$7*AO16)/1.21) -> 0 | BE16: =SUM(AR16:BD16) -> 0 | BF16: =BK20 -> 0 | BG16: FIT + Online | BH16: 100286064118 | BI16: =SUM(BE16:BE30) -> 1.3804436e+11 | BJ16: Online Share
B17: Internet Rate / WIG Rate / BAR 2 | E17: 0.15 | F17: =IF(COUNTA($E17),F$11-(F$11*$E17),0) -> 5525000 | G17: =IF(COUNTA($E17),G$11-(G$11*$E17),0) -> 5950000 | H17: =IF(COUNTA($E17),H$11-(H$11*$E17),0) -> 6290000 | I17: =IF(COUNTA($E17),I$11-(I$11*$E17),0) -> 7820000 | J17: =IF(COUNTA($E17),J$11-(J$11*$E17),0) -> 9435000 | K17: =IF(COUNTA($E17),K$11-(K$11*$E17),0) -> 11730000 | L17: =IF(COUNTA($E17),L$11-(L$11*$E17),0) -> 12495000 | M17: =IF(COUNTA($E17),M$11-(M$11*$E17),0) -> 15640000 | ... R17: =IF(COUNTA($E17),R$11-(R$11*$E17),0) -> 47685000 | T17: Room Sold | U17: : | V17: 144067.09 | Y17: 0 | AC17: =$AC$15*Y17 -> 0 | AD17: =$AD$15*Y17 -> 0 | AE17: =$AE$15*Y17 -> 0 | AF17: =$AF$15*Y17 -> 0 | AG17: =$AG$15*Y17 -> 0 | AH17: =$AH$15*Y17 -> 0 | AI17: =$AI$15*Y17 -> 0 | AJ17: =$AJ$15*Y17 -> 0 | AK17: =$AK$15*Y17 -> 0 | AL17: =$AL$15*Y17 -> 0 | AM17: =$AM$15*Y17 -> 0 | AN17: =$AN$15*Y17 -> 0 | AO17: =$AO$15*Y17 -> 0 | AP17: =SUM(AC17:AO17) -> 0 | AR17: =IF(AC17=0,0,((F17*AC17)-($Y$4*$Y$5*AC17)-Y$7*AC17)/1.21) -> 0 | AT17: =IF(AE17=0,0,((H17*AE17)-($Y$4*$Y$5*AE17)-AA$7*AE17)/1.21) -> 0 | AU17: =IF(AF17=0,0,((I17*AF17)-($Y$4*$Y$5*AF17)-AB$7*AF17)/1.21) -> 0 | AV17: =IF(AG17=0,0,((J17*AG17)-($Y$4*$Y$5*AG17)-AC$7*AG17)/1.21) -> 0 | AW17: =IF(AH17=0,0,((K17*AH17)-($Y$4*$Y$5*AH17)-AD$7*AH17)/1.21) -> 0 | AX17: =IF(AI17=0,0,((L17*AI17)-($Y$4*$Y$5*AI17)-AE$7*AI17)/1.21) -> 0 | AY17: =IF(AJ17=0,0,((M17*AJ17)-($Y$4*$Y$5*AJ17)-AF$7*AJ17)/1.21) -> 0 | AZ17: =IF(AK17=0,0,((O17*AK17)-($Z$4*$Z$5*AK17)-AD8*AK17)/1.21) -> 0 | BA17: =IF(AL17=0,0,((N17*AL17)-($Y$4*$Y$5*AL17)-AH$7*AL17)/1.21) -> 0 | BB17: =IF(AM17=0,0,((P17*AM17)-($Y$4*$Y$5*AM17)-AI$7*AM17)/1.21) -> 0 | BC17: =IF(AN17=0,0,((Q17*AN17)-($Y$4*$Y$5*AN17)-AJ$7*AN17)/1.21) -> 0 | BD17: =IF(AO17=0,0,((R17*AO17)-($Y$4*$Y$5*AO17)-AK$7*AO17)/1.21) -> 0 | BE17: =SUM(AR17:BD17) -> 0 | BJ17: Online Revenue
B18: Internet Rate / WIG Rate / BAR 3 | E18: 0.2 | F18: =IF(COUNTA($E18),F$11-(F$11*$E18),0) -> 5200000 | G18: =IF(COUNTA($E18),G$11-(G$11*$E18),0) -> 5600000 | H18: =IF(COUNTA($E18),H$11-(H$11*$E18),0) -> 5920000 | I18: =IF(COUNTA($E18),I$11-(I$11*$E18),0) -> 7360000 | J18: =IF(COUNTA($E18),J$11-(J$11*$E18),0) -> 8880000 | K18: =IF(COUNTA($E18),K$11-(K$11*$E18),0) -> 11040000 | L18: =IF(COUNTA($E18),L$11-(L$11*$E18),0) -> 11760000 | M18: =IF(COUNTA($E18),M$11-(M$11*$E18),0) -> 14720000 | ... R18: =IF(COUNTA($E18),R$11-(R$11*$E18),0) -> 44880000 | T18: Room Revenue | U18: : | V18: 1.8761209e+11 | Y18: 0 | AC18: =$AC$15*Y18 -> 0 | AD18: =$AD$15*Y18 -> 0 | AE18: =$AE$15*Y18 -> 0 | AF18: =$AF$15*Y18 -> 0 | AG18: =$AG$15*Y18 -> 0 | AH18: =$AH$15*Y18 -> 0 | AI18: =$AI$15*Y18 -> 0 | AJ18: =$AJ$15*Y18 -> 0 | AK18: =$AK$15*Y18 -> 0 | AL18: =$AL$15*Y18 -> 0 | AM18: =$AM$15*Y18 -> 0 | AN18: =$AN$15*Y18 -> 0 | AO18: =$AO$15*Y18 -> 0 | AP18: =SUM(AC18:AO18) -> 0 | AR18: =IF(AC18=0,0,((F18*AC18)-($Y$4*$Y$5*AC18)-Y$7*AC18)/1.21) -> 0 | AT18: =IF(AE18=0,0,((H18*AE18)-($Y$4*$Y$5*AE18)-AA$7*AE18)/1.21) -> 0 | AU18: =IF(AF18=0,0,((I18*AF18)-($Y$4*$Y$5*AF18)-AB$7*AF18)/1.21) -> 0 | AV18: =IF(AG18=0,0,((J18*AG18)-($Y$4*$Y$5*AG18)-AC$7*AG18)/1.21) -> 0 | AW18: =IF(AH18=0,0,((K18*AH18)-($Y$4*$Y$5*AH18)-AD$7*AH18)/1.21) -> 0 | AX18: =IF(AI18=0,0,((L18*AI18)-($Y$4*$Y$5*AI18)-AE$7*AI18)/1.21) -> 0 | AY18: =IF(AJ18=0,0,((M18*AJ18)-($Y$4*$Y$5*AJ18)-AF$7*AJ18)/1.21) -> 0 | AZ18: =IF(AK18=0,0,((O18*AK18)-($Z$4*$Z$5*AK18)-AD9*AK18)/1.21) -> 0 | BA18: =IF(AL18=0,0,((N18*AL18)-($Y$4*$Y$5*AL18)-AH$7*AL18)/1.21) -> 0 | BB18: =IF(AM18=0,0,((P18*AM18)-($Y$4*$Y$5*AM18)-AI$7*AM18)/1.21) -> 0 | BC18: =IF(AN18=0,0,((Q18*AN18)-($Y$4*$Y$5*AN18)-AJ$7*AN18)/1.21) -> 0 | BD18: =IF(AO18=0,0,((R18*AO18)-($Y$4*$Y$5*AO18)-AK$7*AO18)/1.21) -> 0 | BE18: =SUM(AR18:BD18) -> 0 | BJ18: AVG OTA Comm Level
B19: Internet Rate / WIG Rate / BAR 4 | E19: 0.25 | F19: =IF(COUNTA($E19),F$11-(F$11*$E19),0) -> 4875000 | G19: =IF(COUNTA($E19),G$11-(G$11*$E19),0) -> 5250000 | H19: =IF(COUNTA($E19),H$11-(H$11*$E19),0) -> 5550000 | I19: =IF(COUNTA($E19),I$11-(I$11*$E19),0) -> 6900000 | J19: =IF(COUNTA($E19),J$11-(J$11*$E19),0) -> 8325000 | K19: =IF(COUNTA($E19),K$11-(K$11*$E19),0) -> 10350000 | L19: =IF(COUNTA($E19),L$11-(L$11*$E19),0) -> 11025000 | M19: =IF(COUNTA($E19),M$11-(M$11*$E19),0) -> 13800000 | ... R19: =IF(COUNTA($E19),R$11-(R$11*$E19),0) -> 42075000 | T19: Average Room Rate | U19: : | V19: =V18/V17 -> 1302254.9 | Y19: 0 | AC19: =$AC$15*Y19 -> 0 | AD19: =$AD$15*Y19 -> 0 | AE19: =$AE$15*Y19 -> 0 | AF19: =$AF$15*Y19 -> 0 | AG19: =$AG$15*Y19 -> 0 | AH19: =$AH$15*Y19 -> 0 | AI19: =$AI$15*Y19 -> 0 | AJ19: =$AJ$15*Y19 -> 0 | AK19: =$AK$15*Y19 -> 0 | AL19: =$AL$15*Y19 -> 0 | AM19: =$AM$15*Y19+7.5 -> 7.5 | AN19: =$AN$15*Y19 -> 0 | AO19: =$AO$15*Y19 -> 0 | AP19: =SUM(AC19:AO19) -> 7.5 | AR19: =IF(AC19=0,0,((F19*AC19)-($Y$4*$Y$5*AC19)-Y$7*AC19)/1.21) -> 0 | AT19: =IF(AE19=0,0,((H19*AE19)-($Y$4*$Y$5*AE19)-AA$7*AE19)/1.21) -> 0 | AU19: =IF(AF19=0,0,((I19*AF19)-($Y$4*$Y$5*AF19)-AB$7*AF19)/1.21) -> 0 | AV19: =IF(AG19=0,0,((J19*AG19)-($Y$4*$Y$5*AG19)-AC$7*AG19)/1.21) -> 0 | AW19: =IF(AH19=0,0,((K19*AH19)-($Y$4*$Y$5*AH19)-AD$7*AH19)/1.21) -> 0 | AX19: =IF(AI19=0,0,((L19*AI19)-($Y$4*$Y$5*AI19)-AE$7*AI19)/1.21) -> 0 | AY19: =IF(AJ19=0,0,((M19*AJ19)-($Y$4*$Y$5*AJ19)-AF$7*AJ19)/1.21) -> 0 | AZ19: =IF(AK19=0,0,((O19*AK19)-(Z4*Z5*AK19)-AD7*AK19)/1.21) -> 0 | BA19: =IF(AL19=0,0,((N19*AL19)-($Y$4*$Y$5*AL19)-AH$7*AL19)/1.21) -> 0 | BB19: =IF(AM19=0,0,((P19*AM19)-($Y$4*$Y$5*AM19)-AI$7*AM19)/1.21) -> 93904959 | BC19: =IF(AN19=0,0,((Q19*AN19)-($Y$4*$Y$5*AN19)-AJ$7*AN19)/1.21) -> 0 | BD19: =IF(AO19=0,0,((R19*AO19)-($Y$4*$Y$5*AO19)-AK$7*AO19)/1.21) -> 0 | BE19: =SUM(AR19:BD19) -> 93904959 | BJ19: OTA Comm | BL19: 0.32
B20: Internet Rate / WIG Rate / BAR 5 | E20: 0.3 | F20: =IF(COUNTA($E20),F$11-(F$11*$E20),0) -> 4550000 | G20: =IF(COUNTA($E20),G$11-(G$11*$E20),0) -> 4900000 | H20: =IF(COUNTA($E20),H$11-(H$11*$E20),0) -> 5180000 | I20: =IF(COUNTA($E20),I$11-(I$11*$E20),0) -> 6440000 | J20: =IF(COUNTA($E20),J$11-(J$11*$E20),0) -> 7770000 | K20: =IF(COUNTA($E20),K$11-(K$11*$E20),0) -> 9660000 | L20: =IF(COUNTA($E20),L$11-(L$11*$E20),0) -> 10290000 | M20: =IF(COUNTA($E20),M$11-(M$11*$E20),0) -> 12880000 | ... R20: =IF(COUNTA($E20),R$11-(R$11*$E20),0) -> 39270000 | Y20: 0 | AC20: =$AC$15*Y20 -> 0 | AD20: =$AD$15*Y20 -> 0 | AE20: =$AE$15*Y20 -> 0 | AF20: =$AF$15*Y20 -> 0 | AG20: =$AG$15*Y20 -> 0 | AH20: =$AH$15*Y20 -> 0 | AI20: =$AI$15*Y20 -> 0 | AJ20: =$AJ$15*Y20 -> 0 | AK20: =$AK$15*Y20 -> 0 | AL20: =$AL$15*Y20 -> 0 | AM20: 0 | AN20: =$AN$15*Y20 -> 0 | AO20: =$AO$15*Y20 -> 0 | AP20: =SUM(AC20:AO20) -> 0 | AR20: =IF(AC20=0,0,((F20*AC20)-($Y$4*$Y$5*AC20)-Y$7*AC20)/1.21) -> 0 | AS20: =IF(AD20=0,0,((G20*AD20)-($Y$4*$Y$5*AD20)-Z$7*AD20)/1.21) -> 0 | AT20: =IF(AE20=0,0,((H20*AE20)-($Y$4*$Y$5*AE20)-AA$7*AE20)/1.21) -> 0 | AU20: =IF(AF20=0,0,((I20*AF20)-($Y$4*$Y$5*AF20)-AB$7*AF20)/1.21) -> 0 | AV20: =IF(AG20=0,0,((J20*AG20)-($Y$4*$Y$5*AG20)-AC$7*AG20)/1.21) -> 0 | AW20: =IF(AH20=0,0,((K20*AH20)-($Y$4*$Y$5*AH20)-AD$7*AH20)/1.21) -> 0 | AX20: =IF(AI20=0,0,((L20*AI20)-($Y$4*$Y$5*AI20)-AE$7*AI20)/1.21) -> 0 | AY20: =IF(AJ20=0,0,((M20*AJ20)-($Y$4*$Y$5*AJ20)-AF$7*AJ20)/1.21) -> 0 | AZ20: =IF(AK20=0,0,((O20*AK20)-($Z$4*$Z$5*AK20)-AD11*AK20)/1.21) -> 0 | BA20: =IF(AL20=0,0,((N20*AL20)-($Y$4*$Y$5*AL20)-AH$7*AL20)/1.21) -> 0 | BB20: =IF(AM20=0,0,((P20*AM20)-($Y$4*$Y$5*AM20)-AI$7*AM20)/1.21) -> 0 | BC20: =IF(AN20=0,0,((Q20*AN20)-($Y$4*$Y$5*AN20)-AJ$7*AN20)/1.21) -> 0 | BD20: =IF(AO20=0,0,((R20*AO20)-($Y$4*$Y$5*AO20)-AK$7*AO20)/1.21) -> 0 | BE20: =SUM(AR20:BD20) -> 0 | BJ20: OTA + FIT Revenue
B21: Internet Rate / WIG Rate / BAR 6 | E21: 0.4 | F21: =IF(COUNTA($E21),F$11-(F$11*$E21),0) -> 3900000 | G21: =IF(COUNTA($E21),G$11-(G$11*$E21),0) -> 4200000 | H21: =IF(COUNTA($E21),H$11-(H$11*$E21),0) -> 4440000 | I21: =IF(COUNTA($E21),I$11-(I$11*$E21),0) -> 5520000 | J21: =IF(COUNTA($E21),J$11-(J$11*$E21),0) -> 6660000 | K21: =IF(COUNTA($E21),K$11-(K$11*$E21),0) -> 8280000 | L21: =IF(COUNTA($E21),L$11-(L$11*$E21),0) -> 8820000 | M21: =IF(COUNTA($E21),M$11-(M$11*$E21),0) -> 11040000 | ... R21: =IF(COUNTA($E21),R$11-(R$11*$E21),0) -> 33660000 | T21: RATE STRUCTURE RESULT : | Y21: 0 | AC21: =$AC$15*Y21 -> 0 | AD21: =$AD$15*Y21 -> 0 | AE21: =$AE$15*Y21 -> 0 | AF21: =$AF$15*Y21 -> 0 | AG21: =$AG$15*Y21 -> 0 | AH21: =$AH$15*Y21 -> 0 | AI21: =$AI$15*Y21 -> 0 | AJ21: =$AJ$15*Y21 -> 0 | AK21: =$AK$15*Y21 -> 0 | AL21: =$AL$15*Y21 -> 0 | AM21: =$AM$15*Y21 -> 0 | AN21: =$AN$15*Y21 -> 0 | AO21: =$AO$15*Y21 -> 0 | AP21: =SUM(AC21:AO21) -> 0 | AR21: =IF(AC21=0,0,((F21*AC21)-($Y$4*$Y$5*AC21)-Y$7*AC21)/1.21) -> 0 | AS21: =IF(AD21=0,0,((G21*AD21)-($Y$4*$Y$5*AD21)-Z$7*AD21)/1.21) -> 0 | AT21: =IF(AE21=0,0,((H21*AE21)-($Y$4*$Y$5*AE21)-AA$7*AE21)/1.21) -> 0 | AU21: =IF(AF21=0,0,((I21*AF21)-($Y$4*$Y$5*AF21)-AB$7*AF21)/1.21) -> 0 | AV21: =IF(AG21=0,0,((J21*AG21)-($Y$4*$Y$5*AG21)-AC$7*AG21)/1.21) -> 0 | AW21: =IF(AH21=0,0,((K21*AH21)-($Y$4*$Y$5*AH21)-AD$7*AH21)/1.21) -> 0 | AX21: =IF(AI21=0,0,((L21*AI21)-($Y$4*$Y$5*AI21)-AE$7*AI21)/1.21) -> 0 | AY21: =IF(AJ21=0,0,((M21*AJ21)-($Y$4*$Y$5*AJ21)-AF$7*AJ21)/1.21) -> 0 | AZ21: =IF(AK21=0,0,((O21*AK21)-($Z$4*$Z$5*AK21)-AD14*AK21)/1.21) -> 0 | BA21: =IF(AL21=0,0,((N21*AL21)-($Y$4*$Y$5*AL21)-AH$7*AL21)/1.21) -> 0 | BB21: =IF(AM21=0,0,((P21*AM21)-($Y$4*$Y$5*AM21)-AI$7*AM21)/1.21) -> 0 | BC21: =IF(AN21=0,0,((Q21*AN21)-($Y$4*$Y$5*AN21)-AJ$7*AN21)/1.21) -> 0 | BD21: =IF(AO21=0,0,((R21*AO21)-($Y$4*$Y$5*AO21)-AK$7*AO21)/1.21) -> 0 | BE21: =SUM(AR21:BD21) -> 0
B22: Internet Rate / WIG Rate / BAR 7 | E22: 0.425 | F22: =IF(COUNTA($E22),F$11-(F$11*$E22),0) -> 3737500 | G22: =IF(COUNTA($E22),G$11-(G$11*$E22),0) -> 4025000 | H22: =IF(COUNTA($E22),H$11-(H$11*$E22),0) -> 4255000 | I22: =IF(COUNTA($E22),I$11-(I$11*$E22),0) -> 5290000 | J22: =IF(COUNTA($E22),J$11-(J$11*$E22),0) -> 6382500 | K22: =IF(COUNTA($E22),K$11-(K$11*$E22),0) -> 7935000 | L22: =IF(COUNTA($E22),L$11-(L$11*$E22),0) -> 8452500 | M22: =IF(COUNTA($E22),M$11-(M$11*$E22),0) -> 10580000 | ... R22: =IF(COUNTA($E22),R$11-(R$11*$E22),0) -> 32257500 | T22: Room Sold | U22: : | V22: =SUM(AC15:AO15) -> 144067.09 | Y22: 0 | AC22: =$AC$15*Y22 -> 0 | AD22: =$AD$15*Y22 -> 0 | AE22: =$AE$15*Y22 -> 0 | AF22: =$AF$15*Y22 -> 0 | AG22: =$AG$15*Y22 -> 0 | AH22: =$AH$15*Y22 -> 0 | AI22: =$AI$15*Y22 -> 0 | AJ22: =$AJ$15*Y22 -> 0 | AK22: =$AK$15*Y22 -> 0 | AL22: =$AL$15*Y22 -> 0 | AM22: =$AM$15*Y22 -> 0 | AN22: =$AN$15*Y22 -> 0 | AO22: =$AO$15*Y22 -> 0 | AP22: =SUM(AC22:AO22) -> 0 | AR22: =IF(AC22=0,0,((F22*AC22)-($Y$4*$Y$5*AC22)-Y$7*AC22)/1.21) -> 0 | AS22: =IF(AD22=0,0,((G22*AD22)-($Y$4*$Y$5*AD22)-Z$7*AD22)/1.21) -> 0 | AT22: =IF(AE22=0,0,((H22*AE22)-($Y$4*$Y$5*AE22)-AA$7*AE22)/1.21) -> 0 | AU22: =IF(AF22=0,0,((I22*AF22)-($Y$4*$Y$5*AF22)-AB$7*AF22)/1.21) -> 0 | AV22: =IF(AG22=0,0,((J22*AG22)-($Y$4*$Y$5*AG22)-AC$7*AG22)/1.21) -> 0 | AW22: =IF(AH22=0,0,((K22*AH22)-($Y$4*$Y$5*AH22)-AD$7*AH22)/1.21) -> 0 | AX22: =IF(AI22=0,0,((L22*AI22)-($Y$4*$Y$5*AI22)-AE$7*AI22)/1.21) -> 0 | AY22: =IF(AJ22=0,0,((M22*AJ22)-($Y$4*$Y$5*AJ22)-AF$7*AJ22)/1.21) -> 0 | AZ22: =IF(AK22=0,0,((O22*AK22)-($Z$4*$Z$5*AK22)-AD15*AK22)/1.21) -> 0 | BA22: =IF(AL22=0,0,((N22*AL22)-($Y$4*$Y$5*AL22)-AH$7*AL22)/1.21) -> 0 | BB22: =IF(AM22=0,0,((P22*AM22)-($Y$4*$Y$5*AM22)-AI$7*AM22)/1.21) -> 0 | BC22: =IF(AN22=0,0,((Q22*AN22)-($Y$4*$Y$5*AN22)-AJ$7*AN22)/1.21) -> 0 | BD22: =IF(AO22=0,0,((R22*AO22)-($Y$4*$Y$5*AO22)-AK$7*AO22)/1.21) -> 0 | BE22: =SUM(AR22:BD22) -> 0 | BL22: 2248212 | BM22: =F22-BL22 -> 1489288 | BN22: =BM22/F22 -> 0.39847171
B23: Internet Rate / WIG Rate / BAR 8 | E23: 0.45 | F23: =IF(COUNTA($E23),F$11-(F$11*$E23),0) -> 3575000 | G23: =IF(COUNTA($E23),G$11-(G$11*$E23),0) -> 3850000 | H23: =IF(COUNTA($E23),H$11-(H$11*$E23),0) -> 4070000 | I23: =IF(COUNTA($E23),I$11-(I$11*$E23),0) -> 5060000 | J23: =IF(COUNTA($E23),J$11-(J$11*$E23),0) -> 6105000 | K23: =IF(COUNTA($E23),K$11-(K$11*$E23),0) -> 7590000 | L23: =IF(COUNTA($E23),L$11-(L$11*$E23),0) -> 8085000 | M23: =IF(COUNTA($E23),M$11-(M$11*$E23),0) -> 10120000 | ... R23: =IF(COUNTA($E23),R$11-(R$11*$E23),0) -> 30855000 | T23: Room Revenue | U23: : | V23: =SUM(BE16:BE86) -> #REF! | Y23: 0 | AC23: =$AC$15*Y23 -> 0 | AD23: =$AD$15*Y23 -> 0 | AE23: =$AE$15*Y23 -> 0 | AF23: =$AF$15*Y23 -> 0 | AG23: =$AG$15*Y23 -> 0 | AH23: =$AH$15*Y23 -> 0 | AI23: =$AI$15*Y23 -> 0 | AJ23: =$AJ$15*Y23 -> 0 | AK23: =$AK$15*Y23 -> 0 | AL23: =$AL$15*Y23 -> 0 | AM23: =$AM$15*Y23 -> 0 | AN23: =$AN$15*Y23 -> 0 | AO23: =$AO$15*Y23 -> 0 | AP23: =SUM(AC23:AO23) -> 0 | AR23: =IF(AC23=0,0,((F23*AC23)-($Y$4*$Y$5*AC23)-Y$7*AC23)/1.21) -> 0 | AS23: =IF(AD23=0,0,((G23*AD23)-($Y$4*$Y$5*AD23)-Z$7*AD23)/1.21) -> 0 | AT23: =IF(AE23=0,0,((H23*AE23)-($Y$4*$Y$5*AE23)-AA$7*AE23)/1.21) -> 0 | AU23: =IF(AF23=0,0,((I23*AF23)-($Y$4*$Y$5*AF23)-AB$7*AF23)/1.21) -> 0 | AV23: =IF(AG23=0,0,((J23*AG23)-($Y$4*$Y$5*AG23)-AC$7*AG23)/1.21) -> 0 | AW23: =IF(AH23=0,0,((K23*AH23)-($Y$4*$Y$5*AH23)-AD$7*AH23)/1.21) -> 0 | AX23: =IF(AI23=0,0,((L23*AI23)-($Y$4*$Y$5*AI23)-AE$7*AI23)/1.21) -> 0 | AY23: =IF(AJ23=0,0,((M23*AJ23)-($Y$4*$Y$5*AJ23)-AF$7*AJ23)/1.21) -> 0 | AZ23: =IF(AK23=0,0,((O23*AK23)-($Z$4*$Z$5*AK23)-AD16*AK23)/1.21) -> 0 | BA23: =IF(AL23=0,0,((N23*AL23)-($Y$4*$Y$5*AL23)-AH$7*AL23)/1.21) -> 0 | BB23: =IF(AM23=0,0,((P23*AM23)-($Y$4*$Y$5*AM23)-AI$7*AM23)/1.21) -> 0 | BC23: =IF(AN23=0,0,((Q23*AN23)-($Y$4*$Y$5*AN23)-AJ$7*AN23)/1.21) -> 0 | BD23: =IF(AO23=0,0,((R23*AO23)-($Y$4*$Y$5*AO23)-AK$7*AO23)/1.21) -> 0 | BE23: =SUM(AR23:BD23) -> 0 | BL23: =F22 - (F22*BL19) -> 2541500 | BM23: =BL23-(BL23*15%) -> 2160275 | BN23: 2070000
B24: Internet Rate / WIG Rate / BAR 9 | E24: 0.475 | F24: =IF(COUNTA($E24),F$11-(F$11*$E24),0) -> 3412500 | G24: =IF(COUNTA($E24),G$11-(G$11*$E24),0) -> 3675000 | H24: =IF(COUNTA($E24),H$11-(H$11*$E24),0) -> 3885000 | I24: =IF(COUNTA($E24),I$11-(I$11*$E24),0) -> 4830000 | J24: =IF(COUNTA($E24),J$11-(J$11*$E24),0) -> 5827500 | K24: =IF(COUNTA($E24),K$11-(K$11*$E24),0) -> 7245000 | L24: =IF(COUNTA($E24),L$11-(L$11*$E24),0) -> 7717500 | M24: =IF(COUNTA($E24),M$11-(M$11*$E24),0) -> 9660000 | ... R24: =IF(COUNTA($E24),R$11-(R$11*$E24),0) -> 29452500 | T24: Average Room Rate | U24: : | V24: =V23/V22 -> #REF! | Y24: 0 | AC24: =$AC$15*Y24 -> 0 | AD24: =$AD$15*Y24 -> 0 | AE24: =$AE$15*Y24 -> 0 | AF24: =$AF$15*Y24 -> 0 | AG24: =$AG$15*Y24 -> 0 | AH24: =$AH$15*Y24 -> 0 | AI24: =$AI$15*Y24 -> 0 | AJ24: =$AJ$15*Y24 -> 0 | AK24: =$AK$15*Y24 -> 0 | AL24: =$AL$15*Y24 -> 0 | AM24: =$AM$15*Y24 -> 0 | AN24: =$AN$15*Y24 -> 0 | AO24: =$AO$15*Y24 -> 0 | AP24: =SUM(AC24:AO24) -> 0 | AR24: =IF(AC24=0,0,((F24*AC24)-($Y$4*$Y$5*AC24)-Y$7*AC24)/1.21) -> 0 | AS24: =IF(AD24=0,0,((G24*AD24)-($Y$4*$Y$5*AD24)-Z$7*AD24)/1.21) -> 0 | AT24: =IF(AE24=0,0,((H24*AE24)-($Y$4*$Y$5*AE24)-AA$7*AE24)/1.21) -> 0 | AU24: =IF(AF24=0,0,((I24*AF24)-($Y$4*$Y$5*AF24)-AB$7*AF24)/1.21) -> 0 | AV24: =IF(AG24=0,0,((J24*AG24)-($Y$4*$Y$5*AG24)-AC$7*AG24)/1.21) -> 0 | AW24: =IF(AH24=0,0,((K24*AH24)-($Y$4*$Y$5*AH24)-AD$7*AH24)/1.21) -> 0 | AX24: =IF(AI24=0,0,((L24*AI24)-($Y$4*$Y$5*AI24)-AE$7*AI24)/1.21) -> 0 | AY24: =IF(AJ24=0,0,((M24*AJ24)-($Y$4*$Y$5*AJ24)-AF$7*AJ24)/1.21) -> 0 | AZ24: =IF(AK24=0,0,((O24*AK24)-($Z$4*$Z$5*AK24)-AD17*AK24)/1.21) -> 0 | BA24: =IF(AL24=0,0,((N24*AL24)-($Y$4*$Y$5*AL24)-AH$7*AL24)/1.21) -> 0 | BB24: =IF(AM24=0,0,((P24*AM24)-($Y$4*$Y$5*AM24)-AI$7*AM24)/1.21) -> 0 | BC24: =IF(AN24=0,0,((Q24*AN24)-($Y$4*$Y$5*AN24)-AJ$7*AN24)/1.21) -> 0 | BD24: =IF(AO24=0,0,((R24*AO24)-($Y$4*$Y$5*AO24)-AK$7*AO24)/1.21) -> 0 | BE24: =SUM(AR24:BD24) -> 0 | BM24: =BL22-BM23 -> 87937 | BN24: =BN23-BM23 -> -90275
B25: Internet Rate / WIG Rate / BAR 10 | E25: 0.5 | F25: =IF(COUNTA($E25),F$11-(F$11*$E25),0) -> 3250000 | G25: =IF(COUNTA($E25),G$11-(G$11*$E25),0) -> 3500000 | H25: =IF(COUNTA($E25),H$11-(H$11*$E25),0) -> 3700000 | I25: =IF(COUNTA($E25),I$11-(I$11*$E25),0) -> 4600000 | J25: =IF(COUNTA($E25),J$11-(J$11*$E25),0) -> 5550000 | K25: =IF(COUNTA($E25),K$11-(K$11*$E25),0) -> 6900000 | L25: =IF(COUNTA($E25),L$11-(L$11*$E25),0) -> 7350000 | M25: =IF(COUNTA($E25),M$11-(M$11*$E25),0) -> 9200000 | ... R25: =IF(COUNTA($E25),R$11-(R$11*$E25),0) -> 28050000 | Y25: 0 | AC25: =$AC$15*Y25 -> 0 | AD25: =$AD$15*Y25 -> 0 | AE25: =$AE$15*Y25 -> 0 | AF25: =$AF$15*Y25 -> 0 | AG25: =$AG$15*Y25 -> 0 | AH25: =$AH$15*Y25 -> 0 | AI25: =$AI$15*Y25 -> 0 | AJ25: =$AJ$15*Y25 -> 0 | AK25: =$AK$15*Y25 -> 0 | AL25: =$AL$15*Y25 -> 0 | AM25: =$AM$15*Y25 -> 0 | AN25: =$AN$15*Y25 -> 0 | AO25: =$AO$15*Y25 -> 0 | AP25: =SUM(AC25:AO25) -> 0 | AR25: =IF(AC25=0,0,((F25*AC25)-($Y$4*$Y$5*AC25)-Y$7*AC25)/1.21) -> 0 | AS25: =IF(AD25=0,0,((G25*AD25)-($Y$4*$Y$5*AD25)-Z$7*AD25)/1.21) -> 0 | AT25: =IF(AE25=0,0,((H25*AE25)-($Y$4*$Y$5*AE25)-AA$7*AE25)/1.21) -> 0 | AU25: =IF(AF25=0,0,((I25*AF25)-($Y$4*$Y$5*AF25)-AB$7*AF25)/1.21) -> 0 | AV25: =IF(AG25=0,0,((J25*AG25)-($Y$4*$Y$5*AG25)-AC$7*AG25)/1.21) -> 0 | AW25: =IF(AH25=0,0,((K25*AH25)-($Y$4*$Y$5*AH25)-AD$7*AH25)/1.21) -> 0 | AX25: =IF(AI25=0,0,((L25*AI25)-($Y$4*$Y$5*AI25)-AE$7*AI25)/1.21) -> 0 | AY25: =IF(AJ25=0,0,((M25*AJ25)-($Y$4*$Y$5*AJ25)-AF$7*AJ25)/1.21) -> 0 | AZ25: =IF(AK25=0,0,((O25*AK25)-($Z$4*$Z$5*AK25)-AD18*AK25)/1.21) -> 0 | BA25: =IF(AL25=0,0,((N25*AL25)-($Y$4*$Y$5*AL25)-AH$7*AL25)/1.21) -> 0 | BB25: =IF(AM25=0,0,((P25*AM25)-($Y$4*$Y$5*AM25)-AI$7*AM25)/1.21) -> 0 | BC25: =IF(AN25=0,0,((Q25*AN25)-($Y$4*$Y$5*AN25)-AJ$7*AN25)/1.21) -> 0 | BD25: =IF(AO25=0,0,((R25*AO25)-($Y$4*$Y$5*AO25)-AK$7*AO25)/1.21) -> 0 | BE25: =SUM(AR25:BD25) -> 0
B26: Loyalti Program - My Value dan Kerjasama Merchant | F26: =F28-(F28*5%) -> 2309450 | G26: =G28-(G28*5%) -> 2487100 | H26: =H28-(H28*5%) -> 2629220 | I26: =I28-(I28*5%) -> 3268760 | J26: =J28-(J28*5%) -> 3943830 | K26: =K28-(K28*5%) -> 4903140 | L26: =L28-(L28*5%) -> 5222910 | M26: =M28-(M28*5%) -> 6537520 | ... R26: =R28-(R28*5%) -> 30804510 | Y26: 0 | AC26: =$AC$15*Y26 -> 0 | AD26: =$AD$15*Y26 -> 0 | AE26: =$AE$15*Y26 -> 0 | AF26: =$AF$15*Y26 -> 0 | AG26: =$AG$15*Y26 -> 0 | AH26: =$AH$15*Y26 -> 0 | AI26: =$AI$15*Y26 -> 0 | AJ26: =$AJ$15*Y26 -> 0 | AK26: =$AK$15*Y26 -> 0 | AL26: =$AL$15*Y26 -> 0 | AM26: =$AM$15*Y26 -> 0 | AN26: =$AN$15*Y26 -> 0 | AO26: =$AO$15*Y26 -> 0 | AP26: =SUM(AC26:AO26) -> 0 | AR26: =IF(AC26=0,0,((F26*AC26)-($Y$4*$Y$5*AC26)-Y$7*AC26)/1.21) -> 0 | AS26: =IF(AD26=0,0,((G26*AD26)-($Y$4*$Y$5*AD26)-Z$7*AD26)/1.21) -> 0 | AT26: =IF(AE26=0,0,((H26*AE26)-($Y$4*$Y$5*AE26)-AA$7*AE26)/1.21) -> 0 | AU26: =IF(AF26=0,0,((I26*AF26)-($Y$4*$Y$5*AF26)-AB$7*AF26)/1.21) -> 0 | AV26: =IF(AG26=0,0,((J26*AG26)-($Y$4*$Y$5*AG26)-AC$7*AG26)/1.21) -> 0 | AW26: =IF(AH26=0,0,((K26*AH26)-($Y$4*$Y$5*AH26)-AD$7*AH26)/1.21) -> 0 | AX26: =IF(AI26=0,0,((L26*AI26)-($Y$4*$Y$5*AI26)-AE$7*AI26)/1.21) -> 0 | AY26: =IF(AJ26=0,0,((M26*AJ26)-($Y$4*$Y$5*AJ26)-AF$7*AJ26)/1.21) -> 0 | AZ26: =IF(AK26=0,0,((O26*AK26)-($Z$4*$Z$5*AK26)-AD19*AK26)/1.21) -> 0 | BA26: =IF(AL26=0,0,((N26*AL26)-($Y$4*$Y$5*AL26)-AH$7*AL26)/1.21) -> 0 | BB26: =IF(AM26=0,0,((P26*AM26)-($Y$4*$Y$5*AM26)-AI$7*AM26)/1.21) -> 0 | BC26: =IF(AN26=0,0,((Q26*AN26)-($Y$4*$Y$5*AN26)-AJ$7*AN26)/1.21) -> 0 | BD26: =IF(AO26=0,0,((R26*AO26)-($Y$4*$Y$5*AO26)-AK$7*AO26)/1.21) -> 0 | BE26: =SUM(AR26:BD26) -> 0
B27: BAR APPLIED | F27: 8 | G27: =$F$27 -> 8 | H27: =$F$27 -> 8 | I27: =$F$27 -> 8 | J27: =$F$27 -> 8 | K27: =$F$27 -> 8 | L27: =$F$27 -> 8 | M27: =$F$27 -> 8 | N27: =$F$27 -> 8 | O27: =$F$27 -> 8 | P27: 2 | Q27: =$F$27 -> 8 | R27: 2
B28: Staycation Offer | E28: 0.32 | F28: =CHOOSE(F$27, F$16, F$17, F$18, F$19, F$20, F$21, F$22, F$23,F$24,F$25) * (1 - $E28) -> 2431000 | G28: =CHOOSE(G$27, G$16, G$17, G$18, G$19, G$20, G$21, G$22, G$23,G$24,G$25) * (1 - $E28) -> 2618000 | H28: =CHOOSE(H$27, H$16, H$17, H$18, H$19, H$20, H$21, H$22, H$23,H$24,H$25) * (1 - $E28) -> 2767600 | I28: =CHOOSE(I$27, I$16, I$17, I$18, I$19, I$20, I$21, I$22, I$23,I$24,I$25) * (1 - $E28) -> 3440800 | J28: =CHOOSE(J$27, J$16, J$17, J$18, J$19, J$20, J$21, J$22, J$23,J$24,J$25) * (1 - $E28) -> 4151400 | K28: =CHOOSE(K$27, K$16, K$17, K$18, K$19, K$20, K$21, K$22, K$23,K$24,K$25) * (1 - $E28) -> 5161200 | L28: =CHOOSE(L$27, L$16, L$17, L$18, L$19, L$20, L$21, L$22, L$23,L$24,L$25) * (1 - $E28) -> 5497800 | M28: =CHOOSE(M$27, M$16, M$17, M$18, M$19, M$20, M$21, M$22, M$23,M$24,M$25) * (1 - $E28) -> 6881600 | ... R28: =CHOOSE(R$27, R$16, R$17, R$18, R$19, R$20, R$21, R$22, R$23,R$24,R$25) * (1 - $E28) -> 32425800 | T28: VARIANCE | Y28: 0.19 | AC28: =$AC$15*Y28 -> 9854.1893 | AD28: =$AD$15*Y28+472 -> 1840.6374 | AE28: =$AE$15*Y28 -> 12673.582 | AF28: =$AF$15*Y28+755.3 -> 2945.1198 | AG28: =$AG$15*Y28+164.4 -> 438.12748 | AH28: =$AH$15*Y28+94.4 -> 368.12748 | AI28: =$AI$15*Y28+47.2 -> 184.06374 | AJ28: =$AJ$15*Y28+47.2 -> 184.06374 | AK28: =$AK$15*Y28+37.8 -> 147.29099 | AL28: =$AL$15*Y28+94.4 -> 368.12748 | AM28: =$AM$15*Y28+15+9.4 -> 51.772748 | AN28: =$AN$15*Y28+9.4 -> 36.772748 | AO28: =$AO$15*Y28+9.4 -> 36.772748 | AP28: =SUM(AC28:AO28) -> 29128.648 | AR28: =IF(AC28=0,0,((F28*AC28)-($Y$4*$Y$5*AC28)-Y$7*AC28)/1.21)-323320739.77 -> 1.9474641e+10 | AS28: =IF(AD28=0,0,((G28*AD28)-($Y$4*$Y$5*AD28)-Z$7*AD28)/1.21) -> 3.98247e+09 | AT28: =IF(AE28=0,0,((H28*AE28)-($Y$4*$Y$5*AE28)-AA$7*AE28)/1.21)-323320737.77 -> 2.8664618e+10 | AU28: =IF(AF28=0,0,((I28*AF28)-($Y$4*$Y$5*AF28)-AB$7*AF28)/1.21)-323320737.77 -> 8.0515291e+09 | AV28: =IF(AG28=0,0,((J28*AG28)-($Y$4*$Y$5*AG28)-AC$7*AG28)/1.21) -> 1.5031756e+09 | AW28: =IF(AH28=0,0,((K28*AH28)-($Y$4*$Y$5*AH28)-AD$7*AH28)/1.21) -> 1.570231e+09 | AX28: =IF(AI28=0,0,((L28*AI28)-($Y$4*$Y$5*AI28)-AE$7*AI28)/1.21) -> 8.363187e+08 | AZ28: =IF(AK28=0,0,((O28*AK28)-($Z$4*$Z$5*AK28)-AD20*AK28)/1.21) -> 8.8104359e+08 | BA28: =IF(AL28=0,0,((N28*AL28)-($Y$4*$Y$5*AL28)-AH$7*AL28)/1.21) -> 2.2756971e+09 | BB28: =IF(AM28=0,0,((P28*AM28)-($Y$4*$Y$5*AM28)-AI$7*AM28)/1.21) -> 4.9956851e+08 | BC28: =IF(AN28=0,0,((Q28*AN28)-($Y$4*$Y$5*AN28)-AJ$7*AN28)/1.21) -> 3.0233885e+08 | BE28: =SUM(AR28:BD28) -> 6.8041632e+10
B29: Flexible Staycation Offer | E29: 0.27 | F29: =CHOOSE(F$27, F$16, F$17, F$18, F$19, F$20, F$21, F$22, F$23, F$24, F$25) * (1 - $E29) -> 2609750 | G29: =CHOOSE(G$27, G$16, G$17, G$18, G$19, G$20, G$21, G$22, G$23, G$24, G$25) * (1 - $E29) -> 2810500 | H29: =CHOOSE(H$27, H$16, H$17, H$18, H$19, H$20, H$21, H$22, H$23, H$24, H$25) * (1 - $E29) -> 2971100 | I29: =CHOOSE(I$27, I$16, I$17, I$18, I$19, I$20, I$21, I$22, I$23, I$24, I$25) * (1 - $E29) -> 3693800 | J29: =CHOOSE(J$27, J$16, J$17, J$18, J$19, J$20, J$21, J$22, J$23, J$24, J$25) * (1 - $E29) -> 4456650 | K29: =CHOOSE(K$27, K$16, K$17, K$18, K$19, K$20, K$21, K$22, K$23, K$24, K$25) * (1 - $E29) -> 5540700 | L29: =CHOOSE(L$27, L$16, L$17, L$18, L$19, L$20, L$21, L$22, L$23, L$24, L$25) * (1 - $E29) -> 5902050 | M29: =CHOOSE(M$27, M$16, M$17, M$18, M$19, M$20, M$21, M$22, M$23, M$24, M$25) * (1 - $E29) -> 7387600 | ... R29: =CHOOSE(R$27, R$16, R$17, R$18, R$19, R$20, R$21, R$22, R$23, R$24, R$25) * (1 - $E29) -> 34810050 | T29: Room Sold | U29: : | V29: =V22-V17 -> 0 | Y29: 0.09 | AC29: =$AC$15*Y29 -> 4667.7739 | AD29: =$AD$15*Y29 -> 648.30192 | AE29: =$AE$15*Y29 -> 6003.2758 | AF29: =$AF$15*Y29+1215.4 -> 2252.6831 | AG29: =$AG$15*Y29 -> 129.66038 | AH29: =$AH$15*Y29+151.9 -> 281.56038 | AI29: =$AI$15*Y29+76 -> 140.83019 | AJ29: =$AJ$15*Y29+76 -> 140.83019 | AK29: =$AK$15*Y29+60.8 -> 112.66415 | AL29: =$AL$15*Y29+151.9 -> 281.56038 | AM29: =$AM$15*Y29+15+15.2 -> 43.166038 | AN29: =$AN$15*Y29+15.2 -> 28.166038 | AO29: =$AO$15*Y29+15.2 -> 28.166038 | AP29: =SUM(AC29:AO29) -> 14758.638 | AR29: =IF(AC29=0,0,((F29*AC29)-($Y$4*$Y$5*AC29)-Y$7*AC29)/1.21)-323320737.77+134166431 -> 9.8783852e+09 | AS29: =IF(AD29=0,0,((G29*AD29)-($Y$4*$Y$5*AD29)-Z$7*AD29)/1.21)-323320737.77 -> 1.1825078e+09 | AT29: =IF(AE29=0,0,((H29*AE29)-($Y$4*$Y$5*AE29)-AA$7*AE29)/1.21)-323320737.77 -> 1.441745e+10 | AU29: =IF(AF29=0,0,((I29*AF29)-($Y$4*$Y$5*AF29)-AB$7*AF29)/1.21)-323320737.77 -> 6.5535063e+09 | AV29: =IF(AG29=0,0,((J29*AG29)-($Y$4*$Y$5*AG29)-AC$7*AG29)/1.21) -> 4.7756277e+08 | AW29: =IF(AH29=0,0,((K29*AH29)-($Y$4*$Y$5*AH29)-AD$7*AH29)/1.21) -> 1.2892906e+09 | AX29: =IF(AI29=0,0,((L29*AI29)-($Y$4*$Y$5*AI29)-AE$7*AI29)/1.21) -> 6.8693127e+08 | AZ29: =IF(AK29=0,0,((O29*AK29)-($Z$4*$Z$5*AK29)-AD21*AK29)/1.21) -> 7.2692123e+08 | BA29: =IF(AL29=0,0,((N29*AL29)-($Y$4*$Y$5*AL29)-AH$7*AL29)/1.21) -> 1.8685371e+09 | BB29: =IF(AM29=0,0,((P29*AM29)-($Y$4*$Y$5*AM29)-AI$7*AM29)/1.21) -> 4.4714665e+08 | BC29: =IF(AN29=0,0,((Q29*AN29)-($Y$4*$Y$5*AN29)-AJ$7*AN29)/1.21) -> 2.486037e+08 | BE29: =SUM(AR29:BD29) -> 3.7776843e+10
B30: EBO | E30: 0.35 | F30: =CHOOSE(F$27, F$16, F$17, F$18, F$19, F$20, F$21, F$22, F$23, F$24, F$25) * (1 - $E30) -> 2323750 | G30: =CHOOSE(G$27, G$16, G$17, G$18, G$19, G$20, G$21, G$22, G$23, G$24, G$25) * (1 - $E30) -> 2502500 | H30: =CHOOSE(H$27, H$16, H$17, H$18, H$19, H$20, H$21, H$22, H$23, H$24, H$25) * (1 - $E30) -> 2645500 | I30: =CHOOSE(I$27, I$16, I$17, I$18, I$19, I$20, I$21, I$22, I$23, I$24, I$25) * (1 - $E30) -> 3289000 | J30: =CHOOSE(J$27, J$16, J$17, J$18, J$19, J$20, J$21, J$22, J$23, J$24, J$25) * (1 - $E30) -> 3968250 | K30: =CHOOSE(K$27, K$16, K$17, K$18, K$19, K$20, K$21, K$22, K$23, K$24, K$25) * (1 - $E30) -> 4933500 | L30: =CHOOSE(L$27, L$16, L$17, L$18, L$19, L$20, L$21, L$22, L$23, L$24, L$25) * (1 - $E30) -> 5255250 | M30: =CHOOSE(M$27, M$16, M$17, M$18, M$19, M$20, M$21, M$22, M$23, M$24, M$25) * (1 - $E30) -> 6578000 | ... R30: =CHOOSE(R$27, R$16, R$17, R$18, R$19, R$20, R$21, R$22, R$23, R$24, R$25) * (1 - $E30) -> 30995250 | T30: Room Revenue | U30: : | V30: =V23-V18 -> #REF! | Y30: 0.09 | AC30: =$AC$15*Y30 -> 4667.7739 | AD30: =$AD$15*Y30+471.4 -> 1119.7019 | AE30: =$AE$15*Y30 -> 6003.2758 | AF30: =$AF$15*Y30+754.2 -> 1791.4831 | AG30: =$AG$15*Y30+188.5 -> 318.16038 | AH30: =$AH$15*Y30+94.3 -> 223.96038 | AI30: =$AI$15*Y30+47.1 -> 111.93019 | AJ30: =$AJ$15*Y30+47.1 -> 111.93019 | AK30: =$AK$15*Y30+37.7 -> 89.564154 | AL30: =$AL$15*Y30+94.3 -> 223.96038 | AM30: =$AM$15*Y30+15+9.4 -> 37.366038 | AN30: =$AN$15*Y30+9.4 -> 22.366038 | AO30: =$AO$15*Y30+9.4 -> 22.366038 | AP30: =SUM(AC30:AO30) -> 14743.838 | AR30: =IF(AC30=0,0,((F30*AC30)-($Y$4*$Y$5*AC30)-Y$7*AC30)/1.21)-323320737.77 -> 8.6409268e+09 | AS30: =IF(AD30=0,0,((G30*AD30)-($Y$4*$Y$5*AD30)-Z$7*AD30)/1.21) -> 2.3157472e+09 | AT30: =IF(AE30=0,0,((H30*AE30)-($Y$4*$Y$5*AE30)-AA$7*AE30)/1.21)-323320737.77-323320737.77-323320737.77-323320737.77-323320737.77 -> 1.150874e+10 | AU30: =IF(AF30=0,0,((I30*AF30)-($Y$4*$Y$5*AF30)-AB$7*AF30)/1.21) -> 4.8695767e+09 | AV30: =IF(AG30=0,0,((J30*AG30)-($Y$4*$Y$5*AG30)-AC$7*AG30)/1.21) -> 1.0434214e+09 | AW30: =IF(AH30=0,0,((K30*AH30)-($Y$4*$Y$5*AH30)-AD$7*AH30)/1.21) -> 9.1314757e+08 | AX30: =IF(AI30=0,0,((L30*AI30)-($Y$4*$Y$5*AI30)-AE$7*AI30)/1.21) -> 4.8613318e+08 | AZ30: =IF(AK30=0,0,((O30*AK30)-($Z$4*$Z$5*AK30)-AD22*AK30)/1.21) -> 5.1046016e+08 | BA30: =IF(AL30=0,0,((N30*AL30)-($Y$4*$Y$5*AL30)-AH$7*AL30)/1.21) -> 1.3234023e+09 | BB30: =IF(AM30=0,0,((P30*AM30)-($Y$4*$Y$5*AM30)-AI$7*AM30)/1.21) -> 3.4464766e+08 | BC30: =IF(AN30=0,0,((Q30*AN30)-($Y$4*$Y$5*AN30)-AJ$7*AN30)/1.21) -> 1.7577673e+08 | BE30: =SUM(AR30:BD30) -> 3.213198e+10
B31: GAP | F31: 0.12 | G31: 0.12 | H31: 0.12 | I31: 0.12 | J31: 0.12 | K31: 0.07 | L31: 0.07 | M31: 0.07 | N31: 0.07 | O31: 0.07 | P31: 0.07 | Q31: 0.07 | R31: 0.07
B32: Corporate New | F32: =CEILING(F28-(F28*F31),50000) -> 2150000 | G32: =CEILING(G28-(G28*G31),50000) -> 2350000 | H32: =CEILING(H28-(H28*H31),50000) -> 2450000 | I32: =CEILING(I28-(I28*I31),50000) -> 3050000 | J32: =CEILING(J28-(J28*J31),50000) -> 3700000 | K32: =CEILING(K28-(K28*K31),50000) -> 4800000 | L32: =CEILING(L28-(L28*L31),50000) -> 5150000 | M32: =CEILING(M28-(M28*M31),50000) -> 6400000 | ... R32: =CEILING(R28-(R28*R31),50000) -> 30200000 | X32: =SUM(Y32:Y40) -> 0.03 | Y32: 0 | Z32: 0.034439869 | AA32: 0.081267918 | AC32: =$AC$15*Y32 -> 0 | AD32: =$AD$15*Y32 -> 0 | AE32: =$AE$15*Y32 -> 0 | AF32: =$AF$15*Y32 -> 0 | AG32: =$AG$15*Y32 -> 0 | AH32: =$AH$15*Y32 -> 0 | AI32: =$AI$15*Y32 -> 0 | AJ32: =$AJ$15*Y32 -> 0 | AK32: =$AK$15*Y32 -> 0 | AL32: =$AL$15*Y32 -> 0 | AM32: =$AM$15*Y32 -> 0 | AN32: =$AN$15*Y32 -> 0 | AO32: =$AO$15*Y32 -> 0 | AP32: =SUM(AC32:AO32) -> 0 | AR32: =IF(AC32=0,0,((F32*AC32)-($Y$4*$Y$5*AC32)-Y$7*AC32)/1.21) -> 0 | AS32: =IF(AD32=0,0,((G32*AD32)-($Y$4*$Y$5*AD32)-Z$7*AD32)/1.21) -> 0 | AT32: =IF(AE32=0,0,((H32*AE32)-($Y$4*$Y$5*AE32)-AA$7*AE32)/1.21) -> 0 | AU32: =IF(AF32=0,0,((I32*AF32)-($Y$4*$Y$5*AF32)-AB$7*AF32)/1.21) -> 0 | AV32: =IF(AG32=0,0,((J32*AG32)-($Y$4*$Y$5*AG32)-AC$7*AG32)/1.21) -> 0 | AW32: =IF(AH32=0,0,((K32*AH32)-($Y$4*$Y$5*AH32)-AD$7*AH32)/1.21) -> 0 | AX32: =IF(AI32=0,0,((L32*AI32)-($Y$4*$Y$5*AI32)-AE$7*AI32)/1.21) -> 0 | AY32: =IF(AJ32=0,0,((M32*AJ32)-($Y$4*$Y$5*AJ32)-AF$7*AJ32)/1.21) -> 0 | AZ32: =IF(AK32=0,0,((O32*AK32)-($Z$4*$Z$5*AK32)-AD28*AK32)/1.21) -> 0 | BA32: =IF(AL32=0,0,((N32*AL32)-($Y$4*$Y$5*AL32)-AH$7*AL32)/1.21) -> 0 | BB32: =IF(AM32=0,0,((P32*AM32)-($Y$4*$Y$5*AM32)-AI$7*AM32)/1.21) -> 0 | BC32: =IF(AN32=0,0,((Q32*AN32)-($Y$4*$Y$5*AN32)-AJ$7*AN32)/1.21) -> 0 | BD32: =IF(AO32=0,0,((R32*AO32)-($Y$4*$Y$5*AO32)-AK$7*AO32)/1.21) -> 0 | BE32: =SUM(AR32:BD32) -> 0 | BF32: =SUM(BE32:BE40) -> 9.0623534e+09 | BG32: Corp | BH32: 7481949530 | BI32: =BH32-BF32 -> -1.5804038e+09
B33: Corporate Productive | F33: =F32-50000 -> 2100000 | G33: =G32-50000 -> 2300000 | H33: =H32-50000 -> 2400000 | I33: =I32-50000 -> 3000000 | J33: =J32-50000 -> 3650000 | K33: =K32-50000 -> 4750000 | L33: =L32-50000 -> 5100000 | M33: =M32-50000 -> 6350000 | ... R33: =R32-50000 -> 30150000 | Y33: 0.005 | AC33: =$AC$15*Y33 -> 259.32077 | AD33: =$AD$15*Y33 -> 36.016774 | AE33: =$AE$15*Y33 -> 333.51532 | AF33: =$AF$15*Y33 -> 57.626838 | AG33: =$AG$15*Y33 -> 7.2033547 | AH33: =$AH$15*Y33 -> 7.2033547 | AI33: =$AI$15*Y33 -> 3.6016774 | AJ33: =$AJ$15*Y33 -> 3.6016774 | AK33: =$AK$15*Y33 -> 2.8813419 | AL33: =$AL$15*Y33 -> 7.2033547 | AN33: =$AN$15*Y33 -> 0.72033547 | AO33: =$AO$15*Y33 -> 0.72033547 | AP33: =SUM(AC33:AO33) -> 719.61514 | AR33: =IF(AC33=0,0,((F33*AC33)-($Y$4*$Y$5*AC33)-Y$7*AC33)/1.21)+303641628 -> 7.5370247e+08 | AT33: =IF(AE33=0,0,((H33*AE33)-($Y$4*$Y$5*AE33)-AA$7*AE33)/1.21)+303641628 -> 9.6515962e+08 | AV33: =IF(AG33=0,0,((J33*AG33)-($Y$4*$Y$5*AG33)-AC$7*AG33)/1.21) -> 21729128 | BB33: =IF(AM33=0,0,((P33*AM33)-($Y$4*$Y$5*AM33)-AI$7*AM33)/1.21) -> 0 | BE33: =SUM(AR33:BD33) -> 1.7405912e+09
B34: Corporate Super Productive | F34: =F33-50000 -> 2050000 | G34: =G33-50000 -> 2250000 | H34: =H33-50000 -> 2350000 | I34: =I33-50000 -> 2950000 | J34: =J33-50000 -> 3600000 | K34: =K33-50000 -> 4700000 | L34: =L33-50000 -> 5050000 | M34: =M33-50000 -> 6300000 | ... R34: =R33-50000 -> 30100000 | Y34: 0.025 | AC34: =$AC$15*Y34 -> 1296.6038 | AD34: =$AD$15*Y34 -> 180.08387 | AE34: =$AE$15*Y34 -> 1667.5766 | AF34: =$AF$15*Y34 -> 288.13419 | AG34: =$AG$15*Y34 -> 36.016774 | AH34: =$AH$15*Y34 -> 36.016774 | AI34: =$AI$15*Y34 -> 18.008387 | AJ34: =$AJ$15*Y34 -> 18.008387 | AK34: =$AK$15*Y34 -> 14.406709 | AL34: =$AL$15*Y34 -> 36.016774 | AM34: =$AM$15*Y34 -> 3.6016774 | AN34: =$AN$15*Y34 -> 3.6016774 | AO34: =$AO$15*Y34 -> 3.6016774 | AP34: =SUM(AC34:AO34) -> 3601.6774 | AR34: =IF(AC34=0,0,((F34*AC34)-($Y$4*$Y$5*AC34)-Y$7*AC34)/1.21) -> 2.1967255e+09 | AS34: =IF(AD34=0,0,((G34*AD34)-($Y$4*$Y$5*AD34)-Z$7*AD34)/1.21) -> 3.348667e+08 | AT34: =IF(AE34=0,0,((H34*AE34)-($Y$4*$Y$5*AE34)-AA$7*AE34)/1.21) -> 3.2386819e+09 | AU34: =IF(AF34=0,0,((I34*AF34)-($Y$4*$Y$5*AF34)-AB$7*AF34)/1.21) -> 7.0247591e+08 | AV34: =IF(AG34=0,0,((J34*AG34)-($Y$4*$Y$5*AG34)-AC$7*AG34)/1.21) -> 1.0715734e+08 | AW34: =IF(AH34=0,0,((K34*AH34)-($Y$4*$Y$5*AH34)-AD$7*AH34)/1.21) -> 1.3989986e+08 | AX34: =IF(AI34=0,0,((L34*AI34)-($Y$4*$Y$5*AI34)-AE$7*AI34)/1.21) -> 75158970 | AY34: =IF(AJ34=0,0,((M34*AJ34)-($Y$4*$Y$5*AJ34)-AF$7*AJ34)/1.21) -> 93762675 | AZ34: =IF(AK34=0,0,((O34*AK34)-($Z$4*$Z$5*AK34)-AD30*AK34)/1.21) -> 78521094 | BA34: =IF(AL34=0,0,((N34*AL34)-($Y$4*$Y$5*AL34)-AH$7*AL34)/1.21) -> 2.0538491e+08 | BB34: =IF(AM34=0,0,((P34*AM34)-($Y$4*$Y$5*AM34)-AI$7*AM34)/1.21) -> 32147203 | BC34: =IF(AN34=0,0,((Q34*AN34)-($Y$4*$Y$5*AN34)-AJ$7*AN34)/1.21) -> 27384654 | BD34: =IF(AO34=0,0,((R34*AO34)-($Y$4*$Y$5*AO34)-AK$7*AO34)/1.21) -> 89595445 | BE34: =SUM(AR34:BD34) -> 7.3217622e+09
B35: NKA | F35: =F34-50000 -> 2000000 | G35: =G34-50000 -> 2200000 | H35: =H34-50000 -> 2300000 | I35: =I34-50000 -> 2900000 | J35: =J34-50000 -> 3550000 | K35: =K34-50000 -> 4650000 | L35: =L34-50000 -> 5000000 | M35: =M34-50000 -> 6250000 | ... R35: =R34-50000 -> 30050000 | Y35: 0 | AC35: =$AC$15*Y35 -> 0 | AD35: =$AD$15*Y35 -> 0 | AE35: =$AE$15*Y35 -> 0 | AF35: =$AF$15*Y35 -> 0 | AG35: =$AG$15*Y35 -> 0 | AH35: =$AH$15*Y35 -> 0 | AI35: =$AI$15*Y35 -> 0 | AJ35: =$AJ$15*Y35 -> 0 | AK35: =$AK$15*Y35 -> 0 | AL35: =$AL$15*Y35 -> 0 | AM35: =$AM$15*Y35 -> 0 | AN35: =$AN$15*Y35 -> 0 | AO35: =$AO$15*Y35 -> 0 | AP35: =SUM(AC35:AO35) -> 0 | AR35: =IF(AC35=0,0,((F35*AC35)-($Y$4*$Y$5*AC35)-Y$7*AC35)/1.21) -> 0 | AS35: =IF(AD35=0,0,((G35*AD35)-($Y$4*$Y$5*AD35)-Z$7*AD35)/1.21) -> 0 | AT35: =IF(AE35=0,0,((H35*AE35)-($Y$4*$Y$5*AE35)-AA$7*AE35)/1.21) -> 0 | AU35: =IF(AF35=0,0,((I35*AF35)-($Y$4*$Y$5*AF35)-AB$7*AF35)/1.21) -> 0 | AV35: =IF(AG35=0,0,((J35*AG35)-($Y$4*$Y$5*AG35)-AC$7*AG35)/1.21) -> 0 | AW35: =IF(AH35=0,0,((K35*AH35)-($Y$4*$Y$5*AH35)-AD$7*AH35)/1.21) -> 0 | AX35: =IF(AI35=0,0,((L35*AI35)-($Y$4*$Y$5*AI35)-AE$7*AI35)/1.21) -> 0 | AY35: =IF(AJ35=0,0,((M35*AJ35)-($Y$4*$Y$5*AJ35)-AF$7*AJ35)/1.21) -> 0 | AZ35: =IF(AK35=0,0,((O35*AK35)-($Z$4*$Z$5*AK35)-#REF!*AK35)/1.21) -> 0 | BA35: =IF(AL35=0,0,((N35*AL35)-($Y$4*$Y$5*AL35)-AH$7*AL35)/1.21) -> 0 | BB35: =IF(AM35=0,0,((P35*AM35)-($Y$4*$Y$5*AM35)-AI$7*AM35)/1.21) -> 0 | BC35: =IF(AN35=0,0,((Q35*AN35)-($Y$4*$Y$5*AN35)-AJ$7*AN35)/1.21) -> 0 | BD35: =IF(AO35=0,0,((R35*AO35)-($Y$4*$Y$5*AO35)-AK$7*AO35)/1.21) -> 0 | BE35: =SUM(AR35:BD35) -> 0
B36: Corporate Preffered 2 (ad hoc - based) | F36: =F35-50000 -> 1950000 | G36: =G35-50000 -> 2150000 | H36: =H35-50000 -> 2250000 | I36: =I35-50000 -> 2850000 | J36: =J35-50000 -> 3500000 | K36: =K35-50000 -> 4600000 | L36: =L35-50000 -> 4950000 | M36: =M35-50000 -> 6200000 | ... R36: =R35-50000 -> 30000000 | Y36: 0 | AC36: =$AC$15*Y36 -> 0 | AD36: =$AD$15*Y36 -> 0 | AE36: =$AE$15*Y36 -> 0 | AF36: =$AF$15*Y36 -> 0 | AG36: =$AG$15*Y36 -> 0 | AH36: =$AH$15*Y36 -> 0 | AI36: =$AI$15*Y36 -> 0 | AJ36: =$AJ$15*Y36 -> 0 | AK36: =$AK$15*Y36 -> 0 | AL36: =$AL$15*Y36 -> 0 | AM36: =$AM$15*Y36 -> 0 | AN36: =$AN$15*Y36 -> 0 | AO36: =$AO$15*Y36 -> 0 | AP36: =SUM(AC36:AO36) -> 0 | AR36: =IF(AC36=0,0,((F36*AC36)-($Y$4*$Y$5*AC36)-Y$7*AC36)/1.21) -> 0 | AS36: =IF(AD36=0,0,((G36*AD36)-($Y$4*$Y$5*AD36)-Z$7*AD36)/1.21) -> 0 | AT36: =IF(AE36=0,0,((H36*AE36)-($Y$4*$Y$5*AE36)-AA$7*AE36)/1.21) -> 0 | AU36: =IF(AF36=0,0,((I36*AF36)-($Y$4*$Y$5*AF36)-AB$7*AF36)/1.21) -> 0 | AV36: =IF(AG36=0,0,((J36*AG36)-($Y$4*$Y$5*AG36)-AC$7*AG36)/1.21) -> 0 | AW36: =IF(AH36=0,0,((K36*AH36)-($Y$4*$Y$5*AH36)-AD$7*AH36)/1.21) -> 0 | AX36: =IF(AI36=0,0,((L36*AI36)-($Y$4*$Y$5*AI36)-AE$7*AI36)/1.21) -> 0 | AY36: =IF(AJ36=0,0,((M36*AJ36)-($Y$4*$Y$5*AJ36)-AF$7*AJ36)/1.21) -> 0 | AZ36: =IF(AK36=0,0,((O36*AK36)-($Z$4*$Z$5*AK36)-#REF!*AK36)/1.21) -> 0 | BA36: =IF(AL36=0,0,((N36*AL36)-($Y$4*$Y$5*AL36)-AH$7*AL36)/1.21) -> 0 | BB36: =IF(AM36=0,0,((P36*AM36)-($Y$4*$Y$5*AM36)-AI$7*AM36)/1.21) -> 0 | BC36: =IF(AN36=0,0,((Q36*AN36)-($Y$4*$Y$5*AN36)-AJ$7*AN36)/1.21) -> 0 | BD36: =IF(AO36=0,0,((R36*AO36)-($Y$4*$Y$5*AO36)-AK$7*AO36)/1.21) -> 0 | BE36: =SUM(AR36:BD36) -> 0
B37: Corporate Preffered 3 | F37: 0 | G37: =IF(F37=0,0,F37+$G$15) -> 0 | H37: =IF(F37=0,0,F37+$H$15) -> 0 | I37: =IF(F37=0,0,F37+$I$15) -> 0 | J37: =F37+$J$15 -> 0 | K37: =F37+$K$15 -> 0 | L37: =F37+$L$15 -> 0 | M37: =G37+$L$15 -> 0 | N37: =I37+$L$15 -> 0 | O37: =H37+$L$15 -> 0 | P37: =J37+$L$15 -> 0 | Q37: =K37+$L$15 -> 0 | R37: =L37+$L$15 -> 0 | Y37: 0 | AC37: =$AC$15*Y37 -> 0 | AD37: =$AD$15*Y37 -> 0 | AE37: =$AE$15*Y37 -> 0 | AF37: =$AF$15*Y37 -> 0 | AG37: =$AG$15*Y37 -> 0 | AH37: =$AH$15*Y37 -> 0 | AI37: =$AI$15*Y37 -> 0 | AJ37: =$AJ$15*Y37 -> 0 | AK37: =$AK$15*Y37 -> 0 | AL37: =$AL$15*Y37 -> 0 | AM37: =$AM$15*Y37 -> 0 | AN37: =$AN$15*Y37 -> 0 | AO37: =$AO$15*Y37 -> 0 | AP37: =SUM(AC37:AO37) -> 0 | AR37: =IF(AC37=0,0,((F37*AC37)-($Y$4*$Y$5*AC37)-Y$7*AC37)/1.21) -> 0 | AS37: =IF(AD37=0,0,((G37*AD37)-($Y$4*$Y$5*AD37)-Z$7*AD37)/1.21) -> 0 | AT37: =IF(AE37=0,0,((H37*AE37)-($Y$4*$Y$5*AE37)-AA$7*AE37)/1.21) -> 0 | AU37: =IF(AF37=0,0,((I37*AF37)-($Y$4*$Y$5*AF37)-AB$7*AF37)/1.21) -> 0 | AV37: =IF(AG37=0,0,((J37*AG37)-($Y$4*$Y$5*AG37)-AC$7*AG37)/1.21) -> 0 | AW37: =IF(AH37=0,0,((K37*AH37)-($Y$4*$Y$5*AH37)-AD$7*AH37)/1.21) -> 0 | AX37: =IF(AI37=0,0,((L37*AI37)-($Y$4*$Y$5*AI37)-AE$7*AI37)/1.21) -> 0 | AY37: =IF(AJ37=0,0,((M37*AJ37)-($Y$4*$Y$5*AJ37)-AF$7*AJ37)/1.21) -> 0 | AZ37: =IF(AK37=0,0,((O37*AK37)-($Z$4*$Z$5*AK37)-#REF!*AK37)/1.21) -> 0 | BA37: =IF(AL37=0,0,((N37*AL37)-($Y$4*$Y$5*AL37)-AH$7*AL37)/1.21) -> 0 | BB37: =IF(AM37=0,0,((P37*AM37)-($Y$4*$Y$5*AM37)-AI$7*AM37)/1.21) -> 0 | BC37: =IF(AN37=0,0,((Q37*AN37)-($Y$4*$Y$5*AN37)-AJ$7*AN37)/1.21) -> 0 | BD37: =IF(AO37=0,0,((R37*AO37)-($Y$4*$Y$5*AO37)-AK$7*AO37)/1.21) -> 0 | BE37: =SUM(AR37:BD37) -> 0
B38: Corporate Preffered 4 | F38: 0 | G38: =IF(F38=0,0,F38+$G$15) -> 0 | H38: =IF(F38=0,0,F38+$H$15) -> 0 | I38: =IF(F38=0,0,F38+$I$15) -> 0 | J38: =F38+$J$15 -> 0 | K38: =F38+$K$15 -> 0 | L38: =F38+$L$15 -> 0 | M38: =G38+$L$15 -> 0 | N38: =I38+$L$15 -> 0 | O38: =H38+$L$15 -> 0 | P38: =J38+$L$15 -> 0 | Q38: =K38+$L$15 -> 0 | R38: =L38+$L$15 -> 0 | Y38: 0 | AC38: =$AC$15*Y38 -> 0 | AD38: =$AD$15*Y38 -> 0 | AE38: =$AE$15*Y38 -> 0 | AF38: =$AF$15*Y38 -> 0 | AG38: =$AG$15*Y38 -> 0 | AH38: =$AH$15*Y38 -> 0 | AI38: =$AI$15*Y38 -> 0 | AJ38: =$AJ$15*Y38 -> 0 | AK38: =$AK$15*Y38 -> 0 | AL38: =$AL$15*Y38 -> 0 | AM38: =$AM$15*Y38 -> 0 | AN38: =$AN$15*Y38 -> 0 | AO38: =$AO$15*Y38 -> 0 | AP38: =SUM(AC38:AO38) -> 0 | AR38: =IF(AC38=0,0,((F38*AC38)-($Y$4*$Y$5*AC38)-Y$7*AC38)/1.21) -> 0 | AS38: =IF(AD38=0,0,((G38*AD38)-($Y$4*$Y$5*AD38)-Z$7*AD38)/1.21) -> 0 | AT38: =IF(AE38=0,0,((H38*AE38)-($Y$4*$Y$5*AE38)-AA$7*AE38)/1.21) -> 0 | AU38: =IF(AF38=0,0,((I38*AF38)-($Y$4*$Y$5*AF38)-AB$7*AF38)/1.21) -> 0 | AV38: =IF(AG38=0,0,((J38*AG38)-($Y$4*$Y$5*AG38)-AC$7*AG38)/1.21) -> 0 | AW38: =IF(AH38=0,0,((K38*AH38)-($Y$4*$Y$5*AH38)-AD$7*AH38)/1.21) -> 0 | AX38: =IF(AI38=0,0,((L38*AI38)-($Y$4*$Y$5*AI38)-AE$7*AI38)/1.21) -> 0 | AY38: =IF(AJ38=0,0,((M38*AJ38)-($Y$4*$Y$5*AJ38)-AF$7*AJ38)/1.21) -> 0 | AZ38: =IF(AK38=0,0,((O38*AK38)-($Z$4*$Z$5*AK38)-AD32*AK38)/1.21) -> 0 | BA38: =IF(AL38=0,0,((N38*AL38)-($Y$4*$Y$5*AL38)-AH$7*AL38)/1.21) -> 0 | BB38: =IF(AM38=0,0,((P38*AM38)-($Y$4*$Y$5*AM38)-AI$7*AM38)/1.21) -> 0 | BC38: =IF(AN38=0,0,((Q38*AN38)-($Y$4*$Y$5*AN38)-AJ$7*AN38)/1.21) -> 0 | BD38: =IF(AO38=0,0,((R38*AO38)-($Y$4*$Y$5*AO38)-AK$7*AO38)/1.21) -> 0 | BE38: =SUM(AR38:BD38) -> 0
B39: Corporate Promotion 1 | F39: 0 | G39: =IF(F39=0,0,F39+$G$15) -> 0 | H39: =IF(F39=0,0,F39+$H$15) -> 0 | I39: =IF(F39=0,0,F39+$I$15) -> 0 | J39: =F39+$J$15 -> 0 | K39: =F39+$K$15 -> 0 | L39: =F39+$L$15 -> 0 | M39: =G39+$L$15 -> 0 | N39: =I39+$L$15 -> 0 | O39: =H39+$L$15 -> 0 | P39: =J39+$L$15 -> 0 | Q39: =K39+$L$15 -> 0 | R39: =L39+$L$15 -> 0 | Y39: 0 | AC39: =$AC$15*Y39 -> 0 | AD39: =$AD$15*Y39 -> 0 | AE39: =$AE$15*Y39 -> 0 | AF39: =$AF$15*Y39 -> 0 | AG39: =$AG$15*Y39 -> 0 | AH39: =$AH$15*Y39 -> 0 | AI39: =$AI$15*Y39 -> 0 | AJ39: =$AJ$15*Y39 -> 0 | AK39: =$AK$15*Y39 -> 0 | AL39: =$AL$15*Y39 -> 0 | AM39: =$AM$15*Y39 -> 0 | AN39: =$AN$15*Y39 -> 0 | AO39: =$AO$15*Y39 -> 0 | AP39: =SUM(AC39:AO39) -> 0 | AR39: =IF(AC39=0,0,((F39*AC39)-($Y$4*$Y$5*AC39)-Y$7*AC39)/1.21) -> 0 | AS39: =IF(AD39=0,0,((G39*AD39)-($Y$4*$Y$5*AD39)-Z$7*AD39)/1.21) -> 0 | AT39: =IF(AE39=0,0,((H39*AE39)-($Y$4*$Y$5*AE39)-AA$7*AE39)/1.21) -> 0 | AU39: =IF(AF39=0,0,((I39*AF39)-($Y$4*$Y$5*AF39)-AB$7*AF39)/1.21) -> 0 | AV39: =IF(AG39=0,0,((J39*AG39)-($Y$4*$Y$5*AG39)-AC$7*AG39)/1.21) -> 0 | AW39: =IF(AH39=0,0,((K39*AH39)-($Y$4*$Y$5*AH39)-AD$7*AH39)/1.21) -> 0 | AX39: =IF(AI39=0,0,((L39*AI39)-($Y$4*$Y$5*AI39)-AE$7*AI39)/1.21) -> 0 | AY39: =IF(AJ39=0,0,((M39*AJ39)-($Y$4*$Y$5*AJ39)-AF$7*AJ39)/1.21) -> 0 | AZ39: =IF(AK39=0,0,((O39*AK39)-($Z$4*$Z$5*AK39)-AD33*AK39)/1.21) -> 0 | BA39: =IF(AL39=0,0,((N39*AL39)-($Y$4*$Y$5*AL39)-AH$7*AL39)/1.21) -> 0 | BB39: =IF(AM39=0,0,((P39*AM39)-($Y$4*$Y$5*AM39)-AI$7*AM39)/1.21) -> 0 | BC39: =IF(AN39=0,0,((Q39*AN39)-($Y$4*$Y$5*AN39)-AJ$7*AN39)/1.21) -> 0 | BD39: =IF(AO39=0,0,((R39*AO39)-($Y$4*$Y$5*AO39)-AK$7*AO39)/1.21) -> 0 | BE39: =SUM(AR39:BD39) -> 0
B40: Corporate Promotion 2 | F40: 0 | G40: =IF(F40=0,0,F40+$G$15) -> 0 | H40: =IF(F40=0,0,F40+$H$15) -> 0 | I40: =IF(F40=0,0,F40+$I$15) -> 0 | J40: =F40+$J$15 -> 0 | K40: =F40+$K$15 -> 0 | L40: =F40+$L$15 -> 0 | M40: =G40+$L$15 -> 0 | N40: =I40+$L$15 -> 0 | O40: =H40+$L$15 -> 0 | P40: =J40+$L$15 -> 0 | Q40: =K40+$L$15 -> 0 | R40: =L40+$L$15 -> 0 | Y40: 0 | AC40: =$AC$15*Y40 -> 0 | AD40: =$AD$15*Y40 -> 0 | AE40: =$AE$15*Y40 -> 0 | AF40: =$AF$15*Y40 -> 0 | AG40: =$AG$15*Y40 -> 0 | AH40: =$AH$15*Y40 -> 0 | AI40: =$AI$15*Y40 -> 0 | AJ40: =$AJ$15*Y40 -> 0 | AK40: =$AK$15*Y40 -> 0 | AL40: =$AL$15*Y40 -> 0 | AM40: =$AM$15*Y40 -> 0 | AN40: =$AN$15*Y40 -> 0 | AO40: =$AO$15*Y40 -> 0 | AP40: =SUM(AC40:AO40) -> 0 | AR40: =IF(AC40=0,0,((F40*AC40)-($Y$4*$Y$5*AC40)-Y$7*AC40)/1.21) -> 0 | AS40: =IF(AD40=0,0,((G40*AD40)-($Y$4*$Y$5*AD40)-Z$7*AD40)/1.21) -> 0 | AT40: =IF(AE40=0,0,((H40*AE40)-($Y$4*$Y$5*AE40)-AA$7*AE40)/1.21) -> 0 | AU40: =IF(AF40=0,0,((I40*AF40)-($Y$4*$Y$5*AF40)-AB$7*AF40)/1.21) -> 0 | AV40: =IF(AG40=0,0,((J40*AG40)-($Y$4*$Y$5*AG40)-AC$7*AG40)/1.21) -> 0 | AW40: =IF(AH40=0,0,((K40*AH40)-($Y$4*$Y$5*AH40)-AD$7*AH40)/1.21) -> 0 | AX40: =IF(AI40=0,0,((L40*AI40)-($Y$4*$Y$5*AI40)-AE$7*AI40)/1.21) -> 0 | AY40: =IF(AJ40=0,0,((M40*AJ40)-($Y$4*$Y$5*AJ40)-AF$7*AJ40)/1.21) -> 0 | AZ40: =IF(AK40=0,0,((O40*AK40)-($Z$4*$Z$5*AK40)-AD34*AK40)/1.21) -> 0 | BA40: =IF(AL40=0,0,((N40*AL40)-($Y$4*$Y$5*AL40)-AH$7*AL40)/1.21) -> 0 | BB40: =IF(AM40=0,0,((P40*AM40)-($Y$4*$Y$5*AM40)-AI$7*AM40)/1.21) -> 0 | BC40: =IF(AN40=0,0,((Q40*AN40)-($Y$4*$Y$5*AN40)-AJ$7*AN40)/1.21) -> 0 | BD40: =IF(AO40=0,0,((R40*AO40)-($Y$4*$Y$5*AO40)-AK$7*AO40)/1.21) -> 0 | BE40: =SUM(AR40:BD40) -> 0
B41: Government New | F41: =F32 -> 2150000 | G41: =G32 -> 2350000 | H41: =H32 -> 2450000 | I41: =I32 -> 3050000 | J41: =J32 -> 3700000 | K41: =K32 -> 4800000 | L41: =L32 -> 5150000 | M41: =M32 -> 6400000 | ... R41: =R32 -> 30200000 | X41: =SUM(Y41:Y48) -> 0.022 | Y41: 0 | Z41: 0.022591788 | AA41: 0.069597219 | AC41: =$AC$15*Y41 -> 0 | AD41: =$AD$15*Y41 -> 0 | AE41: =$AE$15*Y41 -> 0 | AF41: =$AF$15*Y41 -> 0 | AG41: =$AG$15*Y41 -> 0 | AH41: =$AH$15*Y41 -> 0 | AI41: =$AI$15*Y41 -> 0 | AJ41: =$AJ$15*Y41 -> 0 | AK41: =$AK$15*Y41 -> 0 | AL41: =$AL$15*Y41 -> 0 | AM41: =$AM$15*Y41 -> 0 | AN41: =$AN$15*Y41 -> 0 | AO41: =$AO$15*Y41 -> 0 | AP41: =SUM(AC41:AO41) -> 0 | AR41: =IF(AC41=0,0,((F41*AC41)-($Y$4*$Y$5*AC41)-Y$7*AC41)/1.21) -> 0 | AS41: =IF(AD41=0,0,((G41*AD41)-($Y$4*$Y$5*AD41)-Z$7*AD41)/1.21) -> 0 | AT41: =IF(AE41=0,0,((H41*AE41)-($Y$4*$Y$5*AE41)-AA$7*AE41)/1.21) -> 0 | AU41: =IF(AF41=0,0,((I41*AF41)-($Y$4*$Y$5*AF41)-AB$7*AF41)/1.21) -> 0 | AV41: =IF(AG41=0,0,((J41*AG41)-($Y$4*$Y$5*AG41)-AC$7*AG41)/1.21) -> 0 | AW41: =IF(AH41=0,0,((K41*AH41)-($Y$4*$Y$5*AH41)-AD$7*AH41)/1.21) -> 0 | AX41: =IF(AI41=0,0,((L41*AI41)-($Y$4*$Y$5*AI41)-AE$7*AI41)/1.21) -> 0 | AY41: =IF(AJ41=0,0,((M41*AJ41)-($Y$4*$Y$5*AJ41)-AF$7*AJ41)/1.21) -> 0 | AZ41: =IF(AK41=0,0,((O41*AK41)-($Z$4*$Z$5*AK41)-#REF!*AK41)/1.21) -> 0 | BA41: =IF(AL41=0,0,((N41*AL41)-($Y$4*$Y$5*AL41)-AH$7*AL41)/1.21) -> 0 | BB41: =IF(AM41=0,0,((P41*AM41)-($Y$4*$Y$5*AM41)-AI$7*AM41)/1.21) -> 0 | BC41: =IF(AN41=0,0,((Q41*AN41)-($Y$4*$Y$5*AN41)-AJ$7*AN41)/1.21) -> 0 | BD41: =IF(AO41=0,0,((R41*AO41)-($Y$4*$Y$5*AO41)-AK$7*AO41)/1.21) -> 0 | BE41: =SUM(AR41:BD41) -> 0 | BF41: =SUM(BE41:BE48) -> 4.2014422e+09 | BG41: Govt | BH41: 4907992472
B42: Government Productive | F42: =F33 -> 2100000 | G42: =G33 -> 2300000 | H42: =H33 -> 2400000 | I42: =I33 -> 3000000 | J42: =J33 -> 3650000 | K42: =K33 -> 4750000 | L42: =L33 -> 5100000 | M42: =M33 -> 6350000 | ... R42: =R33 -> 30150000 | Y42: 0.017 | AC42: =$AC$15*Y42 -> 881.69062 | AD42: =$AD$15*Y42 -> 122.45703 | AE42: =$AE$15*Y42 -> 1133.9521 | AF42: =$AF$15*Y42 -> 195.93125 | AG42: =$AG$15*Y42 -> 24.491406 | AH42: =$AH$15*Y42 -> 24.491406 | AI42: =$AI$15*Y42 -> 12.245703 | AJ42: =$AJ$15*Y42 -> 12.245703 | AK42: =$AK$15*Y42 -> 9.7965624 | AL42: =$AL$15*Y42 -> 24.491406 | AN42: =$AN$15*Y42 -> 2.4491406 | AO42: =$AO$15*Y42 -> 2.4491406 | AP42: =SUM(AC42:AO42) -> 2446.6915 | AR42: =IF(AC42=0,0,((F42*AC42)-($Y$4*$Y$5*AC42)-Y$7*AC42)/1.21)+174697656.25 -> 1.7049045e+09 | AT42: =IF(AE42=0,0,((H42*AE42)-($Y$4*$Y$5*AE42)-AA$7*AE42)/1.21)+174697656.25 -> 2.4238588e+09 | AV42: =IF(AG42=0,0,((J42*AG42)-($Y$4*$Y$5*AG42)-AC$7*AG42)/1.21) -> 73879035 | BB42: =IF(AM42=0,0,((P42*AM42)-($Y$4*$Y$5*AM42)-AI$7*AM42)/1.21) -> 0 | BE42: =SUM(AR42:BD42) -> 4.2026424e+09
B43: SBM | F43: 2276000 | H43: 2433000 | N43: 6848000
B44: Government Super Productive | Y44: 0.005 | AC44: =$AC$15*Y44 -> 259.32077 | AD44: =$AD$15*Y44 -> 36.016774 | AE44: =$AE$15*Y44 -> 333.51532 | AF44: =$AF$15*Y44 -> 57.626838 | AG44: =$AG$15*Y44 -> 7.2033547 | AH44: =$AH$15*Y44 -> 7.2033547 | AI44: =$AI$15*Y44 -> 3.6016774 | AJ44: =$AJ$15*Y44 -> 3.6016774 | AK44: =$AK$15*Y44 -> 2.8813419 | AL44: =$AL$15*Y44 -> 7.2033547 | AM44: =$AM$15*Y44 -> 0.72033547 | AN44: =$AN$15*Y44 -> 0.72033547 | AO44: =$AO$15*Y44 -> 0.72033547 | AP44: =SUM(AC44:AO44) -> 720.33547 | AR44: =IF(AC44=0,0,((F44*AC44)-($Y$4*$Y$5*AC44)-Y$7*AC44)/1.21) -> 0 | AS44: =IF(AD44=0,0,((G44*AD44)-($Y$4*$Y$5*AD44)-Z$7*AD44)/1.21) -> 0 | AT44: =IF(AE44=0,0,((H44*AE44)-($Y$4*$Y$5*AE44)-AA$7*AE44)/1.21) -> 0 | AU44: =IF(AF44=0,0,((I44*AF44)-($Y$4*$Y$5*AF44)-AB$7*AF44)/1.21) -> 0 | AV44: =IF(AG44=0,0,((J44*AG44)-($Y$4*$Y$5*AG44)-AC$7*AG44)/1.21) -> 0 | AW44: =IF(AH44=0,0,((K44*AH44)-($Y$4*$Y$5*AH44)-AD$7*AH44)/1.21) -> 0 | AX44: =IF(AI44=0,0,((L44*AI44)-($Y$4*$Y$5*AI44)-AE$7*AI44)/1.21) -> 0 | AY44: =IF(AJ44=0,0,((M44*AJ44)-($Y$4*$Y$5*AJ44)-AF$7*AJ44)/1.21) -> 0 | AZ44: =IF(AK44=0,0,((O44*AK44)-($Z$4*$Z$5*AK44)-AD36*AK44)/1.21) -> -1200162.2 | BA44: =IF(AL44=0,0,((N44*AL44)-($Y$4*$Y$5*AL44)-AH$7*AL44)/1.21) -> 0 | BB44: =IF(AM44=0,0,((P44*AM44)-($Y$4*$Y$5*AM44)-AI$7*AM44)/1.21) -> 0 | BC44: =IF(AN44=0,0,((Q44*AN44)-($Y$4*$Y$5*AN44)-AJ$7*AN44)/1.21) -> 0 | BD44: =IF(AO44=0,0,((R44*AO44)-($Y$4*$Y$5*AO44)-AK$7*AO44)/1.21) -> 0 | BE44: =SUM(AR44:BD44) -> -1200162.2
B45: Government Preferred 1 | F45: 0 | G45: =IF(F45=0,0,F45+$G$15) -> 0 | H45: =IF(F45=0,0,F45+$H$15) -> 0 | I45: =IF(F45=0,0,F45+$I$15) -> 0 | Y45: 0 | AC45: =$AC$15*Y45 -> 0 | AD45: =$AD$15*Y45 -> 0 | AE45: =$AE$15*Y45 -> 0 | AF45: =$AF$15*Y45 -> 0 | AG45: =$AG$15*Y45 -> 0 | AH45: =$AH$15*Y45 -> 0 | AI45: =$AI$15*Y45 -> 0 | AJ45: =$AJ$15*Y45 -> 0 | AK45: =$AK$15*Y45 -> 0 | AL45: =$AL$15*Y45 -> 0 | AM45: =$AM$15*Y45 -> 0 | AN45: =$AN$15*Y45 -> 0 | AO45: =$AO$15*Y45 -> 0 | AP45: =SUM(AC45:AO45) -> 0 | AR45: =IF(AC45=0,0,((F45*AC45)-($Y$4*$Y$5*AC45)-Y$7*AC45)/1.21) -> 0 | AS45: =IF(AD45=0,0,((G45*AD45)-($Y$4*$Y$5*AD45)-Z$7*AD45)/1.21) -> 0 | AT45: =IF(AE45=0,0,((H45*AE45)-($Y$4*$Y$5*AE45)-AA$7*AE45)/1.21) -> 0 | AU45: =IF(AF45=0,0,((I45*AF45)-($Y$4*$Y$5*AF45)-AB$7*AF45)/1.21) -> 0 | AV45: =IF(AG45=0,0,((J45*AG45)-($Y$4*$Y$5*AG45)-AC$7*AG45)/1.21) -> 0 | AW45: =IF(AH45=0,0,((K45*AH45)-($Y$4*$Y$5*AH45)-AD$7*AH45)/1.21) -> 0 | AX45: =IF(AI45=0,0,((L45*AI45)-($Y$4*$Y$5*AI45)-AE$7*AI45)/1.21) -> 0 | AY45: =IF(AJ45=0,0,((M45*AJ45)-($Y$4*$Y$5*AJ45)-AF$7*AJ45)/1.21) -> 0 | AZ45: =IF(AK45=0,0,((O45*AK45)-($Z$4*$Z$5*AK45)-AD37*AK45)/1.21) -> 0 | BA45: =IF(AL45=0,0,((N45*AL45)-($Y$4*$Y$5*AL45)-AH$7*AL45)/1.21) -> 0 | BB45: =IF(AM45=0,0,((P45*AM45)-($Y$4*$Y$5*AM45)-AI$7*AM45)/1.21) -> 0 | BC45: =IF(AN45=0,0,((Q45*AN45)-($Y$4*$Y$5*AN45)-AJ$7*AN45)/1.21) -> 0 | BD45: =IF(AO45=0,0,((R45*AO45)-($Y$4*$Y$5*AO45)-AK$7*AO45)/1.21) -> 0 | BE45: =SUM(AR45:BD45) -> 0
B46: Government Preferred 2 | F46: 0 | G46: =IF(F46=0,0,F46+$G$15) -> 0 | H46: =IF(F46=0,0,F46+$H$15) -> 0 | I46: =IF(F46=0,0,F46+$I$15) -> 0 | Y46: 0 | AC46: =$AC$15*Y46 -> 0 | AD46: =$AD$15*Y46 -> 0 | AE46: =$AE$15*Y46 -> 0 | AF46: =$AF$15*Y46 -> 0 | AG46: =$AG$15*Y46 -> 0 | AH46: =$AH$15*Y46 -> 0 | AI46: =$AI$15*Y46 -> 0 | AJ46: =$AJ$15*Y46 -> 0 | AK46: =$AK$15*Y46 -> 0 | AL46: =$AL$15*Y46 -> 0 | AM46: =$AM$15*Y46 -> 0 | AN46: =$AN$15*Y46 -> 0 | AO46: =$AO$15*Y46 -> 0 | AP46: =SUM(AC46:AO46) -> 0 | AR46: =IF(AC46=0,0,((F46*AC46)-($Y$4*$Y$5*AC46)-Y$7*AC46)/1.21) -> 0 | AS46: =IF(AD46=0,0,((G46*AD46)-($Y$4*$Y$5*AD46)-Z$7*AD46)/1.21) -> 0 | AT46: =IF(AE46=0,0,((H46*AE46)-($Y$4*$Y$5*AE46)-AA$7*AE46)/1.21) -> 0 | AU46: =IF(AF46=0,0,((I46*AF46)-($Y$4*$Y$5*AF46)-AB$7*AF46)/1.21) -> 0 | AV46: =IF(AG46=0,0,((J46*AG46)-($Y$4*$Y$5*AG46)-AC$7*AG46)/1.21) -> 0 | AW46: =IF(AH46=0,0,((K46*AH46)-($Y$4*$Y$5*AH46)-AD$7*AH46)/1.21) -> 0 | AX46: =IF(AI46=0,0,((L46*AI46)-($Y$4*$Y$5*AI46)-AE$7*AI46)/1.21) -> 0 | AY46: =IF(AJ46=0,0,((M46*AJ46)-($Y$4*$Y$5*AJ46)-AF$7*AJ46)/1.21) -> 0 | AZ46: =IF(AK46=0,0,((O46*AK46)-($Z$4*$Z$5*AK46)-AD38*AK46)/1.21) -> 0 | BA46: =IF(AL46=0,0,((N46*AL46)-($Y$4*$Y$5*AL46)-AH$7*AL46)/1.21) -> 0 | BB46: =IF(AM46=0,0,((P46*AM46)-($Y$4*$Y$5*AM46)-AI$7*AM46)/1.21) -> 0 | BC46: =IF(AN46=0,0,((Q46*AN46)-($Y$4*$Y$5*AN46)-AJ$7*AN46)/1.21) -> 0 | BD46: =IF(AO46=0,0,((R46*AO46)-($Y$4*$Y$5*AO46)-AK$7*AO46)/1.21) -> 0 | BE46: =SUM(AR46:BD46) -> 0
B47: Government Preferred 3 | F47: 0 | G47: =IF(F47=0,0,F47+$G$15) -> 0 | H47: =IF(F47=0,0,F47+$H$15) -> 0 | I47: =IF(F47=0,0,F47+$I$15) -> 0 | Y47: 0 | AC47: =$AC$15*Y47 -> 0 | AD47: =$AD$15*Y47 -> 0 | AE47: =$AE$15*Y47 -> 0 | AF47: =$AF$15*Y47 -> 0 | AG47: =$AG$15*Y47 -> 0 | AH47: =$AH$15*Y47 -> 0 | AI47: =$AI$15*Y47 -> 0 | AJ47: =$AJ$15*Y47 -> 0 | AK47: =$AK$15*Y47 -> 0 | AL47: =$AL$15*Y47 -> 0 | AM47: =$AM$15*Y47 -> 0 | AN47: =$AN$15*Y47 -> 0 | AO47: =$AO$15*Y47 -> 0 | AP47: =SUM(AC47:AO47) -> 0 | AR47: =IF(AC47=0,0,((F47*AC47)-($Y$4*$Y$5*AC47)-Y$7*AC47)/1.21) -> 0 | AS47: =IF(AD47=0,0,((G47*AD47)-($Y$4*$Y$5*AD47)-Z$7*AD47)/1.21) -> 0 | AT47: =IF(AE47=0,0,((H47*AE47)-($Y$4*$Y$5*AE47)-AA$7*AE47)/1.21) -> 0 | AU47: =IF(AF47=0,0,((I47*AF47)-($Y$4*$Y$5*AF47)-AB$7*AF47)/1.21) -> 0 | AV47: =IF(AG47=0,0,((J47*AG47)-($Y$4*$Y$5*AG47)-AC$7*AG47)/1.21) -> 0 | AW47: =IF(AH47=0,0,((K47*AH47)-($Y$4*$Y$5*AH47)-AD$7*AH47)/1.21) -> 0 | AX47: =IF(AI47=0,0,((L47*AI47)-($Y$4*$Y$5*AI47)-AE$7*AI47)/1.21) -> 0 | AY47: =IF(AJ47=0,0,((M47*AJ47)-($Y$4*$Y$5*AJ47)-AF$7*AJ47)/1.21) -> 0 | AZ47: =IF(AK47=0,0,((O47*AK47)-($Z$4*$Z$5*AK47)-AD39*AK47)/1.21) -> 0 | BA47: =IF(AL47=0,0,((N47*AL47)-($Y$4*$Y$5*AL47)-AH$7*AL47)/1.21) -> 0 | BB47: =IF(AM47=0,0,((P47*AM47)-($Y$4*$Y$5*AM47)-AI$7*AM47)/1.21) -> 0 | BC47: =IF(AN47=0,0,((Q47*AN47)-($Y$4*$Y$5*AN47)-AJ$7*AN47)/1.21) -> 0 | BD47: =IF(AO47=0,0,((R47*AO47)-($Y$4*$Y$5*AO47)-AK$7*AO47)/1.21) -> 0 | BE47: =SUM(AR47:BD47) -> 0
B48: Government Preferred 4 | F48: 0 | G48: =IF(F48=0,0,F48+$G$15) -> 0 | H48: =IF(F48=0,0,F48+$H$15) -> 0 | I48: =IF(F48=0,0,F48+$I$15) -> 0 | Y48: 0 | AC48: =$AC$15*Y48 -> 0 | AD48: =$AD$15*Y48 -> 0 | AE48: =$AE$15*Y48 -> 0 | AF48: =$AF$15*Y48 -> 0 | AG48: =$AG$15*Y48 -> 0 | AH48: =$AH$15*Y48 -> 0 | AI48: =$AI$15*Y48 -> 0 | AJ48: =$AJ$15*Y48 -> 0 | AK48: =$AK$15*Y48 -> 0 | AL48: =$AL$15*Y48 -> 0 | AM48: =$AM$15*Y48 -> 0 | AN48: =$AN$15*Y48 -> 0 | AO48: =$AO$15*Y48 -> 0 | AP48: =SUM(AC48:AO48) -> 0 | AR48: =IF(AC48=0,0,((F48*AC48)-($Y$4*$Y$5*AC48)-Y$7*AC48)/1.21) -> 0 | AS48: =IF(AD48=0,0,((G48*AD48)-($Y$4*$Y$5*AD48)-Z$7*AD48)/1.21) -> 0 | AT48: =IF(AE48=0,0,((H48*AE48)-($Y$4*$Y$5*AE48)-AA$7*AE48)/1.21) -> 0 | AU48: =IF(AF48=0,0,((I48*AF48)-($Y$4*$Y$5*AF48)-AB$7*AF48)/1.21) -> 0 | AV48: =IF(AG48=0,0,((J48*AG48)-($Y$4*$Y$5*AG48)-AC$7*AG48)/1.21) -> 0 | AW48: =IF(AH48=0,0,((K48*AH48)-($Y$4*$Y$5*AH48)-AD$7*AH48)/1.21) -> 0 | AX48: =IF(AI48=0,0,((L48*AI48)-($Y$4*$Y$5*AI48)-AE$7*AI48)/1.21) -> 0 | AY48: =IF(AJ48=0,0,((M48*AJ48)-($Y$4*$Y$5*AJ48)-AF$7*AJ48)/1.21) -> 0 | AZ48: =IF(AK48=0,0,((O48*AK48)-($Z$4*$Z$5*AK48)-AD40*AK48)/1.21) -> 0 | BA48: =IF(AL48=0,0,((N48*AL48)-($Y$4*$Y$5*AL48)-AH$7*AL48)/1.21) -> 0 | BB48: =IF(AM48=0,0,((P48*AM48)-($Y$4*$Y$5*AM48)-AI$7*AM48)/1.21) -> 0 | BC48: =IF(AN48=0,0,((Q48*AN48)-($Y$4*$Y$5*AN48)-AJ$7*AN48)/1.21) -> 0 | BD48: =IF(AO48=0,0,((R48*AO48)-($Y$4*$Y$5*AO48)-AK$7*AO48)/1.21) -> 0 | BE48: =SUM(AR48:BD48) -> 0
B49: Travel Agent New Domestic | F49: =F57+100000 -> 2400000 | G49: =G57+100000 -> 2600000 | H49: =H57+100000 -> 2700000 | I49: =I57+100000 -> 3300000 | J49: =J57+100000 -> 3950000 | K49: =K57+100000 -> 5050000 | L49: =L57+100000 -> 5400000 | M49: =M57+100000 -> 6650000 | ... R49: =R57+100000 -> 30450000 | X49: =SUM(Y49:Y72) -> 0.25 | Y49: 0.05 | Z49: 0.2329431 | AA49: 0.21980156 | AC49: =$AC$15*Y49 -> 2593.2077 | AD49: =$AD$15*Y49 -> 360.16774 | AE49: =$AE$15*Y49 -> 3335.1532 | AF49: =$AF$15*Y49 -> 576.26838 | AG49: =$AG$15*Y49 -> 72.033547 | AH49: =$AH$15*Y49 -> 72.033547 | AI49: =$AI$15*Y49 -> 36.016774 | AJ49: =$AJ$15*Y49 -> 36.016774 | AK49: =$AK$15*Y49 -> 28.813419 | AL49: =$AL$15*Y49 -> 72.033547 | AM49: =$AM$15*Y49 -> 7.2033547 | AN49: =$AN$15*Y49 -> 7.2033547 | AO49: =$AO$15*Y49 -> 7.2033547 | AP49: =SUM(AC49:AO49) -> 7203.3547 | AR49: =IF(AC49=0,0,((F49*AC49)-($Y$4*$Y$5*AC49)-Y$7*AC49)/1.21) -> 5.1435525e+09 | AS49: =IF(AD49=0,0,((G49*AD49)-($Y$4*$Y$5*AD49)-Z$7*AD49)/1.21) -> 7.7391414e+08 | AT49: =IF(AE49=0,0,((H49*AE49)-($Y$4*$Y$5*AE49)-AA$7*AE49)/1.21) -> 7.4420775e+09 | AU49: =IF(AF49=0,0,((I49*AF49)-($Y$4*$Y$5*AF49)-AB$7*AF49)/1.21) -> 1.571641e+09 | AV49: =IF(AG49=0,0,((J49*AG49)-($Y$4*$Y$5*AG49)-AC$7*AG49)/1.21) -> 2.3515084e+08 | AW49: =IF(AH49=0,0,((K49*AH49)-($Y$4*$Y$5*AH49)-AD$7*AH49)/1.21) -> 3.0063588e+08 | AX49: =IF(AI49=0,0,((L49*AI49)-($Y$4*$Y$5*AI49)-AE$7*AI49)/1.21) -> 1.6073601e+08 | AY49: =IF(AJ49=0,0,((M49*AJ49)-($Y$4*$Y$5*AJ49)-AF$7*AJ49)/1.21) -> 1.9794343e+08 | AZ49: =IF(AK49=0,0,((O49*AK49)-($Z$4*$Z$5*AK49)-AD41*AK49)/1.21) -> 1.6540331e+08 | BA49: =IF(AL49=0,0,((N49*AL49)-($Y$4*$Y$5*AL49)-AH$7*AL49)/1.21) -> 4.3160596e+08 | BB49: =IF(AM49=0,0,((P49*AM49)-($Y$4*$Y$5*AM49)-AI$7*AM49)/1.21) -> 66378021 | BC49: =IF(AN49=0,0,((Q49*AN49)-($Y$4*$Y$5*AN49)-AJ$7*AN49)/1.21) -> 56852924 | BD49: =IF(AO49=0,0,((R49*AO49)-($Y$4*$Y$5*AO49)-AK$7*AO49)/1.21) -> 1.8127451e+08 | BE49: =SUM(AR49:BD49) -> 1.6727166e+10 | BF49: =SUM(BE49:BE72) -> 5.442295e+10 | BG49: TA | BH49: 50606132321
B50: Shoulder | E50: 300000 | F50: =F$49+$E50 -> 2700000 | G50: =G$49+$E50 -> 2900000 | H50: =H$49+$E50 -> 3000000 | I50: =I$49+$E50 -> 3600000 | J50: =J$49+$E50 -> 4250000 | K50: =K$49+$E50 -> 5350000 | L50: =L$49+$E50 -> 5700000 | M50: =M$49+$E50 -> 6950000 | ... R50: =R$49+$E50 -> 30750000 | AC50: =$AC$15*Y50 -> 0 | AD50: =$AD$15*Y50 -> 0 | AE50: =$AE$15*Y50 -> 0 | AF50: =$AF$15*Y50 -> 0 | AG50: =$AG$15*Y50 -> 0 | AH50: =$AH$15*Y50 -> 0 | AI50: =$AI$15*Y50 -> 0 | AJ50: =$AJ$15*Y50 -> 0 | AK50: =$AK$15*Y50 -> 0 | AL50: =$AL$15*Y50 -> 0 | AM50: =$AM$15*Y50 -> 0 | AN50: =$AN$15*Y50 -> 0 | AO50: =$AO$15*Y50 -> 0 | AP50: =SUM(AC50:AO50) -> 0 | AR50: =IF(AC50=0,0,((F50*AC50)-($Y$4*$Y$5*AC50)-Y$7*AC50)/1.21) -> 0 | AS50: =IF(AD50=0,0,((G50*AD50)-($Y$4*$Y$5*AD50)-Z$7*AD50)/1.21) -> 0 | AT50: =IF(AE50=0,0,((H50*AE50)-($Y$4*$Y$5*AE50)-AA$7*AE50)/1.21) -> 0 | AU50: =IF(AF50=0,0,((I50*AF50)-($Y$4*$Y$5*AF50)-AB$7*AF50)/1.21) -> 0 | AV50: =IF(AG50=0,0,((J50*AG50)-($Y$4*$Y$5*AG50)-AC$7*AG50)/1.21) -> 0 | AW50: =IF(AH50=0,0,((K50*AH50)-($Y$4*$Y$5*AH50)-AD$7*AH50)/1.21) -> 0 | AX50: =IF(AI50=0,0,((L50*AI50)-($Y$4*$Y$5*AI50)-AE$7*AI50)/1.21) -> 0 | AY50: =IF(AJ50=0,0,((M50*AJ50)-($Y$4*$Y$5*AJ50)-AF$7*AJ50)/1.21) -> 0 | AZ50: =IF(AK50=0,0,((O50*AK50)-($Z$4*$Z$5*AK50)-AD42*AK50)/1.21) -> 0 | BA50: =IF(AL50=0,0,((N50*AL50)-($Y$4*$Y$5*AL50)-AH$7*AL50)/1.21) -> 0 | BB50: =IF(AM50=0,0,((P50*AM50)-($Y$4*$Y$5*AM50)-AI$7*AM50)/1.21) -> 0 | BC50: =IF(AN50=0,0,((Q50*AN50)-($Y$4*$Y$5*AN50)-AJ$7*AN50)/1.21) -> 0 | BD50: =IF(AO50=0,0,((R50*AO50)-($Y$4*$Y$5*AO50)-AK$7*AO50)/1.21) -> 0 | BE50: =SUM(AR50:BD50) -> 0
B51: High | E51: 600000 | F51: =F$49+$E51 -> 3000000 | G51: =G$49+$E51 -> 3200000 | H51: =H$49+$E51 -> 3300000 | I51: =I$49+$E51 -> 3900000 | J51: =J$49+$E51 -> 4550000 | K51: =K$49+$E51 -> 5650000 | L51: =L$49+$E51 -> 6000000 | M51: =M$49+$E51 -> 7250000 | ... R51: =R$49+$E51 -> 31050000 | AC51: =$AC$15*Y51 -> 0 | AD51: =$AD$15*Y51 -> 0 | AE51: =$AE$15*Y51 -> 0 | AF51: =$AF$15*Y51 -> 0 | AG51: =$AG$15*Y51 -> 0 | AH51: =$AH$15*Y51 -> 0 | AI51: =$AI$15*Y51 -> 0 | AJ51: =$AJ$15*Y51 -> 0 | AK51: =$AK$15*Y51 -> 0 | AL51: =$AL$15*Y51 -> 0 | AM51: =$AM$15*Y51 -> 0 | AN51: =$AN$15*Y51 -> 0 | AO51: =$AO$15*Y51 -> 0 | AP51: =SUM(AC51:AO51) -> 0 | AR51: =IF(AC51=0,0,((F51*AC51)-($Y$4*$Y$5*AC51)-Y$7*AC51)/1.21) -> 0 | AS51: =IF(AD51=0,0,((G51*AD51)-($Y$4*$Y$5*AD51)-Z$7*AD51)/1.21) -> 0 | AT51: =IF(AE51=0,0,((H51*AE51)-($Y$4*$Y$5*AE51)-AA$7*AE51)/1.21) -> 0 | AU51: =IF(AF51=0,0,((I51*AF51)-($Y$4*$Y$5*AF51)-AB$7*AF51)/1.21) -> 0 | AV51: =IF(AG51=0,0,((J51*AG51)-($Y$4*$Y$5*AG51)-AC$7*AG51)/1.21) -> 0 | AW51: =IF(AH51=0,0,((K51*AH51)-($Y$4*$Y$5*AH51)-AD$7*AH51)/1.21) -> 0 | AX51: =IF(AI51=0,0,((L51*AI51)-($Y$4*$Y$5*AI51)-AE$7*AI51)/1.21) -> 0 | AY51: =IF(AJ51=0,0,((M51*AJ51)-($Y$4*$Y$5*AJ51)-AF$7*AJ51)/1.21) -> 0 | AZ51: =IF(AK51=0,0,((O51*AK51)-($Z$4*$Z$5*AK51)-AD44*AK51)/1.21) -> 0 | BA51: =IF(AL51=0,0,((N51*AL51)-($Y$4*$Y$5*AL51)-AH$7*AL51)/1.21) -> 0 | BB51: =IF(AM51=0,0,((P51*AM51)-($Y$4*$Y$5*AM51)-AI$7*AM51)/1.21) -> 0 | BC51: =IF(AN51=0,0,((Q51*AN51)-($Y$4*$Y$5*AN51)-AJ$7*AN51)/1.21) -> 0 | BD51: =IF(AO51=0,0,((R51*AO51)-($Y$4*$Y$5*AO51)-AK$7*AO51)/1.21) -> 0 | BE51: =SUM(AR51:BD51) -> 0
B52: Peak | E52: 800000 | F52: =F$49+$E52 -> 3200000 | G52: =G$49+$E52 -> 3400000 | H52: =H$49+$E52 -> 3500000 | I52: =I$49+$E52 -> 4100000 | J52: =J$49+$E52 -> 4750000 | K52: =K$49+$E52 -> 5850000 | L52: =L$49+$E52 -> 6200000 | M52: =M$49+$E52 -> 7450000 | ... R52: =R$49+$E52 -> 31250000 | AC52: =$AC$15*Y52 -> 0 | AD52: =$AD$15*Y52 -> 0 | AE52: =$AE$15*Y52 -> 0 | AF52: =$AF$15*Y52 -> 0 | AG52: =$AG$15*Y52 -> 0 | AH52: =$AH$15*Y52 -> 0 | AI52: =$AI$15*Y52 -> 0 | AJ52: =$AJ$15*Y52 -> 0 | AK52: =$AK$15*Y52 -> 0 | AL52: =$AL$15*Y52 -> 0 | AM52: =$AM$15*Y52 -> 0 | AN52: =$AN$15*Y52 -> 0 | AO52: =$AO$15*Y52 -> 0 | AP52: =SUM(AC52:AO52) -> 0 | AR52: =IF(AC52=0,0,((F52*AC52)-($Y$4*$Y$5*AC52)-Y$7*AC52)/1.21) -> 0 | AS52: =IF(AD52=0,0,((G52*AD52)-($Y$4*$Y$5*AD52)-Z$7*AD52)/1.21) -> 0 | AT52: =IF(AE52=0,0,((H52*AE52)-($Y$4*$Y$5*AE52)-AA$7*AE52)/1.21) -> 0 | AU52: =IF(AF52=0,0,((I52*AF52)-($Y$4*$Y$5*AF52)-AB$7*AF52)/1.21) -> 0 | AV52: =IF(AG52=0,0,((J52*AG52)-($Y$4*$Y$5*AG52)-AC$7*AG52)/1.21) -> 0 | AW52: =IF(AH52=0,0,((K52*AH52)-($Y$4*$Y$5*AH52)-AD$7*AH52)/1.21) -> 0 | AX52: =IF(AI52=0,0,((L52*AI52)-($Y$4*$Y$5*AI52)-AE$7*AI52)/1.21) -> 0 | AY52: =IF(AJ52=0,0,((M52*AJ52)-($Y$4*$Y$5*AJ52)-AF$7*AJ52)/1.21) -> 0 | AZ52: =IF(AK52=0,0,((O52*AK52)-($Z$4*$Z$5*AK52)-AD45*AK52)/1.21) -> 0 | BA52: =IF(AL52=0,0,((N52*AL52)-($Y$4*$Y$5*AL52)-AH$7*AL52)/1.21) -> 0 | BB52: =IF(AM52=0,0,((P52*AM52)-($Y$4*$Y$5*AM52)-AI$7*AM52)/1.21) -> 0 | BC52: =IF(AN52=0,0,((Q52*AN52)-($Y$4*$Y$5*AN52)-AJ$7*AN52)/1.21) -> 0 | BD52: =IF(AO52=0,0,((R52*AO52)-($Y$4*$Y$5*AO52)-AK$7*AO52)/1.21) -> 0 | BE52: =SUM(AR52:BD52) -> 0
B53: Travel Agent Productive Domestic | F53: =F49-50000 -> 2350000 | G53: =G49-50000 -> 2550000 | H53: =H49-50000 -> 2650000 | I53: =I49-50000 -> 3250000 | J53: =J49-50000 -> 3900000 | K53: =K49-50000 -> 5000000 | L53: =L49-50000 -> 5350000 | M53: =M49-50000 -> 6600000 | ... R53: =R49-50000 -> 30400000
B54: Shoulder | E54: 300000 | F54: =F$53+$E54 -> 2650000 | G54: =G$53+$E54 -> 2850000 | H54: =H$53+$E54 -> 2950000 | I54: =I$53+$E54 -> 3550000 | J54: =J$53+$E54 -> 4200000 | K54: =K$53+$E54 -> 5300000 | L54: =L$53+$E54 -> 5650000 | M54: =M$53+$E54 -> 6900000 | ... R54: =R$53+$E54 -> 30700000
B55: High | E55: 600000 | F55: =F$53+$E55 -> 2950000 | G55: =G$53+$E55 -> 3150000 | H55: =H$53+$E55 -> 3250000 | I55: =I$53+$E55 -> 3850000 | J55: =J$53+$E55 -> 4500000 | K55: =K$53+$E55 -> 5600000 | L55: =L$53+$E55 -> 5950000 | M55: =M$53+$E55 -> 7200000 | ... R55: =R$53+$E55 -> 31000000
B56: Peak | E56: 800000 | F56: =F$53+$E56 -> 3150000 | G56: =G$53+$E56 -> 3350000 | H56: =H$53+$E56 -> 3450000 | I56: =I$53+$E56 -> 4050000 | J56: =J$53+$E56 -> 4700000 | K56: =K$53+$E56 -> 5800000 | L56: =L$53+$E56 -> 6150000 | M56: =M$53+$E56 -> 7400000 | ... R56: =R$53+$E56 -> 31200000
B57: Travel Agent Wholesales Domestic | F57: =F61-300000 -> 2300000 | G57: =G61-300000 -> 2500000 | H57: =H61-300000 -> 2600000 | I57: =I61-300000 -> 3200000 | J57: =J61-300000 -> 3850000 | K57: =K61-300000 -> 4950000 | L57: =L61-300000 -> 5300000 | M57: =M61-300000 -> 6550000 | ... R57: =R61-300000 -> 30350000 | Y57: 0.04 | AC57: =$AC$15*Y57 -> 2074.5662 | AD57: =$AD$15*Y57 -> 288.13419 | AE57: =$AE$15*Y57 -> 2668.1226 | AF57: =$AF$15*Y57 -> 461.0147 | AG57: =$AG$15*Y57 -> 57.626838 | AH57: =$AH$15*Y57 -> 57.626838 | AI57: =$AI$15*Y57 -> 28.813419 | AJ57: =$AJ$15*Y57 -> 28.813419 | AK57: =$AK$15*Y57 -> 23.050735 | AL57: =$AL$15*Y57 -> 57.626838 | AM57: =$AM$15*Y57 -> 5.7626838 | AN57: =$AN$15*Y57 -> 5.7626838 | AO57: =$AO$15*Y57 -> 5.7626838 | AP57: =SUM(AC57:AO57) -> 5762.6838 | AR57: =IF(AC57=0,0,((F57*AC57)-($Y$4*$Y$5*AC57)-Y$7*AC57)/1.21) -> 3.9433902e+09 | AS57: =IF(AD57=0,0,((G57*AD57)-($Y$4*$Y$5*AD57)-Z$7*AD57)/1.21) -> 5.9531857e+08 | AT57: =IF(AE57=0,0,((H57*AE57)-($Y$4*$Y$5*AE57)-AA$7*AE57)/1.21) -> 5.733156e+09 | AU57: =IF(AF57=0,0,((I57*AF57)-($Y$4*$Y$5*AF57)-AB$7*AF57)/1.21) -> 1.2192124e+09 | AV57: =IF(AG57=0,0,((J57*AG57)-($Y$4*$Y$5*AG57)-AC$7*AG57)/1.21) -> 1.8335812e+08 | AW57: =IF(AH57=0,0,((K57*AH57)-($Y$4*$Y$5*AH57)-AD$7*AH57)/1.21) -> 2.3574615e+08 | AX57: =IF(AI57=0,0,((L57*AI57)-($Y$4*$Y$5*AI57)-AE$7*AI57)/1.21) -> 1.2620754e+08 | AY57: =IF(AJ57=0,0,((M57*AJ57)-($Y$4*$Y$5*AJ57)-AF$7*AJ57)/1.21) -> 1.5597347e+08 | AZ57: =IF(AK57=0,0,((O57*AK57)-($Z$4*$Z$5*AK57)-AD42*AK57)/1.21) -> 1.304153e+08 | BA57: =IF(AL57=0,0,((N57*AL57)-($Y$4*$Y$5*AL57)-AH$7*AL57)/1.21) -> 3.4052222e+08 | BB57: =IF(AM57=0,0,((P57*AM57)-($Y$4*$Y$5*AM57)-AI$7*AM57)/1.21) -> 52626162 | BC57: =IF(AN57=0,0,((Q57*AN57)-($Y$4*$Y$5*AN57)-AJ$7*AN57)/1.21) -> 45006084 | BD57: =IF(AO57=0,0,((R57*AO57)-($Y$4*$Y$5*AO57)-AK$7*AO57)/1.21) -> 1.4454335e+08 | BE57: =SUM(AR57:BD57) -> 1.2905476e+10
B58: Shoulder | E58: 300000 | F58: =F$57+$E58 -> 2600000 | G58: =G$57+$E58 -> 2800000 | H58: =H$57+$E58 -> 2900000 | I58: =I$57+$E58 -> 3500000 | J58: =J$57+$E58 -> 4150000 | K58: =K$57+$E58 -> 5250000 | L58: =L$57+$E58 -> 5600000 | M58: =M$57+$E58 -> 6850000 | ... R58: =R$57+$E58 -> 30650000 | AC58: =$AC$15*Y58 -> 0 | AD58: =$AD$15*Y58 -> 0 | AE58: =$AE$15*Y58 -> 0 | AF58: =$AF$15*Y58 -> 0 | AG58: =$AG$15*Y58 -> 0 | AH58: =$AH$15*Y58 -> 0 | AI58: =$AI$15*Y58 -> 0 | AJ58: =$AJ$15*Y58 -> 0 | AK58: =$AK$15*Y58 -> 0 | AL58: =$AL$15*Y58 -> 0 | AM58: =$AM$15*Y58 -> 0 | AN58: =$AN$15*Y58 -> 0 | AO58: =$AO$15*Y58 -> 0 | AP58: =SUM(AC58:AO58) -> 0 | AR58: =IF(AC58=0,0,((F58*AC58)-($Y$4*$Y$5*AC58)-Y$7*AC58)/1.21) -> 0 | AS58: =IF(AD58=0,0,((G58*AD58)-($Y$4*$Y$5*AD58)-Z$7*AD58)/1.21) -> 0 | AT58: =IF(AE58=0,0,((H58*AE58)-($Y$4*$Y$5*AE58)-AA$7*AE58)/1.21) -> 0 | AU58: =IF(AF58=0,0,((I58*AF58)-($Y$4*$Y$5*AF58)-AB$7*AF58)/1.21) -> 0 | AV58: =IF(AG58=0,0,((J58*AG58)-($Y$4*$Y$5*AG58)-AC$7*AG58)/1.21) -> 0 | AW58: =IF(AH58=0,0,((K58*AH58)-($Y$4*$Y$5*AH58)-AD$7*AH58)/1.21) -> 0 | AX58: =IF(AI58=0,0,((L58*AI58)-($Y$4*$Y$5*AI58)-AE$7*AI58)/1.21) -> 0 | AY58: =IF(AJ58=0,0,((M58*AJ58)-($Y$4*$Y$5*AJ58)-AF$7*AJ58)/1.21) -> 0 | AZ58: =IF(AK58=0,0,((O58*AK58)-($Z$4*$Z$5*AK58)-AD44*AK58)/1.21) -> 0 | BA58: =IF(AL58=0,0,((N58*AL58)-($Y$4*$Y$5*AL58)-AH$7*AL58)/1.21) -> 0 | BB58: =IF(AM58=0,0,((P58*AM58)-($Y$4*$Y$5*AM58)-AI$7*AM58)/1.21) -> 0 | BC58: =IF(AN58=0,0,((Q58*AN58)-($Y$4*$Y$5*AN58)-AJ$7*AN58)/1.21) -> 0 | BD58: =IF(AO58=0,0,((R58*AO58)-($Y$4*$Y$5*AO58)-AK$7*AO58)/1.21) -> 0 | BE58: =SUM(AR58:BD58) -> 0
B59: High | E59: 600000 | F59: =F$57+$E59 -> 2900000 | G59: =G$57+$E59 -> 3100000 | H59: =H$57+$E59 -> 3200000 | I59: =I$57+$E59 -> 3800000 | J59: =J$57+$E59 -> 4450000 | K59: =K$57+$E59 -> 5550000 | L59: =L$57+$E59 -> 5900000 | M59: =M$57+$E59 -> 7150000 | ... R59: =R$57+$E59 -> 30950000 | AC59: =$AC$15*Y59 -> 0 | AD59: =$AD$15*Y59 -> 0 | AE59: =$AE$15*Y59 -> 0 | AF59: =$AF$15*Y59 -> 0 | AG59: =$AG$15*Y59 -> 0 | AH59: =$AH$15*Y59 -> 0 | AI59: =$AI$15*Y59 -> 0 | AJ59: =$AJ$15*Y59 -> 0 | AK59: =$AK$15*Y59 -> 0 | AL59: =$AL$15*Y59 -> 0 | AM59: =$AM$15*Y59 -> 0 | AN59: =$AN$15*Y59 -> 0 | AO59: =$AO$15*Y59 -> 0 | AP59: =SUM(AC59:AO59) -> 0 | AR59: =IF(AC59=0,0,((F59*AC59)-($Y$4*$Y$5*AC59)-Y$7*AC59)/1.21) -> 0 | AS59: =IF(AD59=0,0,((G59*AD59)-($Y$4*$Y$5*AD59)-Z$7*AD59)/1.21) -> 0 | AT59: =IF(AE59=0,0,((H59*AE59)-($Y$4*$Y$5*AE59)-AA$7*AE59)/1.21) -> 0 | AU59: =IF(AF59=0,0,((I59*AF59)-($Y$4*$Y$5*AF59)-AB$7*AF59)/1.21) -> 0 | AV59: =IF(AG59=0,0,((J59*AG59)-($Y$4*$Y$5*AG59)-AC$7*AG59)/1.21) -> 0 | AW59: =IF(AH59=0,0,((K59*AH59)-($Y$4*$Y$5*AH59)-AD$7*AH59)/1.21) -> 0 | AX59: =IF(AI59=0,0,((L59*AI59)-($Y$4*$Y$5*AI59)-AE$7*AI59)/1.21) -> 0 | AY59: =IF(AJ59=0,0,((M59*AJ59)-($Y$4*$Y$5*AJ59)-AF$7*AJ59)/1.21) -> 0 | AZ59: =IF(AK59=0,0,((O59*AK59)-($Z$4*$Z$5*AK59)-AD45*AK59)/1.21) -> 0 | BA59: =IF(AL59=0,0,((N59*AL59)-($Y$4*$Y$5*AL59)-AH$7*AL59)/1.21) -> 0 | BB59: =IF(AM59=0,0,((P59*AM59)-($Y$4*$Y$5*AM59)-AI$7*AM59)/1.21) -> 0 | BC59: =IF(AN59=0,0,((Q59*AN59)-($Y$4*$Y$5*AN59)-AJ$7*AN59)/1.21) -> 0 | BD59: =IF(AO59=0,0,((R59*AO59)-($Y$4*$Y$5*AO59)-AK$7*AO59)/1.21) -> 0 | BE59: =SUM(AR59:BD59) -> 0
B60: Peak | E60: 800000 | F60: =F$57+$E60 -> 3100000 | G60: =G$57+$E60 -> 3300000 | H60: =H$57+$E60 -> 3400000 | I60: =I$57+$E60 -> 4000000 | J60: =J$57+$E60 -> 4650000 | K60: =K$57+$E60 -> 5750000 | L60: =L$57+$E60 -> 6100000 | M60: =M$57+$E60 -> 7350000 | ... R60: =R$57+$E60 -> 31150000 | AC60: =$AC$15*Y60 -> 0 | AD60: =$AD$15*Y60 -> 0 | AE60: =$AE$15*Y60 -> 0 | AF60: =$AF$15*Y60 -> 0 | AG60: =$AG$15*Y60 -> 0 | AH60: =$AH$15*Y60 -> 0 | AI60: =$AI$15*Y60 -> 0 | AJ60: =$AJ$15*Y60 -> 0 | AK60: =$AK$15*Y60 -> 0 | AL60: =$AL$15*Y60 -> 0 | AM60: =$AM$15*Y60 -> 0 | AN60: =$AN$15*Y60 -> 0 | AO60: =$AO$15*Y60 -> 0 | AP60: =SUM(AC60:AO60) -> 0 | AR60: =IF(AC60=0,0,((F60*AC60)-($Y$4*$Y$5*AC60)-Y$7*AC60)/1.21) -> 0 | AS60: =IF(AD60=0,0,((G60*AD60)-($Y$4*$Y$5*AD60)-Z$7*AD60)/1.21) -> 0 | AT60: =IF(AE60=0,0,((H60*AE60)-($Y$4*$Y$5*AE60)-AA$7*AE60)/1.21) -> 0 | AU60: =IF(AF60=0,0,((I60*AF60)-($Y$4*$Y$5*AF60)-AB$7*AF60)/1.21) -> 0 | AV60: =IF(AG60=0,0,((J60*AG60)-($Y$4*$Y$5*AG60)-AC$7*AG60)/1.21) -> 0 | AW60: =IF(AH60=0,0,((K60*AH60)-($Y$4*$Y$5*AH60)-AD$7*AH60)/1.21) -> 0 | AX60: =IF(AI60=0,0,((L60*AI60)-($Y$4*$Y$5*AI60)-AE$7*AI60)/1.21) -> 0 | AY60: =IF(AJ60=0,0,((M60*AJ60)-($Y$4*$Y$5*AJ60)-AF$7*AJ60)/1.21) -> 0 | AZ60: =IF(AK60=0,0,((O60*AK60)-($Z$4*$Z$5*AK60)-AD46*AK60)/1.21) -> 0 | BA60: =IF(AL60=0,0,((N60*AL60)-($Y$4*$Y$5*AL60)-AH$7*AL60)/1.21) -> 0 | BB60: =IF(AM60=0,0,((P60*AM60)-($Y$4*$Y$5*AM60)-AI$7*AM60)/1.21) -> 0 | BC60: =IF(AN60=0,0,((Q60*AN60)-($Y$4*$Y$5*AN60)-AJ$7*AN60)/1.21) -> 0 | BD60: =IF(AO60=0,0,((R60*AO60)-($Y$4*$Y$5*AO60)-AK$7*AO60)/1.21) -> 0 | BE60: =SUM(AR60:BD60) -> 0
B61: WW | E61: 450000 | F61: =F32+$E$61 -> 2600000 | G61: =G32+$E$61 -> 2800000 | H61: =H32+$E$61 -> 2900000 | I61: =I32+$E$61 -> 3500000 | J61: =J32+$E$61 -> 4150000 | K61: =K32+$E$61 -> 5250000 | L61: =L32+$E$61 -> 5600000 | M61: =M32+$E$61 -> 6850000 | ... R61: =R32+$E$61 -> 30650000 | Y61: 0.04 | AC61: =$AC$15*Y61 -> 2074.5662 | AD61: =$AD$15*Y61 -> 288.13419 | AE61: =$AE$15*Y61 -> 2668.1226 | AF61: =$AF$15*Y61 -> 461.0147 | AG61: =$AG$15*Y61 -> 57.626838 | AH61: =$AH$15*Y61 -> 57.626838 | AI61: =$AI$15*Y61 -> 28.813419 | AJ61: =$AJ$15*Y61 -> 28.813419 | AK61: =$AK$15*Y61 -> 23.050735 | AL61: =$AL$15*Y61 -> 57.626838 | AN61: =$AN$15*Y61 -> 5.7626838 | AO61: =$AO$15*Y61 -> 5.7626838 | AP61: =SUM(AC61:AO61) -> 5756.9211 | AR61: =IF(AC61=0,0,((F61*AC61)-($Y$4*$Y$5*AC61)-Y$7*AC61)/1.21) -> 4.4577455e+09 | AS61: =IF(AD61=0,0,((G61*AD61)-($Y$4*$Y$5*AD61)-Z$7*AD61)/1.21) -> 6.667568e+08 | AT61: =IF(AE61=0,0,((H61*AE61)-($Y$4*$Y$5*AE61)-AA$7*AE61)/1.21) -> 6.394674e+09 | AU61: =IF(AF61=0,0,((I61*AF61)-($Y$4*$Y$5*AF61)-AB$7*AF61)/1.21) -> 1.3335136e+09 | AV61: =IF(AG61=0,0,((J61*AG61)-($Y$4*$Y$5*AG61)-AC$7*AG61)/1.21) -> 1.9764577e+08 | AW61: =IF(AH61=0,0,((K61*AH61)-($Y$4*$Y$5*AH61)-AD$7*AH61)/1.21) -> 2.500338e+08 | AX61: =IF(AI61=0,0,((L61*AI61)-($Y$4*$Y$5*AI61)-AE$7*AI61)/1.21) -> 1.3335136e+08 | AY61: =IF(AJ61=0,0,((M61*AJ61)-($Y$4*$Y$5*AJ61)-AF$7*AJ61)/1.21) -> 1.6311729e+08 | AZ61: =IF(AK61=0,0,((O61*AK61)-($Z$4*$Z$5*AK61)-AD48*AK61)/1.21) -> 1.3613269e+08 | BA61: =IF(AL61=0,0,((N61*AL61)-($Y$4*$Y$5*AL61)-AH$7*AL61)/1.21) -> 3.5480987e+08 | BB61: =IF(AM61=0,0,((P61*AM61)-($Y$4*$Y$5*AM61)-AI$7*AM61)/1.21) -> 0 | BC61: =IF(AN61=0,0,((Q61*AN61)-($Y$4*$Y$5*AN61)-AJ$7*AN61)/1.21) -> 46434849 | BD61: =IF(AO61=0,0,((R61*AO61)-($Y$4*$Y$5*AO61)-AK$7*AO61)/1.21) -> 1.4597211e+08 | BE61: =SUM(AR61:BD61) -> 1.4280188e+10
B62: Shoulder | E62: 300000 | F62: =F$61+$E62 -> 2900000 | G62: =G$61+$E62 -> 3100000 | H62: =H$61+$E62 -> 3200000 | I62: =I$61+$E62 -> 3800000 | J62: =J$61+$E62 -> 4450000 | K62: =K$61+$E62 -> 5550000 | L62: =L$61+$E62 -> 5900000 | M62: =M$61+$E62 -> 7150000 | ... R62: =R$61+$E62 -> 30950000
B63: High | E63: 600000 | F63: =F$61+$E63 -> 3200000 | G63: =G$61+$E63 -> 3400000 | H63: =H$61+$E63 -> 3500000 | I63: =I$61+$E63 -> 4100000 | J63: =J$61+$E63 -> 4750000 | K63: =K$61+$E63 -> 5850000 | L63: =L$61+$E63 -> 6200000 | M63: =M$61+$E63 -> 7450000 | ... R63: =R$61+$E63 -> 31250000
B64: Peak | E64: 800000 | F64: =F$61+$E64 -> 3400000 | G64: =G$61+$E64 -> 3600000 | H64: =H$61+$E64 -> 3700000 | I64: =I$61+$E64 -> 4300000 | J64: =J$61+$E64 -> 4950000 | K64: =K$61+$E64 -> 6050000 | L64: =L$61+$E64 -> 6400000 | M64: =M$61+$E64 -> 7650000 | ... R64: =R$61+$E64 -> 31450000 | AC64: =$AC$15*Y64 -> 0 | AD64: =$AD$15*Y64 -> 0 | AE64: =$AE$15*Y64 -> 0 | AF64: =$AF$15*Y64 -> 0 | AG64: =$AG$15*Y64 -> 0 | AH64: =$AH$15*Y64 -> 0 | AI64: =$AI$15*Y64 -> 0 | AJ64: =$AJ$15*Y64 -> 0 | AK64: =$AK$15*Y64 -> 0 | AL64: =$AL$15*Y64 -> 0 | AN64: =$AN$15*Y64 -> 0 | AO64: =$AO$15*Y64 -> 0 | AP64: =SUM(AC64:AO64) -> 0 | AR64: =IF(AC64=0,0,((F64*AC64)-($Y$4*$Y$5*AC64)-Y$7*AC64)/1.21) -> 0 | AS64: =IF(AD64=0,0,((G64*AD64)-($Y$4*$Y$5*AD64)-Z$7*AD64)/1.21) -> 0 | AT64: =IF(AE64=0,0,((H64*AE64)-($Y$4*$Y$5*AE64)-AA$7*AE64)/1.21) -> 0 | AU64: =IF(AF64=0,0,((I64*AF64)-($Y$4*$Y$5*AF64)-AB$7*AF64)/1.21) -> 0 | AV64: =IF(AG64=0,0,((J64*AG64)-($Y$4*$Y$5*AG64)-AC$7*AG64)/1.21) -> 0 | AW64: =IF(AH64=0,0,((K64*AH64)-($Y$4*$Y$5*AH64)-AD$7*AH64)/1.21) -> 0 | AX64: =IF(AI64=0,0,((L64*AI64)-($Y$4*$Y$5*AI64)-AE$7*AI64)/1.21) -> 0 | AY64: =IF(AJ64=0,0,((M64*AJ64)-($Y$4*$Y$5*AJ64)-AF$7*AJ64)/1.21) -> 0 | AZ64: =IF(AK64=0,0,((O64*AK64)-($Z$4*$Z$5*AK64)-AD49*AK64)/1.21) -> 0 | BA64: =IF(AL64=0,0,((N64*AL64)-($Y$4*$Y$5*AL64)-AH$7*AL64)/1.21) -> 0 | BB64: =IF(AM64=0,0,((P64*AM64)-($Y$4*$Y$5*AM64)-AI$7*AM64)/1.21) -> 0 | BC64: =IF(AN64=0,0,((Q64*AN64)-($Y$4*$Y$5*AN64)-AJ$7*AN64)/1.21) -> 0 | BD64: =IF(AO64=0,0,((R64*AO64)-($Y$4*$Y$5*AO64)-AK$7*AO64)/1.21) -> 0 | BE64: =SUM(AR64:BD64) -> 0
B65: EU, S. Africa,CIS | F65: =F61-50000 -> 2550000 | G65: =G61-50000 -> 2750000 | H65: =H61-50000 -> 2850000 | I65: =I61-50000 -> 3450000 | J65: =J61-50000 -> 4100000 | K65: =K61-50000 -> 5200000 | L65: =L61-50000 -> 5550000 | M65: =M61-50000 -> 6800000 | ... R65: =R61-50000 -> 30600000 | Y65: 0.03 | AC65: =$AC$15*Y65 -> 1555.9246 | AD65: =$AD$15*Y65 -> 216.10064 | AE65: =$AE$15*Y65 -> 2001.0919 | AF65: =$AF$15*Y65 -> 345.76103 | AG65: =$AG$15*Y65 -> 43.220128 | AH65: =$AH$15*Y65 -> 43.220128 | AI65: =$AI$15*Y65 -> 21.610064 | AJ65: =$AJ$15*Y65 -> 21.610064 | AK65: =$AK$15*Y65 -> 17.288051 | AL65: =$AL$15*Y65 -> 43.220128 | AN65: =$AN$15*Y65 -> 4.3220128 | AO65: =$AO$15*Y65 -> 4.3220128 | AP65: =SUM(AC65:AO65) -> 4317.6908 | AR65: =IF(AC65=0,0,((F65*AC65)-($Y$4*$Y$5*AC65)-Y$7*AC65)/1.21) -> 3.2790147e+09 | AS65: =IF(AD65=0,0,((G65*AD65)-($Y$4*$Y$5*AD65)-Z$7*AD65)/1.21) -> 4.9113782e+08 | AT65: =IF(AE65=0,0,((H65*AE65)-($Y$4*$Y$5*AE65)-AA$7*AE65)/1.21) -> 4.7133157e+09 | AU65: =IF(AF65=0,0,((I65*AF65)-($Y$4*$Y$5*AF65)-AB$7*AF65)/1.21) -> 9.8584755e+08 | AV65: =IF(AG65=0,0,((J65*AG65)-($Y$4*$Y$5*AG65)-AC$7*AG65)/1.21) -> 1.4644837e+08 | AW65: =IF(AH65=0,0,((K65*AH65)-($Y$4*$Y$5*AH65)-AD$7*AH65)/1.21) -> 1.8573939e+08 | AX65: =IF(AI65=0,0,((L65*AI65)-($Y$4*$Y$5*AI65)-AE$7*AI65)/1.21) -> 99120542 | AY65: =IF(AJ65=0,0,((M65*AJ65)-($Y$4*$Y$5*AJ65)-AF$7*AJ65)/1.21) -> 1.2144499e+08 | AZ65: =IF(AK65=0,0,((O65*AK65)-($Z$4*$Z$5*AK65)-AD50*AK65)/1.21) -> 1.0138513e+08 | BA65: =IF(AL65=0,0,((N65*AL65)-($Y$4*$Y$5*AL65)-AH$7*AL65)/1.21) -> 2.6432145e+08 | BB65: =IF(AM65=0,0,((P65*AM65)-($Y$4*$Y$5*AM65)-AI$7*AM65)/1.21) -> 0 | BC65: =IF(AN65=0,0,((Q65*AN65)-($Y$4*$Y$5*AN65)-AJ$7*AN65)/1.21) -> 34647541 | BD65: =IF(AO65=0,0,((R65*AO65)-($Y$4*$Y$5*AO65)-AK$7*AO65)/1.21) -> 1.0930049e+08 | BE65: =SUM(AR65:BD65) -> 1.0531724e+10
B66: Shoulder | E66: 300000 | F66: =F$65+$E66 -> 2850000 | G66: =G$65+$E66 -> 3050000 | H66: =H$65+$E66 -> 3150000 | I66: =I$65+$E66 -> 3750000 | J66: =J$65+$E66 -> 4400000 | K66: =K$65+$E66 -> 5500000 | L66: =L$65+$E66 -> 5850000 | M66: =M$65+$E66 -> 7100000 | ... R66: =R$65+$E66 -> 30900000
B67: High | E67: 600000 | F67: =F$65+$E67 -> 3150000 | G67: =G$65+$E67 -> 3350000 | H67: =H$65+$E67 -> 3450000 | I67: =I$65+$E67 -> 4050000 | J67: =J$65+$E67 -> 4700000 | K67: =K$65+$E67 -> 5800000 | L67: =L$65+$E67 -> 6150000 | M67: =M$65+$E67 -> 7400000 | ... R67: =R$65+$E67 -> 31200000
B68: Peak | E68: 800000 | F68: =F$65+$E68 -> 3350000 | G68: =G$65+$E68 -> 3550000 | H68: =H$65+$E68 -> 3650000 | I68: =I$65+$E68 -> 4250000 | J68: =J$65+$E68 -> 4900000 | K68: =K$65+$E68 -> 6000000 | L68: =L$65+$E68 -> 6350000 | M68: =M$65+$E68 -> 7600000 | ... R68: =R$65+$E68 -> 31400000 | AC68: =$AC$15*Y68 -> 0 | AD68: =$AD$15*Y68 -> 0 | AE68: =$AE$15*Y68 -> 0 | AF68: =$AF$15*Y68 -> 0 | AG68: =$AG$15*Y68 -> 0 | AH68: =$AH$15*Y68 -> 0 | AI68: =$AI$15*Y68 -> 0 | AJ68: =$AJ$15*Y68 -> 0 | AK68: =$AK$15*Y68 -> 0 | AL68: =$AL$15*Y68 -> 0 | AN68: =$AN$15*Y68 -> 0 | AO68: =$AO$15*Y68 -> 0 | AP68: =SUM(AC68:AO68) -> 0 | AR68: =IF(AC68=0,0,((F68*AC68)-($Y$4*$Y$5*AC68)-Y$7*AC68)/1.21) -> 0 | AS68: =IF(AD68=0,0,((G68*AD68)-($Y$4*$Y$5*AD68)-Z$7*AD68)/1.21) -> 0 | AT68: =IF(AE68=0,0,((H68*AE68)-($Y$4*$Y$5*AE68)-AA$7*AE68)/1.21) -> 0 | AU68: =IF(AF68=0,0,((I68*AF68)-($Y$4*$Y$5*AF68)-AB$7*AF68)/1.21) -> 0 | AV68: =IF(AG68=0,0,((J68*AG68)-($Y$4*$Y$5*AG68)-AC$7*AG68)/1.21) -> 0 | AW68: =IF(AH68=0,0,((K68*AH68)-($Y$4*$Y$5*AH68)-AD$7*AH68)/1.21) -> 0 | AX68: =IF(AI68=0,0,((L68*AI68)-($Y$4*$Y$5*AI68)-AE$7*AI68)/1.21) -> 0 | AY68: =IF(AJ68=0,0,((M68*AJ68)-($Y$4*$Y$5*AJ68)-AF$7*AJ68)/1.21) -> 0 | AZ68: =IF(AK68=0,0,((O68*AK68)-($Z$4*$Z$5*AK68)-AD51*AK68)/1.21) -> 0 | BA68: =IF(AL68=0,0,((N68*AL68)-($Y$4*$Y$5*AL68)-AH$7*AL68)/1.21) -> 0 | BB68: =IF(AM68=0,0,((P68*AM68)-($Y$4*$Y$5*AM68)-AI$7*AM68)/1.21) -> 0 | BC68: =IF(AN68=0,0,((Q68*AN68)-($Y$4*$Y$5*AN68)-AJ$7*AN68)/1.21) -> 0 | BD68: =IF(AO68=0,0,((R68*AO68)-($Y$4*$Y$5*AO68)-AK$7*AO68)/1.21) -> 0 | BE68: =SUM(AR68:BD68) -> 0
B69: Domestic / Prefered | Y69: 0.09 | AC69: =$AC$15*Y69 -> 4667.7739 | AD69: =$AD$15*Y69 -> 648.30192 | AE69: =$AE$15*Y69 -> 6003.2758 | AF69: =$AF$15*Y69 -> 1037.2831 | AG69: =$AG$15*Y69 -> 129.66038 | AH69: =$AH$15*Y69 -> 129.66038 | AI69: =$AI$15*Y69 -> 64.830192 | AJ69: =$AJ$15*Y69 -> 64.830192 | AK69: =$AK$15*Y69 -> 51.864154 | AL69: =$AL$15*Y69 -> 129.66038 | AN69: =$AN$15*Y69 -> 12.966038 | AO69: =$AO$15*Y69 -> 12.966038 | AP69: =SUM(AC69:AO69) -> 12953.072 | AR69: =IF(AC69=0,0,((F69*AC69)-($Y$4*$Y$5*AC69)-Y$7*AC69)/1.21) -> 0 | AS69: =IF(AD69=0,0,((G69*AD69)-($Y$4*$Y$5*AD69)-Z$7*AD69)/1.21) -> 0 | AT69: =IF(AE69=0,0,((H69*AE69)-($Y$4*$Y$5*AE69)-AA$7*AE69)/1.21) -> 0 | AU69: =IF(AF69=0,0,((I69*AF69)-($Y$4*$Y$5*AF69)-AB$7*AF69)/1.21) -> 0 | AV69: =IF(AG69=0,0,((J69*AG69)-($Y$4*$Y$5*AG69)-AC$7*AG69)/1.21) -> 0 | AW69: =IF(AH69=0,0,((K69*AH69)-($Y$4*$Y$5*AH69)-AD$7*AH69)/1.21) -> 0 | AX69: =IF(AI69=0,0,((L69*AI69)-($Y$4*$Y$5*AI69)-AE$7*AI69)/1.21) -> 0 | AY69: =IF(AJ69=0,0,((M69*AJ69)-($Y$4*$Y$5*AJ69)-AF$7*AJ69)/1.21) -> 0 | AZ69: =IF(AK69=0,0,((O69*AK69)-($Z$4*$Z$5*AK69)-AD52*AK69)/1.21) -> -21602920 | BA69: =IF(AL69=0,0,((N69*AL69)-($Y$4*$Y$5*AL69)-AH$7*AL69)/1.21) -> 0 | BB69: =IF(AM69=0,0,((P69*AM69)-($Y$4*$Y$5*AM69)-AI$7*AM69)/1.21) -> 0 | BC69: =IF(AN69=0,0,((Q69*AN69)-($Y$4*$Y$5*AN69)-AJ$7*AN69)/1.21) -> 0 | BD69: =IF(AO69=0,0,((R69*AO69)-($Y$4*$Y$5*AO69)-AK$7*AO69)/1.21) -> 0 | BE69: =SUM(AR69:BD69) -> -21602920
B70: Travel Agent Preferred 4 | Y70: 0 | AC70: =$AC$15*Y70 -> 0 | AD70: =$AD$15*Y70 -> 0 | AE70: =$AE$15*Y70 -> 0 | AF70: =$AF$15*Y70 -> 0 | AG70: =$AG$15*Y70 -> 0 | AH70: =$AH$15*Y70 -> 0 | AI70: =$AI$15*Y70 -> 0 | AJ70: =$AJ$15*Y70 -> 0 | AK70: =$AK$15*Y70 -> 0 | AL70: =$AL$15*Y70 -> 0 | AM70: =$AM$15*Y70 -> 0 | AN70: =$AN$15*Y70 -> 0 | AO70: =$AO$15*Y70 -> 0 | AP70: =SUM(AC70:AO70) -> 0 | AR70: =IF(AC70=0,0,((F70*AC70)-($Y$4*$Y$5*AC70)-Y$7*AC70)/1.21) -> 0 | AS70: =IF(AD70=0,0,((G70*AD70)-($Y$4*$Y$5*AD70)-Z$7*AD70)/1.21) -> 0 | AT70: =IF(AE70=0,0,((H70*AE70)-($Y$4*$Y$5*AE70)-AA$7*AE70)/1.21) -> 0 | AU70: =IF(AF70=0,0,((I70*AF70)-($Y$4*$Y$5*AF70)-AB$7*AF70)/1.21) -> 0 | AV70: =IF(AG70=0,0,((J70*AG70)-($Y$4*$Y$5*AG70)-AC$7*AG70)/1.21) -> 0 | AW70: =IF(AH70=0,0,((K70*AH70)-($Y$4*$Y$5*AH70)-AD$7*AH70)/1.21) -> 0 | AX70: =IF(AI70=0,0,((L70*AI70)-($Y$4*$Y$5*AI70)-AE$7*AI70)/1.21) -> 0 | AY70: =IF(AJ70=0,0,((M70*AJ70)-($Y$4*$Y$5*AJ70)-AF$7*AJ70)/1.21) -> 0 | AZ70: =IF(AK70=0,0,((O70*AK70)-($Z$4*$Z$5*AK70)-AD57*AK70)/1.21) -> 0 | BA70: =IF(AL70=0,0,((N70*AL70)-($Y$4*$Y$5*AL70)-AH$7*AL70)/1.21) -> 0 | BB70: =IF(AM70=0,0,((P70*AM70)-($Y$4*$Y$5*AM70)-AI$7*AM70)/1.21) -> 0 | BC70: =IF(AN70=0,0,((Q70*AN70)-($Y$4*$Y$5*AN70)-AJ$7*AN70)/1.21) -> 0 | BD70: =IF(AO70=0,0,((R70*AO70)-($Y$4*$Y$5*AO70)-AK$7*AO70)/1.21) -> 0 | BE70: =SUM(AR70:BD70) -> 0
B71: Travel Agent Promotion 1 | Y71: 0 | AC71: =$AC$15*Y71 -> 0 | AD71: =$AD$15*Y71 -> 0 | AE71: =$AE$15*Y71 -> 0 | AF71: =$AF$15*Y71 -> 0 | AG71: =$AG$15*Y71 -> 0 | AH71: =$AH$15*Y71 -> 0 | AI71: =$AI$15*Y71 -> 0 | AJ71: =$AJ$15*Y71 -> 0 | AK71: =$AK$15*Y71 -> 0 | AL71: =$AL$15*Y71 -> 0 | AM71: =$AM$15*Y71 -> 0 | AN71: =$AN$15*Y71 -> 0 | AO71: =$AO$15*Y71 -> 0 | AP71: =SUM(AC71:AO71) -> 0 | AR71: =IF(AC71=0,0,((F71*AC71)-($Y$4*$Y$5*AC71)-Y$7*AC71)/1.21) -> 0 | AS71: =IF(AD71=0,0,((G71*AD71)-($Y$4*$Y$5*AD71)-Z$7*AD71)/1.21) -> 0 | AT71: =IF(AE71=0,0,((H71*AE71)-($Y$4*$Y$5*AE71)-AA$7*AE71)/1.21) -> 0 | AU71: =IF(AF71=0,0,((I71*AF71)-($Y$4*$Y$5*AF71)-AB$7*AF71)/1.21) -> 0 | AV71: =IF(AG71=0,0,((J71*AG71)-($Y$4*$Y$5*AG71)-AC$7*AG71)/1.21) -> 0 | AW71: =IF(AH71=0,0,((K71*AH71)-($Y$4*$Y$5*AH71)-AD$7*AH71)/1.21) -> 0 | AX71: =IF(AI71=0,0,((L71*AI71)-($Y$4*$Y$5*AI71)-AE$7*AI71)/1.21) -> 0 | AY71: =IF(AJ71=0,0,((M71*AJ71)-($Y$4*$Y$5*AJ71)-AF$7*AJ71)/1.21) -> 0 | AZ71: =IF(AK71=0,0,((O71*AK71)-($Z$4*$Z$5*AK71)-AD58*AK71)/1.21) -> 0 | BA71: =IF(AL71=0,0,((N71*AL71)-($Y$4*$Y$5*AL71)-AH$7*AL71)/1.21) -> 0 | BB71: =IF(AM71=0,0,((P71*AM71)-($Y$4*$Y$5*AM71)-AI$7*AM71)/1.21) -> 0 | BC71: =IF(AN71=0,0,((Q71*AN71)-($Y$4*$Y$5*AN71)-AJ$7*AN71)/1.21) -> 0 | BD71: =IF(AO71=0,0,((R71*AO71)-($Y$4*$Y$5*AO71)-AK$7*AO71)/1.21) -> 0 | BE71: =SUM(AR71:BD71) -> 0
B72: Travel Agent Promotion 2 | Y72: 0 | AC72: =$AC$15*Y72 -> 0 | AD72: =$AD$15*Y72 -> 0 | AE72: =$AE$15*Y72 -> 0 | AF72: =$AF$15*Y72 -> 0 | AG72: =$AG$15*Y72 -> 0 | AH72: =$AH$15*Y72 -> 0 | AI72: =$AI$15*Y72 -> 0 | AJ72: =$AJ$15*Y72 -> 0 | AK72: =$AK$15*Y72 -> 0 | AL72: =$AL$15*Y72 -> 0 | AM72: =$AM$15*Y72 -> 0 | AN72: =$AN$15*Y72 -> 0 | AO72: =$AO$15*Y72 -> 0 | AP72: =SUM(AC72:AO72) -> 0 | AR72: =IF(AC72=0,0,((F72*AC72)-($Y$4*$Y$5*AC72)-Y$7*AC72)/1.21) -> 0 | AS72: =IF(AD72=0,0,((G72*AD72)-($Y$4*$Y$5*AD72)-Z$7*AD72)/1.21) -> 0 | AT72: =IF(AE72=0,0,((H72*AE72)-($Y$4*$Y$5*AE72)-AA$7*AE72)/1.21) -> 0 | AU72: =IF(AF72=0,0,((I72*AF72)-($Y$4*$Y$5*AF72)-AB$7*AF72)/1.21) -> 0 | AV72: =IF(AG72=0,0,((J72*AG72)-($Y$4*$Y$5*AG72)-AC$7*AG72)/1.21) -> 0 | AW72: =IF(AH72=0,0,((K72*AH72)-($Y$4*$Y$5*AH72)-AD$7*AH72)/1.21) -> 0 | AX72: =IF(AI72=0,0,((L72*AI72)-($Y$4*$Y$5*AI72)-AE$7*AI72)/1.21) -> 0 | AY72: =IF(AJ72=0,0,((M72*AJ72)-($Y$4*$Y$5*AJ72)-AF$7*AJ72)/1.21) -> 0 | AZ72: =IF(AK72=0,0,((O72*AK72)-($Z$4*$Z$5*AK72)-AD59*AK72)/1.21) -> 0 | BA72: =IF(AL72=0,0,((N72*AL72)-($Y$4*$Y$5*AL72)-AH$7*AL72)/1.21) -> 0 | BB72: =IF(AM72=0,0,((P72*AM72)-($Y$4*$Y$5*AM72)-AI$7*AM72)/1.21) -> 0 | BC72: =IF(AN72=0,0,((Q72*AN72)-($Y$4*$Y$5*AN72)-AJ$7*AN72)/1.21) -> 0 | BD72: =IF(AO72=0,0,((R72*AO72)-($Y$4*$Y$5*AO72)-AK$7*AO72)/1.21) -> 0 | BE72: =SUM(AR72:BD72) -> 0
B73: KKG - Personal Visit | F73: =F32-250000 -> 1900000 | G73: =G32-250000 -> 2100000 | H73: =H32-250000 -> 2200000 | I73: =I32-250000 -> 2800000 | J73: =J32-250000 -> 3450000 | K73: =K32-250000 -> 4550000 | L73: =L32-250000 -> 4900000 | M73: =M32-250000 -> 6150000 | ... R73: =R32-250000 -> 29950000 | X73: =SUM(Y73:Y77) -> 0.0032 | Y73: 0 | Z73: 0.0037753778 | AA73: 0.0019417278 | AC73: =$AC$15*Y73 -> 0 | AD73: =$AD$15*Y73 -> 0 | AE73: =$AE$15*Y73 -> 0 | AF73: =$AF$15*Y73 -> 0 | AG73: =$AG$15*Y73 -> 0 | AH73: =$AH$15*Y73 -> 0 | AI73: =$AI$15*Y73 -> 0 | AJ73: =$AJ$15*Y73 -> 0 | AK73: =$AK$15*Y73 -> 0 | AL73: =$AL$15*Y73 -> 0 | AN73: =$AN$15*Y73 -> 0 | AO73: =$AO$15*Y73 -> 0 | AP73: =SUM(AC73:AO73) -> 0 | AR73: =IF(AC73=0,0,((F73*AC73)-($Y$4*$Y$5*AC73)-Y$7*AC73)/1.21) -> 0 | AS73: =IF(AD73=0,0,((G73*AD73)-($Y$4*$Y$5*AD73)-Z$7*AD73)/1.21) -> 0 | AT73: =IF(AE73=0,0,((H73*AE73)-($Y$4*$Y$5*AE73)-AA$7*AE73)/1.21) -> 0 | AU73: =IF(AF73=0,0,((I73*AF73)-($Y$4*$Y$5*AF73)-AB$7*AF73)/1.21) -> 0 | AV73: =IF(AG73=0,0,((J73*AG73)-($Y$4*$Y$5*AG73)-AC$7*AG73)/1.21) -> 0 | AW73: =IF(AH73=0,0,((K73*AH73)-($Y$4*$Y$5*AH73)-AD$7*AH73)/1.21) -> 0 | AX73: =IF(AI73=0,0,((L73*AI73)-($Y$4*$Y$5*AI73)-AE$7*AI73)/1.21) -> 0 | AY73: =IF(AJ73=0,0,((M73*AJ73)-($Y$4*$Y$5*AJ73)-AF$7*AJ73)/1.21) -> 0 | AZ73: =IF(AK73=0,0,((O73*AK73)-($Z$4*$Z$5*AK73)-AD60*AK73)/1.21) -> 0 | BA73: =IF(AL73=0,0,((N73*AL73)-($Y$4*$Y$5*AL73)-AH$7*AL73)/1.21) -> 0 | BB73: =IF(AM73=0,0,((P73*AM73)-($Y$4*$Y$5*AM73)-AI$7*AM73)/1.21) -> 0 | BC73: =IF(AN73=0,0,((Q73*AN73)-($Y$4*$Y$5*AN73)-AJ$7*AN73)/1.21) -> 0 | BD73: =IF(AO73=0,0,((R73*AO73)-($Y$4*$Y$5*AO73)-AK$7*AO73)/1.21) -> 0 | BE73: =SUM(AR73:BD73) -> 0 | BF73: =SUM(BE73:BE76) -> #REF! | BG73: KKG | BH73: 820188567
B74: KKG - Relasi | F74: =F73+150000 -> 2050000 | G74: =G73+150000 -> 2250000 | H74: =H73+150000 -> 2350000 | I74: =I73+150000 -> 2950000 | J74: =J73+150000 -> 3600000 | K74: =K73+150000 -> 4700000 | L74: =L73+150000 -> 5050000 | M74: =M73+150000 -> 6300000 | ... R74: =R73+150000 -> 30100000 | Y74: 0.003 | AC74: =$AC$15*Y74 -> 155.59246 | AD74: =$AD$15*Y74 -> 21.610064 | AE74: =$AE$15*Y74 -> 200.10919 | AF74: =$AF$15*Y74 -> 34.576103 | AG74: =$AG$15*Y74 -> 4.3220128 | AH74: =$AH$15*Y74 -> 4.3220128 | AI74: =$AI$15*Y74 -> 2.1610064 | AJ74: =$AJ$15*Y74 -> 2.1610064 | AK74: =$AK$15*Y74 -> 1.7288051 | AL74: =$AL$15*Y74 -> 4.3220128 | AN74: =$AN$15*Y74 -> 0.43220128 | AO74: =$AO$15*Y74 -> 0.43220128 | AP74: =SUM(AC74:AO74) -> 431.76908 | AR74: =IF(AC74=0,0,((F74*AC74)-($Y$4*$Y$5*AC74)-Y$7*AC74)/1.21) -> 2.6360706e+08 | AS74: =IF(AD74=0,0,((G74*AD74)-($Y$4*$Y$5*AD74)-Z$7*AD74)/1.21) -> 40184004 | AT74: =IF(AE74=0,0,((H74*AE74)-($Y$4*$Y$5*AE74)-AA$7*AE74)/1.21) -> 3.8864182e+08 | AU74: =IF(AF74=0,0,((I74*AF74)-($Y$4*$Y$5*AF74)-AB$7*AF74)/1.21) -> 84297110 | AV74: =IF(AG74=0,0,((J74*AG74)-($Y$4*$Y$5*AG74)-AC$7*AG74)/1.21) -> 12858881 | AW74: =IF(AH74=0,0,((K74*AH74)-($Y$4*$Y$5*AH74)-AD$7*AH74)/1.21) -> 16787984 | AX74: =IF(AI74=0,0,((L74*AI74)-($Y$4*$Y$5*AI74)-AE$7*AI74)/1.21) -> 9019076.4 | AY74: =IF(AJ74=0,0,((M74*AJ74)-($Y$4*$Y$5*AJ74)-AF$7*AJ74)/1.21) -> 11251521 | AZ74: =IF(AK74=0,0,((O74*AK74)-($Z$4*$Z$5*AK74)-#REF!*AK74)/1.21) -> #REF! | BA74: =IF(AL74=0,0,((N74*AL74)-($Y$4*$Y$5*AL74)-AH$7*AL74)/1.21) -> 24646189 | BB74: =IF(AM74=0,0,((P74*AM74)-($Y$4*$Y$5*AM74)-AI$7*AM74)/1.21) -> 0 | BC74: =IF(AN74=0,0,((Q74*AN74)-($Y$4*$Y$5*AN74)-AJ$7*AN74)/1.21) -> 3286158.5 | BD74: =IF(AO74=0,0,((R74*AO74)-($Y$4*$Y$5*AO74)-AK$7*AO74)/1.21) -> 10751453 | BE74: =SUM(AR74:BD74) -> #REF!
B75: Owner Rate | F75: =F73 -> 1900000 | G75: =G73 -> 2100000 | H75: =H73 -> 2200000 | I75: =I73 -> 2800000 | J75: =J73 -> 3450000 | K75: =K73 -> 4550000 | L75: =L73 -> 4900000 | M75: =M73 -> 6150000 | ... R75: =R73 -> 29950000 | Y75: 0.0002 | AC75: =$AC$15*Y75 -> 10.372831 | AD75: =$AD$15*Y75 -> 1.4406709 | AE75: =$AE$15*Y75 -> 13.340613 | AF75: =$AF$15*Y75 -> 2.3050735 | AG75: =$AG$15*Y75 -> 0.28813419 | AH75: =$AH$15*Y75 -> 0.28813419 | AI75: =$AI$15*Y75 -> 0.14406709 | AJ75: =$AJ$15*Y75 -> 0.14406709 | AK75: =$AK$15*Y75 -> 0.11525368 | AL75: =$AL$15*Y75 -> 0.28813419 | AN75: =$AN$15*Y75 -> 0.028813419 | AO75: =$AO$15*Y75 -> 0.028813419 | AP75: =SUM(AC75:AO75) -> 28.784605 | AR75: =IF(AC75=0,0,((F75*AC75)-($Y$4*$Y$5*AC75)-Y$7*AC75)/1.21) -> 16287916 | AS75: =IF(AD75=0,0,((G75*AD75)-($Y$4*$Y$5*AD75)-Z$7*AD75)/1.21) -> 2500338 | AT75: =IF(AE75=0,0,((H75*AE75)-($Y$4*$Y$5*AE75)-AA$7*AE75)/1.21) -> 24255660 | AU75: =IF(AF75=0,0,((I75*AF75)-($Y$4*$Y$5*AF75)-AB$7*AF75)/1.21) -> 5334054.4 | AV75: =IF(AG75=0,0,((J75*AG75)-($Y$4*$Y$5*AG75)-AC$7*AG75)/1.21) -> 821539.63 | AW75: =IF(AH75=0,0,((K75*AH75)-($Y$4*$Y$5*AH75)-AD$7*AH75)/1.21) -> 1083479.8 | AX75: =IF(AI75=0,0,((L75*AI75)-($Y$4*$Y$5*AI75)-AE$7*AI75)/1.21) -> 583412.2 | AY75: =IF(AJ75=0,0,((M75*AJ75)-($Y$4*$Y$5*AJ75)-AF$7*AJ75)/1.21) -> 732241.84 | AZ75: =IF(AK75=0,0,((O75*AK75)-($Z$4*$Z$5*AK75)-#REF!*AK75)/1.21) -> #REF! | BA75: =IF(AL75=0,0,((N75*AL75)-($Y$4*$Y$5*AL75)-AH$7*AL75)/1.21) -> 1607360.1 | BB75: =IF(AM75=0,0,((P75*AM75)-($Y$4*$Y$5*AM75)-AI$7*AM75)/1.21) -> 0 | BC75: =IF(AN75=0,0,((Q75*AN75)-($Y$4*$Y$5*AN75)-AJ$7*AN75)/1.21) -> 215505.32 | BD75: =IF(AO75=0,0,((R75*AO75)-($Y$4*$Y$5*AO75)-AK$7*AO75)/1.21) -> 713191.65 | BE75: =SUM(AR75:BD75) -> #REF!
B76: GOHR DLK - Single Occupancy | F76: =F75 -> 1900000 | G76: =G75 -> 2100000 | H76: =H75 -> 2200000 | I76: =I75 -> 2800000 | J76: =J75 -> 3450000 | K76: =K75 -> 4550000 | L76: =L75 -> 4900000 | M76: =M75 -> 6150000 | ... R76: =R75 -> 29950000 | Y76: 0 | AC76: =$AC$15*Y76 -> 0 | AD76: =$AD$15*Y76 -> 0 | AE76: =$AE$15*Y76 -> 0 | AF76: =$AF$15*Y76 -> 0 | AG76: =$AG$15*Y76 -> 0 | AH76: =$AH$15*Y76 -> 0 | AI76: =$AI$15*Y76 -> 0 | AJ76: =$AJ$15*Y76 -> 0 | AK76: =$AK$15*Y76 -> 0 | AL76: =$AL$15*Y76 -> 0 | AM76: =$AM$15*Y76 -> 0 | AN76: =$AN$15*Y76 -> 0 | AO76: =$AO$15*Y76 -> 0 | AP76: =SUM(AC76:AO76) -> 0 | AR76: =IF(AC76=0,0,((F76*AC76)-($Y$4*$Y$5*AC76)-Y$7*AC76)/1.21) -> 0 | AS76: =IF(AD76=0,0,((G76*AD76)-($Y$4*$Y$5*AD76)-Z$7*AD76)/1.21) -> 0 | AT76: =IF(AE76=0,0,((H76*AE76)-($Y$4*$Y$5*AE76)-AA$7*AE76)/1.21) -> 0 | AU76: =IF(AF76=0,0,((I76*AF76)-($Y$4*$Y$5*AF76)-AB$7*AF76)/1.21) -> 0 | AV76: =IF(AG76=0,0,((J76*AG76)-($Y$4*$Y$5*AG76)-AC$7*AG76)/1.21) -> 0 | AW76: =IF(AH76=0,0,((K76*AH76)-($Y$4*$Y$5*AH76)-AD$7*AH76)/1.21) -> 0 | AX76: =IF(AI76=0,0,((L76*AI76)-($Y$4*$Y$5*AI76)-AE$7*AI76)/1.21) -> 0 | AY76: =IF(AJ76=0,0,((M76*AJ76)-($Y$4*$Y$5*AJ76)-AF$7*AJ76)/1.21) -> 0 | AZ76: =IF(AK76=0,0,((O76*AK76)-($Z$4*$Z$5*AK76)-#REF!*AK76)/1.21) -> 0 | BA76: =IF(AL76=0,0,((N76*AL76)-($Y$4*$Y$5*AL76)-AH$7*AL76)/1.21) -> 0 | BB76: =IF(AM76=0,0,((P76*AM76)-($Y$4*$Y$5*AM76)-AI$7*AM76)/1.21) -> 0 | BC76: =IF(AN76=0,0,((Q76*AN76)-($Y$4*$Y$5*AN76)-AJ$7*AN76)/1.21) -> 0 | BD76: =IF(AO76=0,0,((R76*AO76)-($Y$4*$Y$5*AO76)-AK$7*AO76)/1.21) -> 0 | BE76: =SUM(AR76:BD76) -> 0
B77: GOHR DLK - Double Occupancy | F77: =F76 -> 1900000 | G77: =G76 -> 2100000 | H77: =H76 -> 2200000 | I77: =I76 -> 2800000 | J77: =J76 -> 3450000 | K77: =K76 -> 4550000 | L77: =L76 -> 4900000 | M77: =M76 -> 6150000 | ... R77: =R76 -> 29950000 | AC77: =$AC$15*Y77 -> 0 | AD77: =$AD$15*Y77 -> 0 | AE77: =$AE$15*Y77 -> 0 | AF77: =$AF$15*Y77 -> 0 | AG77: =$AG$15*Y77 -> 0 | AH77: =$AH$15*Y77 -> 0 | AI77: =$AI$15*Y77 -> 0 | AJ77: =$AJ$15*Y77 -> 0 | AK77: =$AK$15*Y77 -> 0 | AL77: =$AL$15*Y77 -> 0 | AN77: =$AN$15*Y77 -> 0 | AO77: =$AO$15*Y77 -> 0 | AP77: =SUM(AC77:AO77) -> 0 | AR77: =IF(AC77=0,0,((F77*AC77)-($Y$4*$Y$5*AC77)-Y$7*AC77)/1.21) -> 0 | AS77: =IF(AD77=0,0,((G77*AD77)-($Y$4*$Y$5*AD77)-Z$7*AD77)/1.21) -> 0 | AT77: =IF(AE77=0,0,((H77*AE77)-($Y$4*$Y$5*AE77)-AA$7*AE77)/1.21) -> 0 | AU77: =IF(AF77=0,0,((I77*AF77)-($Y$4*$Y$5*AF77)-AB$7*AF77)/1.21) -> 0 | AV77: =IF(AG77=0,0,((J77*AG77)-($Y$4*$Y$5*AG77)-AC$7*AG77)/1.21) -> 0 | AW77: =IF(AH77=0,0,((K77*AH77)-($Y$4*$Y$5*AH77)-AD$7*AH77)/1.21) -> 0 | AX77: =IF(AI77=0,0,((L77*AI77)-($Y$4*$Y$5*AI77)-AE$7*AI77)/1.21) -> 0 | AY77: =IF(AJ77=0,0,((M77*AJ77)-($Y$4*$Y$5*AJ77)-AF$7*AJ77)/1.21) -> 0 | AZ77: =IF(AK77=0,0,((O77*AK77)-($Z$4*$Z$5*AK77)-#REF!*AK77)/1.21) -> 0 | BA77: =IF(AL77=0,0,((N77*AL77)-($Y$4*$Y$5*AL77)-AH$7*AL77)/1.21) -> 0 | BB77: =IF(AM77=0,0,((P77*AM77)-($Y$4*$Y$5*AM77)-AI$7*AM77)/1.21) -> 0 | BC77: =IF(AN77=0,0,((Q77*AN77)-($Y$4*$Y$5*AN77)-AJ$7*AN77)/1.21) -> 0 | BD77: =IF(AO77=0,0,((R77*AO77)-($Y$4*$Y$5*AO77)-AK$7*AO77)/1.21) -> 0 | BE77: =SUM(AR77:BD77) -> 0
B78: GROUP SERIES | F78: =F75 -> 1900000 | H78: =H73 -> 2200000 | X78: =Y78 -> 0.0419 | Y78: 0.0419 | Z78: 0.041895595 | AA78: 0.021694488 | AC78: =$AC$15*Y78 -> 2173.1081 | AE78: =$AE$15*Y78 -> 2794.8584 | AP78: =SUM(AC78:AO78) -> 4967.9665 | AR78: =IF(AC78=0,0,((F78*AC78)-($Y$4*$Y$5*AC78)-Y$7*AC78)/1.21) -> 3.4123184e+09 | AS78: =IF(AD78=0,0,((G78*AD78)-($Y$4*$Y$5*AD78)-Z$7*AD78)/1.21) -> 0 | AT78: =IF(AE78=0,0,((H78*AE78)-($Y$4*$Y$5*AE78)-AA$7*AE78)/1.21) -> 5.0815607e+09 | AU78: =IF(AF78=0,0,((I78*AF78)-($Y$4*$Y$5*AF78)-AB$7*AF78)/1.21) -> 0 | AV78: =IF(AG78=0,0,((J78*AG78)-($Y$4*$Y$5*AG78)-AC$7*AG78)/1.21) -> 0 | AW78: =IF(AH78=0,0,((K78*AH78)-($Y$4*$Y$5*AH78)-AD$7*AH78)/1.21) -> 0 | AX78: =IF(AI78=0,0,((L78*AI78)-($Y$4*$Y$5*AI78)-AE$7*AI78)/1.21) -> 0 | AY78: =IF(AJ78=0,0,((M78*AJ78)-($Y$4*$Y$5*AJ78)-AF$7*AJ78)/1.21) -> 0 | AZ78: =IF(AK78=0,0,((O78*AK78)-($Z$4*$Z$5*AK78)-AD61*AK78)/1.21) -> 0 | BA78: =IF(AL78=0,0,((N78*AL78)-($Y$4*$Y$5*AL78)-AH$7*AL78)/1.21) -> 0 | BB78: =IF(AM78=0,0,((P78*AM78)-($Y$4*$Y$5*AM78)-AI$7*AM78)/1.21) -> 0 | BC78: =IF(AN78=0,0,((Q78*AN78)-($Y$4*$Y$5*AN78)-AJ$7*AN78)/1.21) -> 0 | BD78: =IF(AO78=0,0,((R78*AO78)-($Y$4*$Y$5*AO78)-AK$7*AO78)/1.21) -> 0 | BE78: =SUM(AR78:BD78) -> 8.4938792e+09 | BF78: =BE78 -> 8.4938792e+09 | BG78: Group | BH78: 9101681813
B79: GROUP / Conference Price Points:
B80: Price Point 1 | F80: =F32 -> 2150000 | G80: =G32 -> 2350000 | H80: =H32 -> 2450000 | I80: =I32 -> 3050000 | J80: =J32 -> 3700000 | K80: =K32 -> 4800000 | L80: =L32 -> 5150000 | M80: =M32 -> 6400000 | ... R80: =R32 -> 30200000 | X80: =SUM(Y80:Y83) -> 0.23 | Y80: 0.04 | Z80: 0.19425272 | AA80: 0.25980522 | AC80: =$AC$15*Y80 -> 2074.5662 | AD80: =$AD$15*Y80 -> 288.13419 | AE80: =$AE$15*Y80 -> 2668.1226 | AF80: =$AF$15*Y80 -> 461.0147 | AG80: =$AG$15*Y80 -> 57.626838 | AH80: =$AH$15*Y80 -> 57.626838 | AI80: =$AI$15*Y80 -> 28.813419 | AJ80: =$AJ$15*Y80 -> 28.813419 | AK80: =$AK$15*Y80 -> 23.050735 | AL80: =$AL$15*Y80 -> 57.626838 | AM80: =$AM$15*Y80 -> 5.7626838 | AN80: =$AN$15*Y80 -> 5.7626838 | AO80: =$AO$15*Y80 -> 5.7626838 | AP80: =SUM(AC80:AO80) -> 5762.6838 | AR80: =IF(AC80=0,0,((F80*AC80)-($Y$4*$Y$5*AC80)-Y$7*AC80)/1.21) -> 3.6862126e+09 | AS80: =IF(AD80=0,0,((G80*AD80)-($Y$4*$Y$5*AD80)-Z$7*AD80)/1.21) -> 5.5959946e+08 | AT80: =IF(AE80=0,0,((H80*AE80)-($Y$4*$Y$5*AE80)-AA$7*AE80)/1.21) -> 5.402397e+09 | AU80: =IF(AF80=0,0,((I80*AF80)-($Y$4*$Y$5*AF80)-AB$7*AF80)/1.21) -> 1.1620619e+09 | AV80: =IF(AG80=0,0,((J80*AG80)-($Y$4*$Y$5*AG80)-AC$7*AG80)/1.21) -> 1.762143e+08 | AW80: =IF(AH80=0,0,((K80*AH80)-($Y$4*$Y$5*AH80)-AD$7*AH80)/1.21) -> 2.2860233e+08 | AX80: =IF(AI80=0,0,((L80*AI80)-($Y$4*$Y$5*AI80)-AE$7*AI80)/1.21) -> 1.2263563e+08 | AY80: =IF(AJ80=0,0,((M80*AJ80)-($Y$4*$Y$5*AJ80)-AF$7*AJ80)/1.21) -> 1.5240155e+08 | AZ80: =IF(AK80=0,0,((O80*AK80)-($Z$4*$Z$5*AK80)-AD64*AK80)/1.21) -> 1.275601e+08 | BA80: =IF(AL80=0,0,((N80*AL80)-($Y$4*$Y$5*AL80)-AH$7*AL80)/1.21) -> 3.333784e+08 | BB80: =IF(AM80=0,0,((P80*AM80)-($Y$4*$Y$5*AM80)-AI$7*AM80)/1.21) -> 51911779 | BC80: =IF(AN80=0,0,((Q80*AN80)-($Y$4*$Y$5*AN80)-AJ$7*AN80)/1.21) -> 44291702 | BD80: =IF(AO80=0,0,((R80*AO80)-($Y$4*$Y$5*AO80)-AK$7*AO80)/1.21) -> 1.4382897e+08 | BE80: =SUM(AR80:BD80) -> 1.2191096e+10 | BF80: =SUM(BE80:BE83) -> 5.2569292e+10 | BG80: MICE | BH80: 42200771263
B81: Price Point 2 | F81: =F80-50000 -> 2100000 | G81: =G80-50000 -> 2300000 | H81: =H80-50000 -> 2400000 | I81: =I80-50000 -> 3000000 | J81: =J80-50000 -> 3650000 | K81: =K80-50000 -> 4750000 | L81: =L80-50000 -> 5100000 | M81: =M80-50000 -> 6350000 | ... R81: =R80-50000 -> 30150000
B82: Price Point 3 | F82: =F81-50000 -> 2050000 | G82: =G81-50000 -> 2250000 | H82: =H81-50000 -> 2350000 | I82: =I81-50000 -> 2950000 | J82: =J81-50000 -> 3600000 | K82: =K81-50000 -> 4700000 | L82: =L81-50000 -> 5050000 | M82: =M81-50000 -> 6300000 | ... R82: =R81-50000 -> 30100000
B83: Price Point 4 | F83: =F82-50000 -> 2000000 | G83: =G82-50000 -> 2200000 | H83: =H82-50000 -> 2300000 | I83: =I82-50000 -> 2900000 | J83: =J82-50000 -> 3550000 | K83: =K82-50000 -> 4650000 | L83: =L82-50000 -> 5000000 | M83: =M82-50000 -> 6250000 | ... R83: =R82-50000 -> 30050000 | Y83: 0.19 | AC83: =$AC$15*Y83 -> 9854.1893 | AE83: =$AE$15*Y83 -> 12673.582 | AP83: =SUM(AC83:AO83) -> 22527.772 | AR83: =IF(AC83=0,0,((F83*AC83)-($Y$4*$Y$5*AC83)-Y$7*AC83)/1.21) -> 1.6287916e+10 | AS83: =IF(AD83=0,0,((G83*AD83)-($Y$4*$Y$5*AD83)-Z$7*AD83)/1.21) -> 0 | AT83: =IF(AE83=0,0,((H83*AE83)-($Y$4*$Y$5*AE83)-AA$7*AE83)/1.21) -> 2.409028e+10 | AU83: =IF(AF83=0,0,((I83*AF83)-($Y$4*$Y$5*AF83)-AB$7*AF83)/1.21) -> 0 | AV83: =IF(AG83=0,0,((J83*AG83)-($Y$4*$Y$5*AG83)-AC$7*AG83)/1.21) -> 0 | AW83: =IF(AH83=0,0,((K83*AH83)-($Y$4*$Y$5*AH83)-AD$7*AH83)/1.21) -> 0 | AX83: =IF(AI83=0,0,((L83*AI83)-($Y$4*$Y$5*AI83)-AE$7*AI83)/1.21) -> 0 | AY83: =IF(AJ83=0,0,((M83*AJ83)-($Y$4*$Y$5*AJ83)-AF$7*AJ83)/1.21) -> 0 | AZ83: =IF(AK83=0,0,((O83*AK83)-($Z$4*$Z$5*AK83)-AD65*AK83)/1.21) -> 0 | BA83: =IF(AL83=0,0,((N83*AL83)-($Y$4*$Y$5*AL83)-AH$7*AL83)/1.21) -> 0 | BB83: =IF(AM83=0,0,((P83*AM83)-($Y$4*$Y$5*AM83)-AI$7*AM83)/1.21) -> 0 | BC83: =IF(AN83=0,0,((Q83*AN83)-($Y$4*$Y$5*AN83)-AJ$7*AN83)/1.21) -> 0 | BD83: =IF(AO83=0,0,((R83*AO83)-($Y$4*$Y$5*AO83)-AK$7*AO83)/1.21) -> 0 | BE83: =SUM(AR83:BD83) -> 4.0378196e+10
B84: Group Adhoc | F84: =F83 -> 2000000 | G84: =G83 -> 2200000 | H84: =H83 -> 2300000 | I84: =I83 -> 2900000 | J84: =J83 -> 3550000 | K84: =K83 -> 4650000 | L84: =L83 -> 5000000 | M84: =M83 -> 6250000 | ... R84: =R83 -> 30050000 | X84: =Y84 -> 0.0064 | Y84: 0.0064 | Z84: 0.0064024044 | AA84: 0.0049000671 | AC84: =$AC$15*Y84 -> 331.93059 | AE84: =$AE$15*Y84 -> 426.89961 | AP84: =SUM(AC84:AO84) -> 758.8302 | AR84: =IF(AC84=0,0,((F84*AC84)-($Y$4*$Y$5*AC84)-Y$7*AC84)/1.21) -> 5.486456e+08 | AS84: =IF(AD84=0,0,((G84*AD84)-($Y$4*$Y$5*AD84)-Z$7*AD84)/1.21) -> 0 | AT84: =IF(AE84=0,0,((H84*AE84)-($Y$4*$Y$5*AE84)-AA$7*AE84)/1.21) -> 8.1146208e+08 | AU84: =IF(AF84=0,0,((I84*AF84)-($Y$4*$Y$5*AF84)-AB$7*AF84)/1.21) -> 0 | AV84: =IF(AG84=0,0,((J84*AG84)-($Y$4*$Y$5*AG84)-AC$7*AG84)/1.21) -> 0 | AW84: =IF(AH84=0,0,((K84*AH84)-($Y$4*$Y$5*AH84)-AD$7*AH84)/1.21) -> 0 | AX84: =IF(AI84=0,0,((L84*AI84)-($Y$4*$Y$5*AI84)-AE$7*AI84)/1.21) -> 0 | AY84: =IF(AJ84=0,0,((M84*AJ84)-($Y$4*$Y$5*AJ84)-AF$7*AJ84)/1.21) -> 0 | AZ84: =IF(AK84=0,0,((O84*AK84)-($Z$4*$Z$5*AK84)-AD68*AK84)/1.21) -> 0 | BA84: =IF(AL84=0,0,((N84*AL84)-($Y$4*$Y$5*AL84)-AH$7*AL84)/1.21) -> 0 | BB84: =IF(AM84=0,0,((P84*AM84)-($Y$4*$Y$5*AM84)-AI$7*AM84)/1.21) -> 0 | BC84: =IF(AN84=0,0,((Q84*AN84)-($Y$4*$Y$5*AN84)-AJ$7*AN84)/1.21) -> 0 | BD84: =IF(AO84=0,0,((R84*AO84)-($Y$4*$Y$5*AO84)-AK$7*AO84)/1.21) -> 0 | BE84: =SUM(AR84:BD84) -> 1.3601077e+09 | BF84: =BE84 -> 1.3601077e+09 | BG84: Adhoc | BH84: 1390901542
B85: Package | F85: =F83 -> 2000000 | G85: =G83 -> 2200000 | H85: =H83 -> 2300000 | I85: =I83 -> 2900000 | J85: =J83 -> 3550000 | K85: =K83 -> 4650000 | L85: =L83 -> 5000000 | M85: =M83 -> 6250000 | ... R85: =R83 -> 30050000 | X85: =Y85 -> 0.002 | Y85: 0.002 | Z85: 0.0020762952 | AA85: 0.000355814 | AC85: =$AC$15*Y85 -> 103.72831 | AE85: =$AE$15*Y85 -> 133.40613 | AP85: =SUM(AC85:AO85) -> 237.13444 | AR85: =IF(AC85=0,0,((F85*AC85)-($Y$4*$Y$5*AC85)-Y$7*AC85)/1.21) -> 1.7145175e+08 | AS85: =IF(AD85=0,0,((G85*AD85)-($Y$4*$Y$5*AD85)-Z$7*AD85)/1.21) -> 0 | AT85: =IF(AE85=0,0,((H85*AE85)-($Y$4*$Y$5*AE85)-AA$7*AE85)/1.21) -> 2.535819e+08 | AU85: =IF(AF85=0,0,((I85*AF85)-($Y$4*$Y$5*AF85)-AB$7*AF85)/1.21) -> 0 | AV85: =IF(AG85=0,0,((J85*AG85)-($Y$4*$Y$5*AG85)-AC$7*AG85)/1.21) -> 0 | AW85: =IF(AH85=0,0,((K85*AH85)-($Y$4*$Y$5*AH85)-AD$7*AH85)/1.21) -> 0 | AX85: =IF(AI85=0,0,((L85*AI85)-($Y$4*$Y$5*AI85)-AE$7*AI85)/1.21) -> 0 | AY85: =IF(AJ85=0,0,((M85*AJ85)-($Y$4*$Y$5*AJ85)-AF$7*AJ85)/1.21) -> 0 | AZ85: =IF(AK85=0,0,((O85*AK85)-($Z$4*$Z$5*AK85)-AD69*AK85)/1.21) -> 0 | BA85: =IF(AL85=0,0,((N85*AL85)-($Y$4*$Y$5*AL85)-AH$7*AL85)/1.21) -> 0 | BB85: =IF(AM85=0,0,((P85*AM85)-($Y$4*$Y$5*AM85)-AI$7*AM85)/1.21) -> 0 | BC85: =IF(AN85=0,0,((Q85*AN85)-($Y$4*$Y$5*AN85)-AJ$7*AN85)/1.21) -> 0 | BD85: =IF(AO85=0,0,((R85*AO85)-($Y$4*$Y$5*AO85)-AK$7*AO85)/1.21) -> 0 | BE85: =SUM(AR85:BD85) -> 4.2503365e+08 | BF85: =BE85 -> 4.2503365e+08 | BG85: Package | BH85: 451068374
B86: Extra Bed | F86: 1000000 | AC86: =$AC$15*Y86 -> 0 | AD86: =$AD$15*Y86 -> 0 | AE86: =$AE$15*Y86 -> 0 | AF86: =$AF$15*Y86 -> 0 | AG86: =$AG$15*Y86 -> 0 | AH86: =$AH$15*Y86 -> 0 | AI86: =$AI$15*Y86 -> 0 | AJ86: =$AJ$15*Y86 -> 0 | AK86: =$AK$15*Y86 -> 0 | AL86: =$AL$15*Y86 -> 0 | AM86: =$AM$15*Y86 -> 0 | AN86: =$AN$15*Y86 -> 0 | AO86: =$AO$15*Y86 -> 0 | AP86: =SUM(AC86:AO86) -> 0 | AR86: =IF(AC86=0,0,((F86*AC86)-($Y$4*$Y$5)-Y$7)/1.21) -> 0 | AS86: =IF(AD86=0,0,((G86*AD86)-($Y$4*$Y$5)-Z$7)/1.21) -> 0 | AT86: =IF(AE86=0,0,((H86*AE86)-($Y$4*$Y$5)-AA$7)/1.21) -> 0 | AU86: =IF(AF86=0,0,((I86*AF86)-($Y$4*$Y$5)-AB$7)/1.21) -> 0 | AV86: =IF(AG86=0,0,((J86*AG86)-($Y$4*$Y$5)-AC$7)/1.21) -> 0 | AW86: =IF(AH86=0,0,((K86*AH86)-($Y$4*$Y$5)-AD$7)/1.21) -> 0 | AX86: =IF(AI86=0,0,((L86*AI86)-($Y$4*$Y$5)-AE$7)/1.21) -> 0 | AY86: =IF(AJ86=0,0,((M86*AJ86)-($Y$4*$Y$5)-AF$7)/1.21) -> 0 | AZ86: =IF(AK86=0,0,((O86*AK86)-($Z$4*$Z$5*AK86)-AD76*AK86)/1.21) -> 0 | BA86: =IF(AL86=0,0,((N86*AL86)-($Y$4*$Y$5)-AH$7)/1.21) -> 0 | BB86: =IF(AM86=0,0,((P86*AM86)-($Y$4*$Y$5)-AI$7)/1.21) -> 0 | BC86: =IF(AN86=0,0,((Q86*AN86)-($Y$4*$Y$5)-AJ$7)/1.21) -> 0 | BD86: =IF(AO86=0,0,((R86*AO86)-($Y$4*$Y$5)-AK$7)/1.21) -> 0 | BE86: =SUM(AR86:BD86) -> 0
X87: =SUM(X16:X85) -> 0.9555 | Y87: =SUM(Y16:Y86) -> 0.9555 | Z87: =SUM(Z16:Z85) -> 1 | AA87: =SUM(AA16:AA85) -> 1 | AC87: =SUM(AC16:AC86) -> 49556.199 | AD87: =SUM(AD16:AD86) -> 6095.2393 | AE87: =SUM(AE16:AE86) -> 63734.778 | AF87: =SUM(AF16:AF86) -> 10967.843 | AG87: =SUM(AG16:AG86) -> 1383.2679 | AH87: =SUM(AH16:AH86) -> 1370.9679 | AI87: =SUM(AI16:AI86) -> 685.48393 | AJ87: =SUM(AJ16:AJ86) -> 685.48393 | ... AO87: =SUM(AO16:AO86) -> 137.03679 | AP87: =SUM(AC87:AO87) -> 136835.61 | AR87: =SUM(AR16:AR86) -> 8.3859428e+10 | AS87: =SUM(AS16:AS86) -> 1.0945003e+10 | AT87: =SUM(AT16:AT86) -> 1.2155391e+11 | AU87: =SUM(AU16:AU86) -> 2.6538996e+10 | AV87: =SUM(AV16:AV86) -> 4.1794231e+09 | AW87: =SUM(AW16:AW86) -> 5.1311981e+09 | AX87: =SUM(AX16:AX86) -> 2.7361957e+09 | AY87: =SUM(AY16:AY86) -> 8.9662716e+08 | ... BD87: =SUM(BD16:BD86) -> 8.2597951e+08 | BE87: =SUM(AR87:BD87) -> #REF! | BF87: =SUM(BF16:BF86) -> #REF! | BH87: =SUM(BH16:BH85) -> 217246750000
BG88: VAR | BH88: =BF87-BH87 -> #REF!

Sheet Sheet2
D11: Deluxe Room | E11: 2600000 | F11: 2900000 | G11: 3200000 | H11: 3400000
D12: Deluxe Pool Access | E12: 2800000 | F12: 3100000 | G12: 3400000 | H12: 3600000
D13: Premiere Room | E13: 2900000 | F13: 3200000 | G13: 3500000 | H13: 3700000
D14: Premiere Lagoon Access | E14: 3500000 | F14: 3800000 | G14: 4100000 | H14: 4300000
D15: Family Premiere | E15: 4150000 | F15: 4450000 | G15: 4750000 | H15: 4950000
D16: Deluxe Suite | E16: 5100000 | F16: 5400000 | G16: 5700000 | H16: 5900000
D17: Premiere Suite | E17: 5550000 | F17: 5850000 | G17: 6150000 | H17: 6350000
D18: The Anvaya Suite No Pool | E18: 6800000 | F18: 7100000 | G18: 7400000 | H18: 7600000
D19: The Anvaya Suite Whirl Pool | E19: 7350000 | F19: 7650000 | G19: 7950000 | H19: 8150000
D20: Beach Front Private Suite | E20: 7600000 | F20: 7900000 | G20: 8200000 | H20: 8400000
D21: Anvaya Residence | E21: 11000000 | F21: 11300000 | G21: 11600000 | H21: 11800000
D22: The Anvaya Suite with Pool | E22: 9450000 | F22: 9750000 | G22: 10050000 | H22: 10250000
D23: The Anvaya Villa | E23: 29650000 | F23: 29950000 | G23: 30250000 | H23: 30450000

Sheet tactical
B2: OTA Comission | D2: 0.16
A6: Room Type | B6: BAR - OTA | C6: OTA GEO | D6: OTA Net | E6: OTA GEO NET | F6: Wholesale Margin | G6: Wholesale Net | H6: Wholesaler Retail | I6: Parity Diff | J6: Parity Status | K6: Corporate | L6: WW | M6: margin Bedbanks | N6: Net to Bedbanks | O6: Hotelbeds - Differential
A7: Deluxe Room | B7: ='7. Rate Strategy'!F$28 -> 2431000 | C7: =B7-(B7*10%) -> 2187900 | D7: =B7*(1-$D$2) -> 2042040 | E7: =C7*(1-$D$2) -> 1837836 | F7: 0.15 | G7: =MROUND(B7*(1-F7),50000) -> 2050000 | H7: =G7*(1+F7) -> 2357500 | I7: =(B7-H7)/B7 -> 0.030234471 | J7: =IF(I7<=0.03,"✅","⚠️") -> ⚠️ | K7: 2150000 | L7: 2600000 | M7: 0.15 | N7: =FLOOR(B7*(1-M7),50000) -> 2050000 | O7: 0.05 | P7: =FLOOR(N7-(N7*O7),5000) -> 1945000 | Q7: =(P7-N7)/N7 -> -0.051219512
A8: Deluxe Pool Access | B8: ='7. Rate Strategy'!G$28 -> 2618000 | C8: =B8-(B8*10%) -> 2356200 | D8: =B8*(1-$D$2) -> 2199120 | E8: =C8*(1-$D$2) -> 1979208 | F8: 0.15 | G8: =MROUND(B8*(1-F8),50000) -> 2250000 | H8: =G8*(1+F8) -> 2587500 | I8: =(B8-H8)/B8 -> 0.011650115 | J8: =IF(I8<=0.03,"✅","⚠️") -> ✅ | K8: 2350000 | L8: 2800000 | M8: 0.15 | N8: =FLOOR(B8*(1-M8),50000) -> 2200000 | O8: 0.05 | P8: =FLOOR(N8-(N8*O8),5000) -> 2090000 | Q8: =(P8-N8)/N8 -> -0.05
A9: Premiere Room | B9: ='7. Rate Strategy'!H$28 -> 2767600 | C9: =B9-(B9*10%) -> 2490840 | D9: =B9*(1-$D$2) -> 2324784 | E9: =C9*(1-$D$2) -> 2092305.6 | F9: 0.15 | G9: =MROUND(B9*(1-F9),50000) -> 2350000 | H9: =G9*(1+F9) -> 2702500 | I9: =(B9-H9)/B9 -> 0.023522185 | J9: =IF(I9<=0.03,"✅","⚠️") -> ✅ | K9: 2450000 | L9: 2900000 | M9: 0.15 | N9: =FLOOR(B9*(1-M9),50000) -> 2350000 | O9: 0.05 | P9: =FLOOR(N9-(N9*O9),5000) -> 2230000 | Q9: =(P9-N9)/N9 -> -0.05106383
A10: Premiere Lagoon Access | B10: ='7. Rate Strategy'!I$28 -> 3440800 | C10: =B10-(B10*10%) -> 3096720 | D10: =B10*(1-$D$2) -> 2890272 | E10: =C10*(1-$D$2) -> 2601244.8 | F10: 0.11 | G10: =MROUND(B10*(1-F10),50000) -> 3050000 | H10: =G10*(1+F10) -> 3385500 | I10: =(B10-H10)/B10 -> 0.016071844 | J10: =IF(I10<=0.03,"✅","⚠️") -> ✅ | K10: 3050000 | L10: 3500000 | M10: 0.11 | N10: =FLOOR(B10*(1-M10),50000) -> 3050000 | O10: 0.05 | P10: =FLOOR(N10-(N10*O10),5000) -> 2895000 | Q10: =(P10-N10)/N10 -> -0.050819672
A11: Family Premiere | B11: ='7. Rate Strategy'!J$28 -> 4151400 | C11: =B11-(B11*10%) -> 3736260 | D11: =B11*(1-$D$2) -> 3487176 | E11: =C11*(1-$D$2) -> 3138458.4 | F11: 0.11 | G11: =MROUND(B11*(1-F11),50000) -> 3700000 | H11: =G11*(1+F11) -> 4107000 | I11: =(B11-H11)/B11 -> 0.010695187 | J11: =IF(I11<=0.03,"✅","⚠️") -> ✅ | K11: 3700000 | L11: 4150000 | M11: 0.11 | N11: =FLOOR(B11*(1-M11),50000) -> 3650000 | O11: 0.05 | P11: =FLOOR(N11-(N11*O11),5000) -> 3465000 | Q11: =(P11-N11)/N11 -> -0.050684932
A12: Deluxe Suite | B12: ='7. Rate Strategy'!K$28 -> 5161200 | C12: =B12-(B12*10%) -> 4645080 | D12: =B12*(1-$D$2) -> 4335408 | E12: =C12*(1-$D$2) -> 3901867.2 | F12: 0.11 | G12: =MROUND(B12*(1-F12),50000) -> 4600000 | H12: =G12*(1+F12) -> 5106000 | I12: =(B12-H12)/B12 -> 0.010695187 | J12: =IF(I12<=0.03,"✅","⚠️") -> ✅ | K12: 4800000 | L12: 5100000 | M12: 0.11 | N12: =FLOOR(B12*(1-M12),50000) -> 4550000 | O12: 0.05 | P12: =FLOOR(N12-(N12*O12),5000) -> 4320000 | Q12: =(P12-N12)/N12 -> -0.050549451
A13: Premiere Suite | B13: ='7. Rate Strategy'!L$28 -> 5497800 | C13: =B13-(B13*10%) -> 4948020 | D13: =B13*(1-$D$2) -> 4618152 | E13: =C13*(1-$D$2) -> 4156336.8 | F13: 0.11 | G13: =MROUND(B13*(1-F13),50000) -> 4900000 | H13: =G13*(1+F13) -> 5439000 | I13: =(B13-H13)/B13 -> 0.010695187 | J13: =IF(I13<=0.03,"✅","⚠️") -> ✅ | K13: 5150000 | L13: 5550000 | M13: 0.11 | N13: =FLOOR(B13*(1-M13),50000) -> 4850000 | O13: 0.05 | P13: =FLOOR(N13-(N13*O13),5000) -> 4605000 | Q13: =(P13-N13)/N13 -> -0.050515464
A14: The Anvaya Suite No Pool | B14: ='7. Rate Strategy'!M$28 -> 6881600 | C14: =B14-(B14*10%) -> 6193440 | D14: =B14*(1-$D$2) -> 5780544 | E14: =C14*(1-$D$2) -> 5202489.6 | F14: 0.09 | G14: =MROUND(B14*(1-F14),50000) -> 6250000 | H14: =G14*(1+F14) -> 6812500 | I14: =(B14-H14)/B14 -> 0.010041269 | J14: =IF(I14<=0.03,"✅","⚠️") -> ✅ | K14: 6400000 | L14: 6800000 | M14: 0.09 | N14: =FLOOR(B14*(1-M14),50000) -> 6250000 | O14: 0.05 | P14: =FLOOR(N14-(N14*O14),5000) -> 5935000 | Q14: =(P14-N14)/N14 -> -0.0504
A15: The Anvaya Suite Whirl Pool | B15: ='7. Rate Strategy'!N$28 -> 7480000 | C15: =B15-(B15*10%) -> 6732000 | D15: =B15*(1-$D$2) -> 6283200 | E15: =C15*(1-$D$2) -> 5654880 | F15: 0.09 | G15: =MROUND(B15*(1-F15),50000) -> 6800000 | H15: =G15*(1+F15) -> 7412000 | I15: =(B15-H15)/B15 -> 0.0090909091 | J15: =IF(I15<=0.03,"✅","⚠️") -> ✅ | K15: 7000000 | L15: 7350000 | M15: 0.09 | N15: =FLOOR(B15*(1-M15),50000) -> 6800000 | O15: 0.05 | P15: =FLOOR(N15-(N15*O15),5000) -> 6460000 | Q15: =(P15-N15)/N15 -> -0.05
A16: Beach Front Private Suite | B16: ='7. Rate Strategy'!O$28 -> 7741800 | C16: =B16-(B16*10%) -> 6967620 | D16: =B16*(1-$D$2) -> 6503112 | E16: =C16*(1-$D$2) -> 5852800.8 | F16: 0.09 | G16: =MROUND(B16*(1-F16),50000) -> 7050000 | H16: =G16*(1+F16) -> 7684500 | I16: =(B16-H16)/B16 -> 0.0074013795 | J16: =IF(I16<=0.03,"✅","⚠️") -> ✅ | K16: 7200000 | L16: 7600000 | M16: 0.09 | N16: =FLOOR(B16*(1-M16),50000) -> 7000000 | O16: 0.05 | P16: =FLOOR(N16-(N16*O16),5000) -> 6650000 | Q16: =(P16-N16)/N16 -> -0.05
A17: Anvaya Residence | B17: ='7. Rate Strategy'!P$28 -> 11675600 | C17: =B17-(B17*10%) -> 10508040 | D17: =B17*(1-$D$2) -> 9807504 | E17: =C17*(1-$D$2) -> 8826753.6 | F17: 0.09 | G17: =MROUND(B17*(1-F17),50000) -> 10600000 | H17: =G17*(1+F17) -> 11554000 | I17: =(B17-H17)/B17 -> 0.010414882 | J17: =IF(I17<=0.03,"✅","⚠️") -> ✅ | K17: 10900000 | L17: 11000000 | M17: 0.09 | N17: =FLOOR(B17*(1-M17),50000) -> 10600000 | O17: 0.05 | P17: =FLOOR(N17-(N17*O17),5000) -> 10070000 | Q17: =(P17-N17)/N17 -> -0.05
A18: The Anvaya Suite with Pool | B18: ='7. Rate Strategy'!Q$28 -> 9948400 | C18: =B18-(B18*10%) -> 8953560 | D18: =B18*(1-$D$2) -> 8356656 | E18: =C18*(1-$D$2) -> 7520990.4 | F18: 0.11 | G18: =MROUND(B18*(1-F18),50000) -> 8850000 | H18: =G18*(1+F18) -> 9823500 | I18: =(B18-H18)/B18 -> 0.012554783 | J18: =IF(I18<=0.03,"✅","⚠️") -> ✅ | K18: 9300000 | L18: 9450000 | M18: 0.11 | N18: =FLOOR(B18*(1-M18),50000) -> 8850000 | O18: 0.05 | P18: =FLOOR(N18-(N18*O18),5000) -> 8405000 | Q18: =(P18-N18)/N18 -> -0.050282486
A19: The Anvaya Villa | B19: ='7. Rate Strategy'!R$28 -> 32425800 | C19: =B19-(B19*10%) -> 29183220 | D19: =B19*(1-$D$2) -> 27237672 | E19: =C19*(1-$D$2) -> 24513905 | F19: 0.11 | G19: =MROUND(B19*(1-F19),50000) -> 28850000 | H19: =G19*(1+F19) -> 32023500 | I19: =(B19-H19)/B19 -> 0.012406787 | J19: =IF(I19<=0.03,"✅","⚠️") -> ✅ | K19: 30200000 | L19: 29650000 | M19: 0.11 | N19: =FLOOR(B19*(1-M19),50000) -> 28850000 | O19: 0.05 | P19: =FLOOR(N19-(N19*O19),5000) -> 27405000 | Q19: =(P19-N19)/N19 -> -0.050086655
A27: Deluxe | B27: 1945000
A28: Deluxe Pool Access | B28: 2090000
A29: Premiere | B29: 2230000
A30: Premiere with Lagoon Access | B30: 2895000
A31: Deluxe Suite | B31: 4320000
A32: Premiere Suite | B32: 4605000
A33: Beach Front Private Suite | B33: 6650000

Sheet Sheet1

Sheet Owner
B5: Room Type | C5: Owner | D5: Relasi | E5: Owner | F5: Relasi | G5: Owner | H5: Relasi
B6: Deluxe Room | C6: 2000000 | D6: 2150000 | E6: =C6+200000 -> 2200000 | F6: =D6+200000 -> 2350000 | G6: =C6+700000 -> 2700000 | H6: =D6+700000 -> 2850000
B7: Deluxe Pool Access | C7: 2200000 | D7: 2350000 | E7: =C7+200000 -> 2400000 | F7: =D7+200000 -> 2550000 | G7: =C7+700000 -> 2900000 | H7: =D7+700000 -> 3050000
B8: Premiere Room | C8: 2300000 | D8: 2450000 | E8: =C8+200000 -> 2500000 | F8: =D8+200000 -> 2650000 | G8: =C8+700000 -> 3000000 | H8: =D8+700000 -> 3150000
B9: Premiere Lagoon Access | C9: 2950000 | D9: 3100000 | E9: =C9+200000 -> 3150000 | F9: =D9+200000 -> 3300000 | G9: =C9+700000 -> 3650000 | H9: =D9+700000 -> 3800000
B10: Family Premiere | C10: 3600000 | D10: 3750000 | E10: =C10+200000 -> 3800000 | F10: =D10+200000 -> 3950000 | G10: =C10+700000 -> 4300000 | H10: =D10+700000 -> 4450000
B11: Deluxe Suite | C11: 4800000 | D11: 4950000 | E11: =C11+200000 -> 5000000 | F11: =D11+200000 -> 5150000 | G11: =C11+700000 -> 5500000 | H11: =D11+700000 -> 5650000
B12: Premiere Suite | C12: 5100000 | D12: 5250000 | E12: =C12+200000 -> 5300000 | F12: =D12+200000 -> 5450000 | G12: =C12+700000 -> 5800000 | H12: =D12+700000 -> 5950000
B13: The Anvaya Suite No Pool | C13: 6450000 | D13: 6600000 | E13: =C13+200000 -> 6650000 | F13: =D13+200000 -> 6800000 | G13: =C13+700000 -> 7150000 | H13: =D13+700000 -> 7300000 | J13: =D13-$D$8 -> 4150000
B14: The Anvaya Suite Whirl Pool | C14: 7050000 | D14: 7200000 | E14: =C14+200000 -> 7250000 | F14: =D14+200000 -> 7400000 | G14: =C14+700000 -> 7750000 | H14: =D14+700000 -> 7900000 | J14: =D14-$D$8 -> 4750000
B15: Beach Front Private Suite | C15: 7300000 | D15: 7450000 | E15: =C15+200000 -> 7500000 | F15: =D15+200000 -> 7650000 | G15: =C15+700000 -> 8000000 | H15: =D15+700000 -> 8150000 | J15: =D15-$D$8 -> 5000000
B16: Anvaya Residence | C16: 10650000 | D16: 10800000 | E16: =C16+200000 -> 10850000 | F16: =D16+200000 -> 11000000 | G16: =C16+700000 -> 11350000 | H16: =D16+700000 -> 11500000 | J16: =D16-$D$8 -> 8350000
B17: The Anvaya Suite with Pool | C17: 9450000 | D17: 9600000 | E17: =C17+200000 -> 9650000 | F17: =D17+200000 -> 9800000 | G17: =C17+700000 -> 10150000 | H17: =D17+700000 -> 10300000 | J17: =D17-$D$8 -> 7150000
